Workbook
Name ConcUnit: [1]Concrete!$G$61
Name ConcUnitM: 'ICE Summary'!$G$267
Name ConcUnitM: #REF!
Name ICESummary: '[2]ICE Readable'!$K$6:$CZ$1003

Sheet FRONT
E6: ICE (Inventory of Carbon & Energy)
H8: All authors are listed alphabetically
F10: Current Authors: | H10: Circular Ecology*
F11: Affiliation:
G14: *corresponding author. Contact details: http://www.circularecology.com/contact.html
E15: Version Control
G16: Version: | H16: Educational
G17: Version Number: | H17: =Miscellaneous!E3 -> V4.1 - Oct 2025
E19: Users are required to Register for Permission to use the data for Non-educational Use. Registration is Free. Use the link below and fill in the form on the webpage. Educational use does not require registration, but it is encouraged to register to support the ICE Database.
E20: Is this version still valid? | G20: Check link below, to see if a newer version is available.
E21: Register for permission to use the data for non educational use and to check if this copy is up to date at: | G21: http://www.circularecology.com/embodied-energy-and-carbon-footprint-database.html
E23: Acknowledgments
E24: The authors are grateful to the below organisations, who have provided funding to update this version of the ICE database.
E25: Version | G25: Funded by:
E26: ICE V 4.0 & 4.1
H27: The latest version was funded by (appearing alphabetically):
H28: BCIS
H30: Circular Ecology
H33: Innovate UK
E36: Previous versions | G36: Please see the Acknowledgements page for details of previous funders.
E39: Authors
F42: Original Authors: | H42: Dr Craig Jones (Circular Ecology) | J42: Professor Geoffrey Hammond (University of Bath)
F44: Circular Ecology Current Authors: | H44: Jon Burrow (Oversight), Dr Craig Jones (QA), Joe Rouse (Project Manager), Charlie Zhu (Lead Analyst), Vaishnavi Unnad, Kit Wickens, Thomas Relph, Liam Seprini, Edwin Lowe.
F46: Previous Contributors: | H46: S. Vernon (PM), W. Garner (PM), J. Pearce, K. Dävé, B. Sodagar, M. Brill, A. Ranathungage.

Sheet Acknowledgements
E6: ICE Acknowledgements
E8: Authors
F11: Original Authors: | H11: Dr Craig Jones (Circular Ecology) | J11: Professor Geoffrey Hammond (University of Bath)
F13: Circular Ecology Current Authors: | H13: Jon Burrow (Oversight), Dr Craig Jones (QA), Joe Rouse (Project Manager, PM), Charlie Zhu (Lead Analyst), Vaishnavi Unnad, Kit Wickens, Thomas Relph, Liam Seprini, Edwin Lowe.
F15: Previous Contributors: | H15: S. Vernon (PM), W. Garner (PM), J. Pearce, K. Dävé, B. Sodagar, M. Brill, A. Ranathungage.
E19: Main Funders
E20: Version | G20: Funded by:
E21: ICE V 4.0 & 4.1
H22: The latest version was funded by (appearing alphabetically):
H24: BCIS
H26: Circular Ecology
H28: Innovate UK
E33: Contributors
E34: The authors are grateful to the below organisations, who have provided contributions to the ICE database.
E35: Version | G35: Contribution:
E36: ICE V 4.0
H38: Anglian Water | I38: Funded update data for Stainless Steel (no conflict of interest confirmed).
H40: xbim | I40: Circular Ecology were included as a partner in an Innovate UK funded project called Net Zero Flow, which part covered some of the research time of the background ICE Database.
H41: Morgan Sindall | I41: Circular Ecology were included as a sub-contractor in an Innovate UK funded project.
E44: Previous Acknowledgments
E45: The authors are grateful to the below organisations, who have previously provided funding to update the ICE database.
E46: Version | G46: Funded by:
E47: ICE V 3.0
H48: This version was funded by (appearing alphabetically):
H49: Environment Agency
H50: Heathrow Airport
H51: Rail Safety and Standards Board (RSSB)
E53: Previous versions | G53: The original ICE database was joint funded under the Carbon Vision Buildings program by the Engineering and Physical Sciences Research Council (EPSRC) and the Carbon Trust (before they became a private organisation), at the University of Bath.

Sheet Support ICE
E6: Support the ICE Database
F10: The ICE Database is a free resource. Circular Ecology are committed to keeping it freely available. However, the reality is that funds need to be raised to cover the maintenance and development of the database. Updates have been too infrequent, being in 2011, 2019 and more recently 2024. The embodied carbon landscape has changed immeasurably over that time, but the ICE database wasn’t updated enough to reflect this. We intend to change this and plan to bring all the old data up to date (various data is still from the 2011 version). We also hope to expand the database in the future. In order to help raise the funds for the maintenance and development of the ICE database, we have developed a supporter system. Contributions are optional for all users. This will recognise organisations that have made contributions to the ICE database, with several levels of support to suit different organisation sizes.
F17: Read more about the ICE Supporter System: | G17: https://circularecology.com/ice-supporter-system.html

Sheet TERMS OF USE
E6: ICE (Inventory of Carbon & Energy) Terms of Use
F7: REGISTRATION FOR PERMISSION TO USE THE DATA FOR NON-EDUCATIONAL USE
F8: Users are required to register for permission to use the data for non-educational applications. Registration is free and lasts until 30th June 2026. Once the initial registration has elapsed, users may re-register for free to cover a further 12 month period from the date of registration.
F9: Register for permission to use the ICE Database for non-educational use: | G9: https://circularecology.com/RegisterICE.html
F10: TERMS OF USE
F11: Users are required to adhere fully to the latest Terms of Use.
F12: Terms of Use: | G12: https://circularecology.com/terms-of-use.html
F13: Below are some of the terms of use for the Inventory of Carbon & Energy (ICE) database, which must be abided by (list not comprehensive, please check full terms of use at the above webpage): - Users are required to register for permission to use the data for non-educational uses. The registration is free and lasts up to 12 months. Once the period has elapsed, users can complete another free registration for the next 12 months. - The ICE database will only be valid for use for non-educational uses for a maximum of 3 years from the published date on the version number. After the 3 year period has elapsed, the data shall only be used for educational uses. This 3 year period is separate to the need to register for permission to use the data. It will encourage the database to be updated more frequency than it has in the past. - The ICE database must not be distributed nor uploaded to websites without the written permission of the authors. Instead the link to the download website should be referred to, which will always contain the most recent version of the database, http://www.circularecology.com/embodied-energy-and-carbon-footprint-database.html. - The data contained within the ICE database may be used on projects and within carbon tools - so long as registration is completed for permission to use, and so long as full reference to the database is provided and with a link to the download website to ensure readers can check for the most recent version of the ICE database. - The ICE database shall not be reproduced, copied, distributed, published, modified or in any way exploited, in whole or in part. - The disclaimer below shall be adhered to.
F14: DISCLAIMER
F15: Whilst efforts have been made to ensure the accuracy of the information contained in the Inventory of Carbon & Energy (ICE), the content is subject to change and the authors and their affiliated organisations cannot guarantee its accuracy or currency. The right is reserved to make changes to the information without notice. The information is consequently provided "as is" without any representation or warranty as to accuracy, currency, quality or fitness for purpose of any kind. You should independently verify any information contained in ICE before relying on it. The authors and their affiliated organisations do not make any representation nor give any warranty as to the ownership of the copyright of any material forming part of ICE and does not accept any liability for any direct, indirect, incidental or consequential losses arising from the infringement of any third party rights in relation to any material in ICE.

Sheet Contents - Navigation
E6: ICE (Inventory of Carbon & Energy) Contents
E7: Attention is drawn to these areas of the ICE database:
E8: Content | F8: Description
E9: Terms of use | F9: See terms of use worksheet.
E10: Glossary of terms | F10: A glossary of terms.
E11: Method | F11: Notes on the method and boundaries.
E12: Update Notes | F12: Notes on the key changes in this version of the ICE database.
E13: Data Quality Matrix | F13: A data quality matrix is applied to judge data quality.
E14: Main ICE Database Summary Table | F14: This summaries all of the data in the ICE database, on one worksheet. For more information on each material, see the material profiles.
E15: Material profiles | F15: A material profile is presented for each of the main materials, such as cement, concrete, steel, timber…etc. Here you will find a lot more data, such as statistics, references and further information.
E16: References | F16: For the references in this version of ICE, see the material profiles, there is a references section on each worksheet. For references from ICE V2.0, see the worksheet at the end of this workbook.
E17: Calculator for cement, mortar and concrete | F17: See separate excel file, distributed with the ICE database.
E18: Calculator for steel, to modify recycled content and recyclability assumptions | F18: See the material profile for steel.
E19: Calculator for precast concrete | F19: See material profile for concrete. Also see concrete on the main summary table.
E20: Data quality scores | F20: See the material profiles

Sheet >> Background >>
E6: Background Information >>>

Sheet Glossary
E6: ICE (Inventory of Carbon & Energy) Glossary
E7: Find below a glossary of terms.
E10: Term | F10: Description
E11: Allocation | F11: The sub-division of input and output flows between one or more product systems. Also applies to recycling methodology.
E12: Biogenic | F12: Derived from living organisms, but not from fossil origin, e.g. biomass is considered biogenic, but coal is not.
E13: (System) Boundaries | F13: A set of criteria that defines which processes are included within the (boundaries of) assessment.
E14: By-product | F14: Material that is a sub-derivative of the processing operations but is considered to have an economic value (e.g. facilitated by an application and market demand).
E15: Calorific Value (CV) of energy | F15: The energy content of a fuel (as may be released through combustion). It may be expressed as a Gross Calorific Value (GCV) or Net Calorific Value (NCV). The former is always larger than (or equal to) the latter. The difference is due to latent heat (energy) remaining in condensation (water vapour) after combustion. The difference is typically 5-12 per cent (examples, 11 per cent for natural gas, 5 per cent for coal).
E16: Capital carbon | F16: Capital carbon is a term that is mainly used for intrastate projects, to denote embodied carbon of the infrastructure construction project. It can be confusing when reading older background literature, who would use the term capital energy, as described below.
E17: Capital energy | F17: Energy required to manufacture capital inputs (e.g. ancillary infrastructure, such as buildings, machinery, tools). See also capital carbon.
E18: Carbon dioxide equivalent (CO2e) | F18: See Global Warming Potential (GWP).
E19: Carbon storage | F19: See carbon sequestration.
E20: Carbon sequestration | F20: The extraction of carbon from the atmosphere, for example from trees and plants.
E21: Co-product | F21: Material or product that is produced alongside the investigated product, i.e. co-production.
... E53: EOL | F53: End of life

Sheet Method and Update Notes
E7: ICE (Inventory of Carbon & Energy) V4.1
E8: Note on scope of this update: The ICE database version 4.1 contains updates to a small number of materials (bitumen and GGBS), but these materials have large changes in their embodied carbon and influence several important construction materials. The majority of material categories are unaffected by this update. Data for other materials is still presented from the previous versions of the ICE database (V4.0, V3.0 and V2.0) for completeness. Users should consider that data from ICE V3.0 was published in 2019, and data from ICE V2.0 was published in 2011.
E11: ICE (Inventory of Carbon & Energy) Background
E12: The Inventory of Carbon and Energy (ICE) was initially created by Craig Jones, under the supervision of Professor Geoffrey Hammond, whilst working as a researcher at the University of Bath. Work started in 2004. Versions were released periodically over the period 2005-2011. The original research project was funded by the Engineering and Physical Sciences Research Council (EPSRC) and the Carbon Trust (before they became a private company). The project involved assessing the implications of embodied energy and carbon in construction for new UK buildings. The Inventory was created to provide a freely available, robust and reliable source of data for the materials used in the construction process for the project partners. It soon became obvious that this data would be of interest to a wide range of users beyond the project partners. Subsequently, in 2006 the ICE database was made available for download from the authors website. Since then it has been downloaded by over 50,000 professional users from industry, academia, government departments and agencies around the world.
E16: ICE (Inventory of Carbon & Energy) Method
E17: The ICE database is essentially a meta-database. It is based upon a large literature review, where data is collected and compiled on the embodied carbon of construction materials. There is a background database, which stores embodied carbon datapoints collected from the literature. That version is not publicly available. That version of the database stores a lot of meta data, which logs information for each datapoint, such as the method, boundaries, age, level of peer review, ...etc. It also categorises each datapoint according to main and sub-material categories, e.g. aluminium > cast aluminium. This database gives us a good basis for analysing the data.
E18: This available version of the ICE database is compiled from the background database. The data collection for this updated version of ICE has now been able to focus on collecting data with a more consistent method and boundaries than was previously available. The latest background ICE database has been modified to accommodate new formats for collected data. This was needed due to the changes seen in the carbon footprint landscape since 2019, which is when the previous version of the ICE database was released.
E19: Notably, there has been a large increase in the availability of Environmental Product Declarations (EPDs) and improved accessibility of EPDs via EPD libraries. These EPDs, undertaken to the EU wide standard EN 15804, have offered a considerably larger and more consistent dataset than was previously available. In fact, EN 15804 EPDs have been be the main source of data for this version of the ICE database.
E21: ICE (Inventory of Carbon & Energy) Method Diagram
E22: A diagram showing the approach to developing the ICE database is shown below. Due to the increased methodological consistency that modern data brings, it was possible to introduce the quality filter earlier in the data collection process, before data is extracted from literature resources.
E29: ICE (Inventory of Carbon & Energy) Scope and Method
E30: The ICE database retains a cradle to (factory) gate scope. This is known as Module A1 to A3 in the EU wide standards EN 15978 and EN 15804, on sustainability assessment of construction works. The ICE database is a meta database, e.g. a database storing metadata about datapoints. As a meta database, the background ICE database contains datapoints with a wide range of method and boundaries. These are logged as meta data in the background database. The boundaries and methodological consistency of the data collected is much improved over previous versions of ICE, due mainly to an increase in carbon footprint standards. There is also considerable overlap between many of the main footprinting standards in regards to method and boundaries.
... E35: Statistics on the average carbon footprint calculation method of all data collected from the previous version (ICE V3.0) of the ICE database are presented below for context. Updated figures for ICE V4.0 onwards are to be reviewed in due course.
E36: Method Stated | G36: Fraction of All Data Collected | I36: Totals will not add to 100%. This is because some studies claim adherence to multiple footprint standards.
E37: EN 15804 Data | G37: 0.89057239
E38: ISO 14067 | G38: 0.043771044
E39: ISO 14044 Only | G39: 0.042648709
E40: No standardised method claimed | G40: 0.057800224
E42: ICE (Inventory of Carbon & Energy) Update Notes
E44: V4.1
E45: The ICE database version 4.1 contains updates to a small number of materials (bitumen and GGBS), but these materials have large changes in their embodied carbon and influence several important construction materials. The majority of material categories are unaffected by this update. A summary of the main changes are logged here.
E47: General update notes
E49: Description | G49: Update Notes
E50: Material Category Updates | G50: This update is in response to industry LCA methodological changes to bitumen and GGBS, resulting in significant changes to their emissions factors. The following material categories have been updated accordingly to reflect those changes: Asphalt, Bitumen, Cement & Mortar, Concrete.
E52: V4.0
E53: The ICE database version 4.0 contained a number of important updates over the previous version, V3.0 (2019) and V2.0 (2011). A summary of the main changes is logged here.
E55: General update notes
E57: Description | G57: Update Notes
E58: Background database updated | G58: The background database, which is not publicly accessible, has been updated. Noting ICE V3.0 data (where no updates have been made) have been kept in the previous format. This is because the target data is now EPDs (EN 15804), which are available in bulk volumes from EPD libraries utilising APIs.
E59: Updated Data Quality Indictors (V2.0) introduced | G59: Data quality indicators have been updated to V2.0 for all newly added material profiles. ICE V3.0 data will still utilise the original DQI (V1.0) until the data is next updated. See the data quality matrix worksheet.
E60: New material profiles added | G60: New material profiles have been added for Ceramic, Insulation, Paint, Plaster, Rubber and Vinyl in ICE V4.0. These profiles now provide more data, more statistics, more charts and more links to the references used for each material.
E61: Limited updates on carbon data for Cement, Concrete, Steel, and Timber | G61: Updated carbon data is available for Cement, Concrete, Steel, and Timber (CLT and Glulam only), based on limited updated to background factors and newly available data sources. See material profiles for further information.
E62: Updated ICE Machine Readable version | G62: The ICE Machine Readable version has been updated in alignment to the ICE V4.0 updates made in this database
E63: Updates to the Cement, mortar and concrete model | G63: See the separate excel file, which has been updated following updates to the core cement and concrete carbon factors. The tool allows users to model the embodied carbon of specific cement, mortar and concrete mixtures, including precast concrete.
E64: ICE V2.0 "Miscellaneous" GWP data removed | G64: GWP data references from ICE V2.0 "Miscellaneous" materials has been removed from ICE V4.0 due to the age of the source data, as this is now deemed too out of date for inclusion
E66: ICE (Inventory of Carbon & Energy) Material Profiles Last Reviewed Notes
E68: Material Profile | G68: Date Last Updated | I68: Notes
E69: Aggregates and Sand | G69: May 2019
E70: Aluminium | G70: May 2019
E71: Asphalt | G71: Oct 2025 | I71: Updates to incorporate the significant increase of the embodied carbon of Bitumen in Eurobitume's latest study (2025). Production emissions (A3) also updated with newer MPA sector average data.
E72: Bitumen | G72: Oct 2025 | I72: Updates have been implemented following the increase of Bitumen embodied carbon reported in Eurobitume's latest study (2025)
E73: Brass | G73: ICE V2 - 2011 | I73: Click here for notice regarding the expiration of ICE V2 data
E74: Bricks | G74: Dec 2024 | I74: Data for mortar has been updated for brick wall compositions. The UK Brick sector EPD for bricks is overdue an update
E75: Bronze | G75: ICE V2 - 2011 | I75: Click here for notice regarding the expiration of ICE V2 data
E76: Carpet | G76: ICE V2 - 2011 | I76: Click here for notice regarding the expiration of ICE V2 data
E77: Cement and Mortar | G77: Oct 2025 | I77: Update to the GGBS embodied carbon, to a newer factor using economic allocation, more aligned with EN15804.
E78: Ceramics | G78: Dec 2024
E79: Clay | G79: Dec 2024
E80: Concrete | G80: Oct 2025 | I80: Update to the GGBS embodied carbon, to a newer factor using economic allocation, more aligned with EN15804.
E81: Copper | G81: ICE V2 - 2011 | I81: Click here for notice regarding the expiration of ICE V2 data
E82: Glass | G82: May 2019
E83: Insulation | G83: Dec 2024 | I83: Update to mineral based insulation types only. Natural insulation types still require an update.
E84: Iron | G84: ICE V2 - 2011 | I84: Click here for notice regarding the expiration of ICE V2 data
E85: Lead | G85: ICE V2 - 2011 | I85: Click here for notice regarding the expiration of ICE V2 data
E86: Lime | G86: ICE V2 - 2011 | I86: Click here for notice regarding the expiration of ICE V2 data
E87: Linoleum | G87: ICE V2 - 2011 | I87: Click here for notice regarding the expiration of ICE V2 data
E88: Miscellaneous | G88: Majority of data removed | I88: Most of the data in the Miscellaneous category has been removed. It was data from ICE V2.0 2011 and was some of the oldest data in the database, it has therefore been removed.
E89: Paint | G89: Waterborne - Dec 2024 Solventborne - ICE V2 2011
E90: Paper | G90: ICE V2 - 2011 | I90: Click here for notice regarding the expiration of ICE V2 data
E91: Plaster | G91: Dec 2024
E92: Plastics | G92: ICE V2 - 2011 | I92: There are challenges to updating the data for plastics, but it is high on the priority list. Click here for notice regarding the expiration of ICE V2 data
E93: Rubber | G93: Dec 2024
E94: Sealants and Adhesives | G94: ICE V2 - 2011 | I94: Click here for notice regarding the expiration of ICE V2 data
E95: Soil | G95: ICE V2 - 2011 | I95: Click here for notice regarding the expiration of ICE V2 data
E96: Steel | G96: Dec 2024
E97: Stone | G97: ICE V2 - 2011 | I97: Analysis has been undertaken on stone. However, we have discovered large methodological differences from the EPDs collected on Stone. This will need further investigation to resolve. Click here for notice regarding the expiration of ICE V2 data
E98: Timber | G98: Glulam and CLT - Dec 2024 All other timber - May 2019 | I98: Timber is high on the list to update, although it is a larger challenge for materials that contain biogenic carbon.
E99: Tin | G99: ICE V2 - 2011 | I99: Click here for notice regarding the expiration of ICE V2 data
E100: Titanium | G100: ICE V2 - 2011 | I100: Click here for notice regarding the expiration of ICE V2 data
E101: Vinyl | G101: Dec 2024
E102: Zinc | G102: ICE V2 - 2011 | I102: Click here for notice regarding the expiration of ICE V2 data

Sheet Data Quality Matrix
E6: Data Quality Indicator (DQI) Matrix
E10: DQI Version: | F10: V2.0 | G10: Date DQI matrix last updated: | I10: 45631
E11: Version applied to: | F11: ICE V4.0 material profiles - Ceramics, Insulation, Paint, Plaster, Rubber, Stainless Steel, Vinyl
E12: Is this version still valid? | F12: Check link below, to see if a newer version is available.
E13: Check if this copy is up to date at: | F13: http://www.circularecology.com/embodied-energy-and-carbon-footprint-database.html
E16: Overview to DQI Scoring Framework
E17: The updated DQI scoring framework (V2.0) considers two separate DQI grouping to assess the quality of the material profile data: - Core DQIs for individual data points (50% weighting) - e.g., temporal correlation, geographical compatibility, method compatibility etc. - Calculated Average DQIs for material subcategories (50% weighting) - e.g., population and precision, analytical review approach etc. Further information on each of these DQI groupings can be found below.
E21: Core DQIs for individual data points e.g. EPDs
E22: These criteria are applied to all datapoints collected. The Core DQI scoring framework closely reflects the original DQI (V1.0) framework, noting some small modifications to the scoring allocations for each criteria, except for Assurance which has remained the same.
E25: Score | F25: 5 (Best) | G25: 4 | H25: 3 | I25: 2 | J25: 1 (Worst) | K25: Notes
E26: Method compatibility | F26: Industry-specific prescriptive standards (e.g. EN 15804, ISO 21930) | G26: Industry non-specific prescriptive standards (e.g. ISO 14067, PAS 2050, GHGP Product) - EPDs without stated methods will be awarded this score by default. | H26: Other standardised method | I26: Recognised method, but not standardised (e.g. ISO 14040/44 only) | J26: No declared method (e.g. missing data or research paper without defined method)
E27: Assurance | F27: External panel review (e.g. ISO 14040 panel review with 3 or more people) | G27: 2 External reviewers (e.g. academic papers) | H27: 1 External reviewer (EPDs score this by default) | I27: Internal review | J27: No declared review process
E28: Temporal correlation - Age of study | F28: <= 3 years old | G28: 4 - 6 years old | H28: 7 - 9 years old | I28: >= 10 years old | J28: No declared year
E29: Geographical compatibility | F29: UK | G29: European data or World Average | H29: North American | I29: All other countries and regions, or no declared geography | J29: - | K29: Note: Ideal boundaries of ICE DB are UK. This DQI is not a statement on quality of LCA data from various regions around the world.
E30: Transparency | F30: Full calculation model and detailed report available (very rare) | G30: Detailed report (e.g. full LCA report, documenting assumptions in detail), but no calculation model. Or transparent calculation model, but not detailed report. | H30: Summary report covering an overview of method incl. key data (EPDs will be awarded this score) | I30: - | J30: Limited details on method, or key information missing
E32: Category Average DQIs on material sub-categories:
E33: These criteria are not applicable to the individual datapoints collected in the background ICE database. They are applied to material categories and sub-categories that have used the average of all data collected. For example, if the data for a material was the average of '50' datapoints collected, the below additional data quality indicators will be applied. This is included so that, where statistical average data is used, the sample size, precision, and analytical approach can be considered as a part of the data quality score, e.g. larger datasets are more beneficial, and in theory better, and so this allows it to be reflected in the DQI score. For datapoints that were selected based upon a specific reference, these data quality indicators are not applied.
E36: Population & Precision DQI (Max 5 Points)
E37: The Population & Precision DQI is a quality assessment of material sub-categories, and takes into account the number of individual datapoints contributing to the statistical average, as well as the mean absolute percentage deviation (MAPD) which describes variance of the sample. MAPD is calculated as the average of absolute percentage deviations for all datapoints' GWP values against the mean GWP value for that material sub-category. This value represents the average absolute deviation (positive and negative deviations) of GWP from the mean for all datapoints within a given material sub-category. These two characteristics are represented in a matrix format to allow for flexibility of datasets to be fairly represented within this DQI scoring e.g. a large dataset with a very high MAPD value, may not be inherently preferable to a smaller dataset with a lower MAPD value. The final DQI score (max 5 points) is assigned based on the combination of the two characteristics, e.g. a material sub-category whose sample size is 50, and MAPD is 25%, would score 2.5 points.
E40: Sample Size / MAPD | F40: > 40% | G40: 40% ≥ x > 30% | H40: 30% ≥ x > 20% | I40: 20% ≥ x > 10% | J40: ≤ 10%
E41: 1 - 10 | F41: 0.5 | G41: 1 | H41: 1.5 | I41: 2 | J41: 2
E42: 11 - 25 | F42: 1 | G42: 1.5 | H42: 2 | I42: 2.5 | J42: 3
E43: 26 - 50 | F43: 1.5 | G43: 2 | H43: 2.5 | I43: 3 | J43: 3.5
E44: 51 - 100 | F44: 2 | G44: 2.5 | H44: 3 | I44: 3.5 | J44: 4.5
E45: 101+ | F45: 2 | G45: 3 | H45: 3.5 | I45: 4 | J45: 5
E47: Analytical DQI (Max 5 Points)
E48: When compiling individual datapoints into material sub-categories, different analytical and review processes were undertaken to ensure, as much as possible, the accuracy and suitability of data utilised within those sub-categories. These processes include, but are not limited to, inspecting anomalous results to verify that GWP and other key metric values are correct as stated in the original data source, or sense checking whether the cut-off methods and assessment boundaries are consistent to allow for fair comparisons between datapoints. The scoring allocations outlined below aim to reflect the analytical approach taken, based on available resource, and the status of any noted concerns outstanding at the end of this process. The Analytical DQI assigns a score (max 5 points) to the material sub-category based on these findings.
E51: Description | I51: Score | J51: Notes
E52: Every datapoint in this category has been checked, and all targeted analysis (e.g. via statistical methods, reference values, visual inspection) has been closed out satisfactorily | I52: 5 | J52: -
E53: Targeted analysis (e.g. via statistical methods, reference values, visual inspection) has been closed out satisfactorily, with minor or no concerns noted | I53: 4 | J53: Example of minor concern includes: identification of minor individual outliers within the dataset
E54: Targeted analysis (e.g. via statistical methods, reference values, visual inspection) has been closed out satisfactorily, with moderate concerns noted | I54: 3 | J54: Example of moderate concern includes: possible overlap of given datapoint(s) across multiple material sub-categories
E55: Targeted analysis (e.g. via statistical methods, reference values, visual inspection) has been closed out satisfactorily, with larger concerns noted | I55: 2 | J55: Example of larger concern includes: possible distortion of a dataset due to modelling inconsistencies such as unaccounted recycled content which can significantly affect average values for key metrics
E56: Data has been categorised, automatic capping applied, but no analysis or review of individual datapoints has taken place; or targeted analysis (e.g. via statistical methods, reference values, visual inspection) has been attempted but major concerns are noted | I56: 1 | J56: Example includes: a published dataset that otherwise does not satisfy the minimum required level of confidence to achieve the above higher scores.
E60: [PREVIOUS] Data Quality Indicator (DQI) Matrix
E65: DQI Version: | F65: V1.0 | G65: Date DQI matrix last updated: | I65: 43615
E66: Version applied to: | F66: All ICE V3.0 material profiles and ICE V4.0 / V4.1 - Cement_and_Mortar, Clay_Bricks, Concrete, Steel (excl. Stainless Steel), Timber
E68: Introduction
E69: Data quality indicators are used in this version of the ICE database, to assess the data quality of each datapoint collected. In order to do this, a data quality matrix is used and is applied to all of the data collected.
E72: Data quality for individual data, e.g. EPDs
E73: These criteria are applied to all datapoints collected.
E76: Score | F76: 5 (Best) | G76: 4 | H76: 3 | I76: 2 | J76: 1 (Worst) | K76: Notes
E77: Method compatibility | F77: EN 15804 | G77: ISO 14067 or ISO 21930 or PAS 2050 or GHG Protocol for Products (not including any of the other GHG Protocol standards) | H77: Other standardised method recognised nationally or internationally | I77: Recognised method, but not standardised, e.g. ISO 14040/44 only, which is not a prescriptive method. | J77: No recognised or standardised method
E78: Assurance | F78: External panel review (e.g. ISO 14040 panel review with 3 or more people) | G78: 2 External reviewers (e.g. academic papers often have two reviewer) | H78: 1 external reviewer (e.g. EPDs) | I78: Internal review | J78: No review process stated
E79: Temporal correlation - Age of study | F79: <= 5 years | G79: <= 6 years | H79: <= 7 years | I79: < 10 years | J79: >= 10 years
E80: Geographical compatibility | F80: Data from UK | G80: European Data or World Average | H80: North American | I80: - | J80: All other countries and regions | K80: Note: Ideal boundaries of ICE DB are UK. This DQI is not a statement on quality of LCA data from various regions around the world.
E81: Transparency | F81: Full calculation model and detailed report available (very rare) | G81: Detailed report (e.g. full LCA report, documenting assumptions in detail), but no calculation model. Or transparent calculation model, but no detailed report. | H81: - | I81: Summary report covering an overview of method incl. key data (most EPDs will be this rating) | J81: Limited details on method, or key information missing
E84: Data quality on material sub-categories:
E85: These criteria are not applicable to the individual datapoints collected in the background ICE database. They are applied to material categories and sub-categories that have used the average of all data collected. For example, if the data for a material was the average of '50' datapoints collected, the below additional data quality indicator will be applied. This is so that where statistical average data is used, the sample size can be considered as a part of the data quality score. Larger datasets should be more accurate and this allows it to be reflected in the DQI score. For datapoints that were selected based upon a specific reference, this data quality indicator is not applied.
E88: Score | F88: 10 (Best) | G88: 9 | H88: 8 | I88: 7 | J88: 6 | K88: 5 | L88: 4 | M88: 3 | N88: 2 | O88: 1 (Worst)
E89: Sample size | F89: >=250 data points | G89: >=150 data points | H89: >=100 datapoints | I89: >=75 data points | J89: >=50 data points | K89: >=25 data points | L89: >=10 data points | M89: >=5 data points | N89: <5data points | O89: 1 data point

Sheet >> ICE DB Summary >>
E6: Main ICE Database Summary Table >>>

Sheet ICE Summary
F6: INVENTORY OF CARBON & ENERGY (ICE) SUMMARY - V 4.1 | T6: Lookup Name In ICE DB [Hide these]
F10: ICE DB Version: | G10: =Miscellaneous!$E$3 -> V4.1 - Oct 2025 | I10: Check this link to see when the material profiles below were last updated
F11: Is this version still valid? | G11: Check link below, to see if a newer version is available. | J11: This version has expired. Please download a new version using the link below.
F12: Check if this copy is up to date at: | G12: http://www.circularecology.com/embodied-energy-and-carbon-footprint-database.html
F14: Introduction
F15: Materials covered in ICE V4.1 | G15: The updated ICE database, to ICE V4.1, has expanded on the data updates for the main construction materials provided in ICE V4.0 and ICE V3.0. This is following a pareto principle, also known as the 80:20 rule, to update the database within the level of resource that was available. Those materials should cover the majority of embodied carbon for many construction projects. It is appreciated that there are materials that haven't been updated, but which are still an important part of a materials inventory in construction, particularly on some projects. In order for users to be able to model the embodied carbon of these materials, the data from the previous versions of ICE, V3.0 (published in 2019) and V2.0 (published in 2011), have been copied to this summary.
F17: Aggregates and Sand
F19: Materials | G19: Embodied Carbon - kgCO2e/kg | J19: Comments | K19: DQI Score | L19: DQI Version | T19: Name Exactly as in ICE DB
F20: general UK, mixture of land won, marine, secondary and recycled, bulk, loose | G20: 0.0074696455 | J20: This is an estimate of a market average aggregate. It models a mixture of 64.2% land won, 27.5% recycled and secondary, and 8.3% marine aggregates. Consumption statistics have been taken from a report, by British Marine Aggregates Producer Association, a member of the Mineral Products Association (MPA). [Tenth sustainable development report for the British marine aggregate industry, Dec 2016]. These results are sensitive to the embodied carbon of secondary aggregates, which is a material where data would benefit from improvement. If you know the specific type of aggregates you will use, then it is recommended to use a more specific category of aggregates. | K20: 0.57223891 | L20: V1.0 | T20: Aggregates and sand, general UK, mixture of land won, marine, secondary and recycled, bulk, loose
F21: general, virgin mixture of land won and marine, bulk, loose | G21: 0.0049277889 | J21: Excludes recycled and secondary aggregate. This has been modelled with 89% land won and 11% marine won aggregate. Consumption statistics have been taken from a report, by British Marine Aggregates Producer Association, a member of the Mineral Products Association (MPA). [Tenth sustainable development report for the British marine aggregate industry, Dec 2016]. The consumption of marine aggregate was taken to be the total marine aggregate production. Of the total, 68% are consumed in the GB market, 11% are sent to the European market and 21% used as beach replenishment or fill. | K21: 0.56684369 | L21: V1.0 | T21: Aggregates and sand, general, virgin mixture of land won and marine, bulk, loose
F22: from virgin land won resources, bulk, loose | G22: 0.0043575012 | J22: Based upon the statistical average of all data collected for virgin aggregates in the ICE Database. | K22: 0.64818763 | L22: V1.0 | T22: Aggregates and sand, from virgin land won resources, bulk, loose
F23: from virgin marine resources, bulk, loose | G23: 0.0090375 | J23: Consumption statistics have been taken from a report, by British Marine Aggregates Producer Association, a member of the Mineral Products Association (MPA). [Tenth sustainable development report for the British marine aggregate industry, Dec 2016]. The consumption of marine aggregate was taken to be the total marine aggregate production. The data has been modelled with the average energy consumption for extracting marine aggregates in the UK. The original data did not use all scope emissions factors, instead just scope 1 and 2. The data was therefore used to estimate the full scope 1, 2 and 3 emissions. The impacts to produce aggregates has a particularly large variation in embodied impacts. | K23: 0.34285714 | L23: V1.0 | T23: Aggregates and sand, from virgin marine resources, bulk, loose
F24: from recycled resources, no heat treatment, bulk, loose | G24: 0.0060529786 | J24: Based upon the statistical average of all data collected for recycled aggregates with no heat treatment in the ICE Database. Recycled aggregates include aggregates from construction and demolition waste. It does not cover secondary aggregates, such as blast furnace slag, or bottom ash (see separate category for these). Data for recycled aggregates is more difficult to obtain than for virgin aggregates. There is also a large range in results for recycled aggregates, adding uncertainty into the results. | K24: 0.56122449 | L24: V1.0 | T24: Aggregates and sand, from recycled resources, no heat treatment, bulk, loose
F25: from recycled resources, with heat treatment, bulk, loose | G25: 0.11877167 | J25: Based upon the statistical average of all data collected for recycled aggregates that have been through heat treatment in the ICE Database. Recycled aggregates include aggregates from construction and demolition waste. It does not cover secondary aggregates such as blast furnace slag, or bottom ash (see separate category for these). Data for recycled aggregates is more difficult to obtain than for virgin aggregates. There is also a large range in results for recycled aggregates, adding uncertainty into the results. | K25: 0.44761905 | L25: V1.0 | T25: Aggregates and sand, from recycled resources, with heat treatment, bulk, loose
F26: expanded clay, bulk, loose | G26: 0.3350915 | J26: Based upon the statistical average of all data collected for expanded clay aggregates in the ICE Database. | K26: 0.48571429 | L26: V1.0 | T26: Aggregates and sand, expanded clay, bulk, loose
F27: expanded foamed glass, bulk, loose | G27: 0.273532 | J27: Based upon the statistical average of all data collected for expanded foamed glass aggregates in the ICE Database. | K27: 0.45714286 | L27: V1.0 | T27: Aggregates, expanded foamed glass, bulk, loose
F28: from secondary resources, bulk, loose | G28: 0.063323 | J28: Including blast furnace slag, bottom ashes, road planings, mining spoil and other aggregates manufactured from secondary resources. Limited data on the embodied carbon of secondary aggregates was available. There was also limited data on the consumption mixture of secondary aggregates in the UK. The mixture was estimated based upon two sub-regional reports for the Aggregate Minerals survey2015 (AM15). See the references [Table 6.1 in Ref: North East Aggregates Working Party, Annual Aggregates Monitoring report 2015, Dec 2016 ] and [Table 10B in South East Aggregates Working Party, South East Aggregates Monitoring report 2014 & 2015, Sept 2016]. The data would benefit from covering a wider share of the UK secondary aggregate market, | K28: 0.51428571 | L28: V1.0 | T28: Aggregates and sand, from secondary resources, bulk, loose
F29: mixture of recycled and secondary resources, bulk, loose | G29: 0.014181254 | J29: Data on recycled and (particularly) secondary aggregates would benefit from improvement. Limited data on the embodied carbon of secondary aggregates was available. There was also limited data on the consumption mixture of recycled and secondary aggregates in the UK. The mixture was modelled with 33% secondary and 67% recycled aggregates. [Estimated from Ref: Aggregates, cement and ready-mix concrete market investigation, Working paper on market definition for aggregates, cement and RMX. ND67. Available from: https://assets.publishing.service.gov.uk/media/5329dfb440f0b60a730002cf/market_definition_housestyled.pdf] | K29: 0.59042185 | L29: V1.0 | T29: Aggregates and sand, mixture of recycled and secondary resources, bulk, loose
F31: Aluminium
F33: The data for aluminium are based upon detailed LCAs from the World Aluminium Institute, http://www.world-aluminium.org/. Their LCA model is used as the basis for LCA's from the European Aluminium Institute, https://www.european-aluminium.eu/, as well as the North American Aluminium Association, https://www.aluminum.org/. The source LCAs reports generally don't combine the data for ingot with the semi-fabrication processes, such as casting, sheet production or extrusion. The below data has combined the data in the LCA's, to produce the values below. All data is modelled at the world average recycled material input, taken from the "Global Aluminium Flow Model 2016", available from http://www.world-aluminium.org/publications/. This approach of using world averages for all regions is to avoid market distortions. Should any users require data for other recycled contents, there is further information on the material profile for aluminium.
F35: European consumption - Includes European production and imports - At world average recycled content
F37: Materials | G37: Embodied Carbon - kgCO2e/kg | J37: Comments | K37: DQI Score | L37: DQI Version | T37: Name Exactly as in ICE DB
F38: Aluminium General, European Mix, Inc Imports | G38: 6.6687175 | J38: This data has been derived from the world aluminium LCA's. They have produced LCA reports for Europe, North America and worldwide aluminium. Modelled at worldwide average scrap input of 31%, to avoid market distortions. Modelled with 25.6% extrusions, 55.7% rolled and 18.7% castings. Based upon European production and the import of aluminium consumed in Europe. Module D = -3.13 kg CO2e per unit. EOL recovery rate of 95%, based upon DU Telft study of European construction sector. With a 2% material loss yield on the scrap recovered. | K38: 0.64 | L38: V1.0 | T38: Aluminium General, European Mix, Inc Imports
F39: Aluminium sheet, European Mix, Inc Imports | G39: 6.581176 | J39: This data has been derived from the world aluminium LCA's. They have produced LCA reports for Europe, North America and worldwide aluminium. Modelled at worldwide average scrap input of 31%, to avoid market distortions. Based upon European production and the import of aluminium consumed in Europe. Module D = -3.09 kg CO2e per unit. EOL recovery rate of 95%, based upon DU Telft study of European construction sector. With a 2% material loss yield on the scrap recovered. | K39: 0.64 | L39: V1.0 | T39: Aluminium sheet, European Mix, Inc Imports
F40: Aluminium foil, European Mix, Inc Imports | G40: 7.468978 | J40: This data has been derived from the world aluminium LCA's. They have produced LCA reports for Europe, North America and worldwide aluminium. Modelled at worldwide average scrap input of 31%, to avoid market distortions. Based upon European production and the import of aluminium consumed in Europe. Module D = -3.54 kg CO2e per unit. EOL recovery rate of 95%, based upon DU Telft study of European construction sector. With a 2% material loss yield on the scrap recovered. | K40: 0.64 | L40: V1.0 | T40: Aluminium foil, European Mix, Inc Imports
F41: Aluminium extruded profile, European Mix, Inc Imports | G41: 6.825242 | J41: This data has been derived from the world aluminium LCA's. They have produced LCA reports for Europe, North America and worldwide aluminium. Modelled at worldwide average scrap input of 31%, to avoid market distortions. Based upon European production and the import of aluminium consumed in Europe. Module D = -3.21 kg CO2e per unit. EOL recovery rate of 95%, based upon DU Telft study of European construction sector. With a 2% material loss yield on the scrap recovered. | K41: 0.64 | L41: V1.0 | T41: Aluminium extruded profile, European Mix, Inc Imports
F42: Aluminium, cast, European Mix, Inc Imports | G42: 6.7151901 | J42: This data has been derived from the world aluminium LCA's. They have produced LCA reports for Europe, North America and worldwide aluminium. Modelled at worldwide average scrap input of 31%, to avoid market distortions. Based upon European production and the import of aluminium consumed in Europe. Module D = -3.12 kg CO2e per unit. EOL recovery rate of 83%, based upon worldwide global aluminium flow model and for the building and construction sector. With a 2% material loss yield on the scrap recovered. | K42: 0.64 | L42: V1.0 | T42: Aluminium, cast, European Mix, Inc Imports
F44: Worldwide production - At world average recycled content
F46: Materials | G46: Embodied Carbon - kgCO2e/kg | J46: Comments | K46: DQI Score | L46: DQI Version | T46: Name Exactly as in ICE DB
F47: Aluminium General, Worldwide | G47: 13.05554 | J47: This data has been derived from the world aluminium LCA's. They have produced LCA reports for Europe, North America and worldwide aluminium. Modelled at worldwide average scrap input of 31%, to avoid market distortions. Modelled with 25.6% extrusions, 55.7% rolled and 18.7% castings. Module D = -8.69 kg CO2e per unit. EOL recovery rate of 83%, based upon worldwide global aluminium flow model and for the building and construction sector. With a 2% material loss yield on the scrap recovered. | K47: 0.64 | L47: V1.0 | T47: Aluminium General, Worldwide
F48: Aluminium sheet, Worldwide | G48: 12.955895 | J48: This data has been derived from the world aluminium LCA's. They have produced LCA reports for Europe, North America and worldwide aluminium. Modelled at worldwide average scrap input of 31%, to avoid market distortions. Module D = -8.69 kg CO2e per unit. EOL recovery rate of 83%, based upon worldwide global aluminium flow model and for the building and construction sector. With a 2% material loss yield on the scrap recovered. | K48: 0.64 | L48: V1.0 | T48: Aluminium sheet, Worldwide
F49: Aluminium foil, Worldwide | G49: 13.766895 | J49: This data has been derived from the world aluminium LCA's. They have produced LCA reports for Europe, North America and worldwide aluminium. Modelled at worldwide average scrap input of 31%, to avoid market distortions. Module D = -8.69 kg CO2e per unit. EOL recovery rate of 83%, based upon worldwide global aluminium flow model and for the building and construction sector. With a 2% material loss yield on the scrap recovered. | K49: 0.64 | L49: V1.0 | T49: Aluminium foil, Worldwide
F50: Aluminium extruded profile, Worldwide | G50: 13.176395 | J50: This data has been derived from the world aluminium LCA's. They have produced LCA reports for Europe, North America and worldwide aluminium. Modelled at worldwide average scrap input of 31%, to avoid market distortions. Module D = -8.69 kg CO2e per unit. EOL recovery rate of 83%, based upon worldwide global aluminium flow model and for the building and construction sector. With a 2% material loss yield on the scrap recovered. | K50: 0.64 | L50: V1.0 | T50: Aluminium extruded profile, Worldwide
F51: Aluminium cast, Worldwide | G51: 13.186895 | J51: This data has been derived from the world aluminium LCA's. They have produced LCA reports for Europe, North America and worldwide aluminium. Modelled at worldwide average scrap input of 31%, to avoid market distortions. Module D = -8.69 kg CO2e per unit. EOL recovery rate of 83%, based upon worldwide global aluminium flow model and for the building and construction sector. With a 2% material loss yield on the scrap recovered. | K51: 0.64 | L51: V1.0 | T51: Aluminium cast, Worldwide
F53: Regional aluminium - At world average recycled content
F55: Materials | G55: Embodied Carbon - kgCO2e/kg | J55: Comments | K55: DQI Score | L55: DQI Version | T55: Name Exactly as in ICE DB
F56: Aluminium General, European Mix, Inc Imports | G56: 6.6687175 | J56: This data has been derived from the world aluminium LCA's. They have produced LCA reports for Europe, North America and worldwide aluminium. Modelled at worldwide average scrap input of 31%, to avoid market distortions. Modelled with 25.6% extrusions, 55.7% rolled and 18.7% castings. Based upon European production and the import of aluminium consumed in Europe. Module D = -3.13 kg CO2e per unit. EOL recovery rate of 95%, based upon DU Telft study of European construction sector. With a 2% material loss yield on the scrap recovered. | K56: 0.64 | L56: V1.0 | T56: Aluminium General, European Mix, Inc Imports
F57: Aluminium, produced in Europe | G57: 5.5839382 | J57: This data has been derived from the world aluminium LCA's. They have produced LCA reports for Europe, North America and worldwide aluminium. Modelled at worldwide average scrap input of 31%, to avoid market distortions. This entry doesn’t consider aluminium imported into Europe. The aluminium must be made in Europe. Modelled with 25.6% extrusions, 55.7% rolled and 18.7% castings. Module D = -3.64 kg CO2e per unit. EOL recovery rate of 83%, based upon worldwide global aluminium flow model and for the building and construction sector. With a 2% material loss yield on the scrap recovered. | K57: 0.64 | L57: V1.0 | T57: Aluminium, produced in Europe
F58: Aluminium General, Worldwide | G58: 13.05554 | J58: This data has been derived from the world aluminium LCA's. They have produced LCA reports for Europe, North America and worldwide aluminium. Modelled at worldwide average scrap input of 31%, to avoid market distortions. Modelled with 25.6% extrusions, 55.7% rolled and 18.7% castings. Module D = -8.69 kg CO2e per unit. EOL recovery rate of 83%, based upon worldwide global aluminium flow model and for the building and construction sector. With a 2% material loss yield on the scrap recovered. | K58: 0.64 | L58: V1.0 | T58: Aluminium General, Worldwide
F59: Aluminium, North American | G59: 5.651616 | J59: This data has been derived from the world aluminium LCA's. They have produced LCA reports for Europe, North America and worldwide aluminium. Modelled at worldwide average scrap input of 31%, to avoid market distortions. Modelled with 25.6% extrusions, 55.7% rolled and 18.7% castings. Module D = -3.69 kg CO2e per unit. EOL recovery rate of 83%, based upon worldwide global aluminium flow model and for the building and construction sector. With a 2% material loss yield on the scrap recovered. | K59: 0.64 | L59: V1.0 | T59: Aluminium, North American
F60: Aluminium, Africa | G60: 12.40575 | J60: This data has been derived from the world aluminium LCA's. They have produced LCA reports for Europe, North America and worldwide aluminium. Modelled at worldwide average scrap input of 31%, to avoid market distortions. Modelled with 25.6% extrusions, 55.7% rolled and 18.7% castings. Module D = -8.65 kg CO2e per unit. EOL recovery rate of 83%, based upon worldwide global aluminium flow model and for the building and construction sector. With a 2% material loss yield on the scrap recovered. | K60: 0.64 | L60: V1.0 | T60: Aluminium, Africa
F61: Aluminium, China | G61: 14.593569 | J61: This data has been derived from the world aluminium LCA's. They have produced LCA reports for Europe, North America and worldwide aluminium. Modelled at worldwide average scrap input of 31%, to avoid market distortions. Modelled with 25.6% extrusions, 55.7% rolled and 18.7% castings. Module D = -10.25 kg CO2e per unit. EOL recovery rate of 83%, based upon worldwide global aluminium flow model and for the building and construction sector. With a 2% material loss yield on the scrap recovered. | K61: 0.64 | L61: V1.0 | T61: Aluminium, China
F62: Aluminium, Japan | G62: 10.624513 | J62: This data has been derived from the world aluminium LCA's. They have produced LCA reports for Europe, North America and worldwide aluminium. Modelled at worldwide average scrap input of 31%, to avoid market distortions. Modelled with 25.6% extrusions, 55.7% rolled and 18.7% castings. Module D = -7.34 kg CO2e per unit. EOL recovery rate of 83%, based upon worldwide global aluminium flow model and for the building and construction sector. With a 2% material loss yield on the scrap recovered. | K62: 0.64 | L62: V1.0 | T62: Aluminium, Japan
F63: Aluminium, Middle East | G63: 10.8098 | J63: This data has been derived from the world aluminium LCA's. They have produced LCA reports for Europe, North America and worldwide aluminium. Modelled at worldwide average scrap input of 31%, to avoid market distortions. Modelled with 25.6% extrusions, 55.7% rolled and 18.7% castings. Module D = -7.48 kg CO2e per unit. EOL recovery rate of 83%, based upon worldwide global aluminium flow model and for the building and construction sector. With a 2% material loss yield on the scrap recovered. | K63: 0.64 | L63: V1.0 | T63: Aluminium, Middle East
F64: Aluminium, Oceania | G64: 12.752085 | J64: This data has been derived from the world aluminium LCA's. They have produced LCA reports for Europe, North America and worldwide aluminium. Modelled at worldwide average scrap input of 31%, to avoid market distortions. Modelled with 25.6% extrusions, 55.7% rolled and 18.7% castings. Module D = -8.9 kg CO2e per unit. EOL recovery rate of 83%, based upon worldwide global aluminium flow model and for the building and construction sector. With a 2% material loss yield on the scrap recovered. | K64: 0.64 | L64: V1.0 | T64: Aluminium, Oceania
F65: Aluminium, Other Asia | G65: 15.869097 | J65: This data has been derived from the world aluminium LCA's. They have produced LCA reports for Europe, North America and worldwide aluminium. Modelled at worldwide average scrap input of 31%, to avoid market distortions. Modelled with 25.6% extrusions, 55.7% rolled and 18.7% castings. Module D = -11.19 kg CO2e per unit. EOL recovery rate of 83%, based upon worldwide global aluminium flow model and for the building and construction sector. With a 2% material loss yield on the scrap recovered. | K65: 0.64 | L65: V1.0 | T65: Aluminium, Other Asia
F66: Aluminium, Russia | G66: 5.548323 | J66: This data has been derived from the world aluminium LCA's. They have produced LCA reports for Europe, North America and worldwide aluminium. Modelled at worldwide average scrap input of 31%, to avoid market distortions. Modelled with 25.6% extrusions, 55.7% rolled and 18.7% castings. Module D = -3.61 kg CO2e per unit. EOL recovery rate of 83%, based upon worldwide global aluminium flow model and for the building and construction sector. With a 2% material loss yield on the scrap recovered. | K66: 0.64 | L66: V1.0 | T66: Aluminium, Russia
F67: Aluminium, South America | G67: 8.3190006 | J67: This data has been derived from the world aluminium LCA's. They have produced LCA reports for Europe, North America and worldwide aluminium. Modelled at worldwide average scrap input of 31%, to avoid market distortions. Modelled with 25.6% extrusions, 55.7% rolled and 18.7% castings. Module D = -5.65 kg CO2e per unit. EOL recovery rate of 83%, based upon worldwide global aluminium flow model and for the building and construction sector. With a 2% material loss yield on the scrap recovered. | K67: 0.64 | L67: V1.0 | T67: Aluminium, South America
F68: Aluminium, South Korea | G68: 11.946853 | J68: This data has been derived from the world aluminium LCA's. They have produced LCA reports for Europe, North America and worldwide aluminium. Modelled at worldwide average scrap input of 31%, to avoid market distortions. Modelled with 25.6% extrusions, 55.7% rolled and 18.7% castings. Module D = -8.31 kg CO2e per unit. EOL recovery rate of 83%, based upon worldwide global aluminium flow model and for the building and construction sector. With a 2% material loss yield on the scrap recovered. | K68: 0.64 | L68: V1.0 | T68: Aluminium, South Korea
F71: Asphalt
F73: Asphalt, mixed at plant
F75: The boundaries of this data is cradle to mixed asphalt. It includes the asphalt mixing energy, transport of constituents to asphalt mixing plant and the embodied carbon of ingredients.
E77: Embodied Carbon - kgCO2e per tonne | F77: Materials | G77: Embodied Carbon - kgCO2e per tonne | J77: Comments | K77: DQI Score | L77: DQI Version | T77: Name Exactly as in ICE DB
F78: Asphalt, 3% (bitumen) binder content (by mass) | G78: 50.684228 | J78: Straight run bitumen content by mass. Using ICE DB average aggregates. Cradle to mixed asphalt. Includes asphalt mixing energy (based upon MPA Sector Level HRA EPD, EPD HUB-1658, Aug 2024), transport of constituents by road to asphalt plant (assumed 250km for bitumen. 28.0 miles for aggregates [Ref: MPA Sustainable Development Report 2022]) and embodied carbon of ingredients. The transport of mixed asphalt to site is not included, e.g. cradle to mixed asphalt boundary. Density is for compacted asphalt. Embodied carbon of bitumen from EuroBitume Life Cycle Assessment 4.0 for bitumen, 2025. | K78: 0.76 | L78: V1.0 | T78: Asphalt, 3% (bitumen) binder content (by mass)
F79: Asphalt, 3.5% binder content | G79: 53.418686 | K79: 0.76 | L79: V1.0 | T79: Asphalt, 3.5% binder content
F80: Asphalt, 4% binder content | G80: 56.153145 | K80: 0.76 | L80: V1.0 | T80: Asphalt, 4% binder content
F81: Asphalt, 4.5% binder content | G81: 58.887603 | K81: 0.76 | L81: V1.0 | T81: Asphalt, 4.5% binder content
F82: Asphalt, 5% binder content | G82: 61.622061 | K82: 0.76 | L82: V1.0 | T82: Asphalt, 5% binder content
F83: Asphalt, 5.5% binder content | G83: 64.35652 | K83: 0.76 | L83: V1.0 | T83: Asphalt, 5.5% binder content
F84: Asphalt, 6% binder content | G84: 67.090978 | K84: 0.76 | L84: V1.0 | T84: Asphalt, 6% binder content
F85: Asphalt, 6.5% binder content | G85: 69.825436 | K85: 0.76 | L85: V1.0 | T85: Asphalt, 6.5% binder content
F86: Asphalt, 7% binder content | G86: 72.559895 | K86: 0.76 | L86: V1.0 | T86: Asphalt, 7% binder content
F88: Road surfaces - Asphalt surface or binder course, including laying and compacting, per 1m2 at 100mm thickness
F90: The boundaries of this data is cradle to laid road surface. It includes the cradle to mixed asphalt data above, as well as transport of mixed asphalt to site, road laying and compacting energy and a small allowance for construction waste.
E92: Embodied Carbon - kgCO2e per 1 m2, per 100mm depth surface or binder course | F92: Materials | G92: Embodied Carbon - kgCO2e per unit | I92: Units | J92: Comments | K92: DQI Score | L92: DQI Version | T92: Name Exactly as in ICE DB
F93: Road surface, asphalt, 3% (bitumen) binder content (by mass) | G93: 14.24074 | I93: 1 m2, per 100mm depth surface or binder course | J93: Surface or binder course, at the stated average straight run bitumen content by mass. Cradle to constructed road surface. Using ICE DB average aggregates. Includes embodied carbon of ingredients. Also includes transport of mixed asphalt to site, distance 31 miles [Ref: Mineral Products Association, Sustainable Development Report 2022]. Density is for compacted asphalt. Includes road laying and compacting energy [Ref: TRL, report PRP575 (V4), Protocol for the calculation of whole life cycle greenhouse gas emissions generated by asphalt, M Wayman et al., 2014.]. Assumed 1% waste during road construction (assumption - specific data was not available). Embodied carbon of bitumen from EuroBitume, 2025. | K93: 0.76 | L93: V1.0 | T93: Road surface, asphalt, 3% (bitumen) binder content (by mass)
F94: Road surface, asphalt, 3.5% binder content | G94: 14.889764 | I94: #N/A | K94: 0.76 | L94: V1.0 | T94: Road surface, asphalt, 3.5% binder content
F95: Road surface, asphalt, 4% binder content | G95: 15.538788 | I95: #N/A | K95: 0.76 | L95: V1.0 | T95: Road surface, asphalt, 4% binder content
F96: Road surface, asphalt, 4.5% binder content | G96: 16.187812 | I96: #N/A | K96: 0.76 | L96: V1.0 | T96: Road surface, asphalt, 4.5% binder content
F97: Road surface, asphalt, 5% binder content | G97: 16.836835 | I97: #N/A | K97: 0.76 | L97: V1.0 | T97: Road surface, asphalt, 5% binder content
F98: Road surface, asphalt, 5.5% binder content | G98: 17.485859 | I98: #N/A | K98: 0.76 | L98: V1.0 | T98: Road surface, asphalt, 5.5% binder content
F99: Road surface, asphalt, 6% binder content | G99: 18.134883 | I99: #N/A | K99: 0.76 | L99: V1.0 | T99: Road surface, , asphalt, 6% binder content
F100: Road surface, asphalt, 6.5% binder content | G100: 18.783906 | I100: #N/A | K100: 0.76 | L100: V1.0 | T100: Road surface, asphalt, 6.5% binder content
F101: Road surface, asphalt, 7% binder content | G101: 19.43293 | I101: #N/A | K101: 0.76 | L101: V1.0 | T101: Road surface, asphalt, 7% binder content
F103: Bitumen
F105: Materials | G105: Embodied Carbon - kgCO2e/kg | J105: Comments | K105: DQI Score | L105: DQI Version | T105: Name Exactly as in ICE DB
F106: Straight-run bitumen | G106: 0.53 | J106: Source: Eurobitume, 2025. The Eurobitume Life Cycle Assessment 4.0 for bitumen. Note that this is a large change in the carbon emissions over the previous version of the study. The new study claims alliance with the EN15804 method. | K106: 0.72 | L106: V1.0 | T106: Straight-run bitumen
F107: Polymer modified bitumen (PMB) | G107: This data has been removed in ICE V4.1. The newer EuroBitume study doesn’t contain factors for these materials anymore. We would like to replace these values in future updates of the ICE database - please refer to our website for more information on how you could contribute to future ICE updates. | T107: Polymer modified bitumen (PMB)
F108: Bitumen emulsion | T108: Bitumen emulsion
F110: Brass
F111: Version: ICE V 2.0 2011
F113: Materials | G113: Embodied Carbon - kgCO2e/kg | J113: Comments | T113: Name Exactly as in ICE DB
F114: General | G114: 2.64 (?) | J114: Poor data availability. It is believed that the data may be largely dependent upon ore grade. Poor carbon data, making estimate of embodied carbon difficult.
F115: Virgin | G115: 4.80 (?)
F116: Recycled | G116: 1.20 (?)
F118: Bricks
F120: Materials | G120: Embodied Carbon - kgCO2e/kg | J120: Comments | K120: DQI Score | L120: DQI Version | T120: Name Exactly as in ICE DB
F121: General (Common Brick) | G121: 0.213 | J121: Density needs to consider voids in the finished bricks. Average UK brick weighs 2.13 kg per brick [Source: The Brick Development Association]. | K121: 0.76 | L121: V1.0 | T121: Clay, Brick
F122: A Single Brick | G122: 0.45369 | J122: Average UK brick weighs 2.13 kg per brick [Source: The Brick Development Association]. | K122: 0.76 | L122: V1.0 | T122: Clay brick, one brick, 215 x 65 x 102.5mm
F124: Clay brick walls - per m2 of wall including mortar, not including waste
F126: Single skin walls - 102.5mm thick
E128: Embodied Carbon - kgCO2e per m2 | F128: Materials | G128: Declared Units | H128: EC - kgCO2e per unit | I128: Mass per declared unit - kg | J128: Comments | K128: DQI Score | L128: DQI Version | T128: Name Exactly as in ICE DB
F129: with Mortar 1:3 cement:sand mix (Using CEM I cement) | G129: 1 | H129: 39.084842 | I129: m2 | J129: 1900 bricks per m3 of mortar. Mortar uses CEM I, e.g. no cement replacements in the mix. You must consider if this strength of mortar is suitable for your application. Average UK brick weighs 2.13 kg per brick [Source: The Brick Development Association]. | K129: 0.75893246 | L129: V1.0 | T129: wall, clay brick, single skin, 102.5 mm with Mortar 1:3 cement:sand mix (Using CEM I cement)
F130: with Mortar 1:4 cement:sand mix (Using CEM I cement) | G130: 1 | H130: 36.903919 | I130: m2 | K130: 0.7587827 | L130: V1.0 | T130: wall, clay brick, single skin, 102.5 mm with Mortar 1:4 cement:sand mix (Using CEM I cement)
F131: with Mortar 1:5 cement:sand mix (Using CEM I cement) | G131: 1 | H131: 35.425103 | I131: m2 | K131: 0.75867065 | L131: V1.0 | T131: wall, clay brick, single skin, 102.5 mm with Mortar 1:5 cement:sand mix (Using CEM I cement)
F132: with Mortar 1:6 cement:sand mix (Using CEM I cement) | G132: 1 | H132: 34.356358 | I132: m2 | K132: 0.75858367 | L132: V1.0 | T132: wall, clay brick, single skin, 102.5 mm with Mortar 1:6 cement:sand mix (Using CEM I cement)
F133: with Mortar (1:½:4½ Cement:Lime:Sand mix) (Using CEM I cement) | G133: 1 | H133: 37.43656 | I133: m2 | K133: 0.74703524 | L133: V1.0 | T133: wall, clay brick, single skin, 102.5 mm with Mortar (1:½:4½ Cement:Lime:Sand mix) (Using CEM I cement)
F134: with Mortar (1:1:6 Cement:Lime:Sand mix) (Using CEM I cement) | G134: 1 | H134: 36.51385 | I134: m2 | K134: 0.73990622 | L134: V1.0 | T134: wall, clay brick, single skin, 102.5 mm with Mortar (1:1:6 Cement:Lime:Sand mix) (Using CEM I cement)
F135: with Mortar (1:2:9 Cement:Lime:Sand mix) (Using CEM I cement) | G135: 1 | H135: 35.514515 | I135: m2 | K135: 0.7317673 | L135: V1.0 | T135: wall, clay brick, single skin, 102.5 mm with Mortar (1:2:9 Cement:Lime:Sand mix) (Using CEM I cement)
F137: Double skin walls
...

Sheet >> Material Profiles >>
E6: Material Profiles >>>

Sheet Aggregates_Sand
A1: THESE ROWS AND COLUMNS WILL BE HIDDEN - They contain update notes and information for lookup calculations
F2: SELECT Material | G2: AggregateSand | I2: Hide these rows, used for lookup formulas
F3: Sheet name | G3: =MID(CELL("filename",A1),FIND("]",CELL("filename",A1))+1,255) -> Aggregates_Sand
F4: Workbook name | G4: =MID(CELL("filename",A1),FIND("[",CELL("filename",A1))+1,FIND("]", CELL("filename",A1))-FIND("[",CELL("filename",A1))-1) -> ICE DB Educational V4.1 - Oct 2025.xlsx
B6: Edit Title Manually | F6: Material Profile: Aggregates & Sand
F7: ICE DB Version: | G7: =Miscellaneous!$E$3 -> V4.1 - Oct 2025 | J7: Check this link to see when the material profile was last updated
B8: Update URL Manually | F8: This material profile is provided in full to demonstrate the format and scope of the information provided in the Advanced version. For access to all material profiles, please refer to the advanced version using the links below:
F9: Is this version still valid? | H9: Check link below, to see if a newer version is available. | K9: This version has expired. Please download a new version using the link below.
F10: Check if this copy is up to date at: | H10: http://www.circularecology.com/embodied-energy-and-carbon-footprint-database.html
F17: Section Navigation
F19: Section - Click to Go | J19: Comments
A20: A51 | B20: =CONCATENATE("#",$G$3,"!"&A20) -> #Aggregates_Sand!A51 | C20: Introduction to Material | F20: =HYPERLINK(B20,C20) -> Introduction to Material | J20: Notes on the embodied carbon of this material. This may include some important information.
A21: A60 | B21: =CONCATENATE("#",$G$3,"!"&A21) -> #Aggregates_Sand!A60 | C21: Selected Embodied Carbon Coefficients | F21: =HYPERLINK(B21,C21) -> Selected Embodied Carbon Coefficients | J21: These are the main embodied carbon footprint coefficients for the material types.
A22: A483 | B22: =CONCATENATE("#",$G$3,"!"&A22) -> #Aggregates_Sand!A483 | C22: Wider Life Cycle Notes | F22: =HYPERLINK(B22,C22) -> Wider Life Cycle Notes | J22: Notes on wider life cycle impacts.
A23: A495 | B23: =CONCATENATE("#",$G$3,"!"&A23) -> #Aggregates_Sand!A495 | C23: ICE Database Embodied Carbon (EC) Statistics - kg CO2e/kg | F23: =HYPERLINK(B23,C23) -> ICE Database Embodied Carbon (EC) Statistics - kg CO2e/kg | J23: Here you will find detailed statistics on the data collected. For the full list of all datapoints, a separate section is included further below.
A24: A533 | B24: =CONCATENATE("#",$G$3,"!"&A24) -> #Aggregates_Sand!A533 | C24: Histograms and distribution charts | F24: =HYPERLINK(B24,C24) -> Histograms and distribution charts | J24: For some of the sub-material categories, histograms and embodied carbon distribution charts have been included.
A25: A583 | B25: =CONCATENATE("#",$G$3,"!"&A25) -> #Aggregates_Sand!A583 | C25: Data Quality | F25: =HYPERLINK(B25,C25) -> Data Quality | J25: The data within the ICE Database is rated for data quality. The average data quality is shown here, along with a link to the data quality matrix.
A26: A759 | B26: =CONCATENATE("#",$G$3,"!"&A26) -> #Aggregates_Sand!A759 | C26: Material Properties | F26: =HYPERLINK(B26,C26) -> Material Properties | J26: Information on material density, specific heat, and more.
A27: A776 | B27: =CONCATENATE("#",$G$3,"!"&A27) -> #Aggregates_Sand!A776 | C27: All Data Points | F27: =HYPERLINK(B27,C27) -> All Data Points | J27: Here you will find a list of all the datapoints collected. These datapoints are used to produce the histograms and may be useful for further statistical analysis.
A28: A1072 | B28: =CONCATENATE("#",$G$3,"!"&A28) -> #Aggregates_Sand!A1072 | C28: Further Reading | F28: =HYPERLINK(B28,C28) -> Further Reading | J28: A list of recommended reading.
A29: A1799 | B29: =CONCATENATE("#",$G$3,"!"&A29) -> #Aggregates_Sand!A1799 | C29: References and EPDs | F29: =HYPERLINK(B29,C29) -> References and EPDs | J29: The ICE Database uses data from multiple resources. However, EPDs have become the most important data resource. Here you will find reference details and links to EPDs for this material.
B30: =CONCATENATE("#",$G$3,"!"&A30) -> #Aggregates_Sand! | C30: INSERT LINK TO WEBPAGE FOR MATERIAL PROFILE | F30: =HYPERLINK(B30,C30) -> INSERT LINK TO WEBPAGE FOR MATERIAL PROFILE | J30: For further information, please visit the webpage for this material profile.
B36: CUSTOMISE WHOLE SECTION FOR MATERIAL | F36: Introduction to Material
F37: Data for aggregates has a particularly notable embodied carbon range. There are also many different types of aggregates. ICE V2.0 only contained data for general aggregates. The ICE database now contains data for many different types of aggregates, including land won, marine, recycled and secondary aggregates. The data suggests that for most types of aggregates there is a wide range of embodied carbon. There is also a notable difference in the embodied carbon of virgin and non-virgin aggregates (recycled and secondary). The data suggests that virgin aggregates may have a lower embodied carbon of production. However, every case should be judged on an individual basis. It is important to consider with aggregates that carbon is only one of many environmental and resource use indicators. Whilst there are cases here recycled or secondary aggregates may be higher embodied carbon than virgin aggregates, it should also be considered that embodied carbon does not consider any of the wider resource use benefits. The use of recycled resources, reduces the burden on virgin resources. This is something that embodied carbon assessment doesn't consider adequately. Embodied carbon data for recycled and secondary aggregates would benefit from improvement. Data for secondary aggregates was particularly poor. Likewise, data on the consumption mixture of secondary and recycled aggregates was limited and would benefit from improvement.
F46: Boundaries: | G46: Cradle to Gate = A1-A3
B49: COPY FROM SUMMARY TABLE | F49: Selected Embodied Carbon Coefficients
F51: Comments
F52: There is a notable embodied carbon range for most types of aggregates, as well as for different types of aggregates. It is therefore recommended to use data on specific types of aggregates, over the data for UK general aggregates, where possible. This is because the data on secondary and recycled aggregates influences the average notably.
F57: <<< Start of Main Embodied Carbon Data >>>
F59: Materials | G59: Embodied Carbon - kgCO2e/kg | H59: Comments | M59: DQI Score | N59: DQI Version | T59: Name Exactly as in ICE DB
F60: Aggregates and sand, general UK, mixture of land won, marine, secondary and recycled, bulk, loose | G60: 0.0074696455 | H60: This is an estimate of a market average aggregate. It models a mixture of 64.2% land won, 27.5% recycled and secondary, and 8.3% marine aggregates. Consumption statistics have been taken from a report, by British Marine Aggregates Producer Association, a member of the Mineral Products Association (MPA). [Tenth sustainable development report for the British marine aggregate industry, Dec 2016]. These results are sensitive to the embodied carbon of secondary aggregates, which is a material where data would benefit from improvement. If you know the specific type of aggregates you will use, then it is recommended to use a more specific category of aggregates. | M60: 0.57223891 | N60: V1.0 | T60: Aggregates and sand, general UK, mixture of land won, marine, secondary and recycled, bulk, loose
F61: Aggregates and sand, general, virgin mixture of land won and marine, bulk, loose | G61: 0.0049277889 | H61: Excludes recycled and secondary aggregate. This has been modelled with 89% land won and 11% marine won aggregate. Consumption statistics have been taken from a report, by British Marine Aggregates Producer Association, a member of the Mineral Products Association (MPA). [Tenth sustainable development report for the British marine aggregate industry, Dec 2016]. The consumption of marine aggregate was taken to be the total marine aggregate production. Of the total, 68% are consumed in the GB market, 11% are sent to the European market and 21% used as beach replenishment or fill. | M61: 0.56684369 | N61: V1.0 | T61: Aggregates and sand, general, virgin mixture of land won and marine, bulk, loose
F62: Aggregates and sand, from virgin land won resources, bulk, loose | G62: 0.0043575012 | H62: Based upon the statistical average of all data collected for virgin aggregates in the ICE Database. | M62: 0.64818763 | N62: V1.0 | T62: Aggregates and sand, from virgin land won resources, bulk, loose
F63: Aggregates and sand, from virgin marine resources, bulk, loose | G63: 0.0090375 | H63: Consumption statistics have been taken from a report, by British Marine Aggregates Producer Association, a member of the Mineral Products Association (MPA). [Tenth sustainable development report for the British marine aggregate industry, Dec 2016]. The consumption of marine aggregate was taken to be the total marine aggregate production. The data has been modelled with the average energy consumption for extracting marine aggregates in the UK. The original data did not use all scope emissions factors, instead just scope 1 and 2. The data was therefore used to estimate the full scope 1, 2 and 3 emissions. The impacts to produce aggregates has a particularly large variation in embodied impacts. | M63: 0.34285714 | N63: V1.0 | T63: Aggregates and sand, from virgin marine resources, bulk, loose
F64: Aggregates and sand, from recycled resources, no heat treatment, bulk, loose | G64: 0.0060529786 | H64: Based upon the statistical average of all data collected for recycled aggregates with no heat treatment in the ICE Database. Recycled aggregates include aggregates from construction and demolition waste. It does not cover secondary aggregates, such as blast furnace slag, or bottom ash (see separate category for these). Data for recycled aggregates is more difficult to obtain than for virgin aggregates. There is also a large range in results for recycled aggregates, adding uncertainty into the results. | M64: 0.56122449 | N64: V1.0 | T64: Aggregates and sand, from recycled resources, no heat treatment, bulk, loose
F65: Aggregates and sand, from recycled resources, with heat treatment, bulk, loose | G65: 0.11877167 | H65: Based upon the statistical average of all data collected for recycled aggregates that have been through heat treatment in the ICE Database. Recycled aggregates include aggregates from construction and demolition waste. It does not cover secondary aggregates such as blast furnace slag, or bottom ash (see separate category for these). Data for recycled aggregates is more difficult to obtain than for virgin aggregates. There is also a large range in results for recycled aggregates, adding uncertainty into the results. | M65: 0.44761905 | N65: V1.0 | T65: Aggregates and sand, from recycled resources, with heat treatment, bulk, loose
F66: Aggregates and sand, expanded clay, bulk, loose | G66: 0.3350915 | H66: Based upon the statistical average of all data collected for expanded clay aggregates in the ICE Database. | M66: 0.48571429 | N66: V1.0 | T66: Aggregates and sand, expanded clay, bulk, loose
F67: Aggregates, expanded foamed glass, bulk, loose | G67: 0.273532 | H67: Based upon the statistical average of all data collected for expanded foamed glass aggregates in the ICE Database. | M67: 0.45714286 | N67: V1.0 | T67: Aggregates, expanded foamed glass, bulk, loose
F68: Aggregates and sand, from secondary resources, bulk, loose | G68: 0.063323 | H68: Including blast furnace slag, bottom ashes, road planings, mining spoil and other aggregates manufactured from secondary resources. Limited data on the embodied carbon of secondary aggregates was available. There was also limited data on the consumption mixture of secondary aggregates in the UK. The mixture was estimated based upon two sub-regional reports for the Aggregate Minerals survey2015 (AM15). See the references [Table 6.1 in Ref: North East Aggregates Working Party, Annual Aggregates Monitoring report 2015, Dec 2016 ] and [Table 10B in South East Aggregates Working Party, South East Aggregates Monitoring report 2014 & 2015, Sept 2016]. The data would benefit from covering a wider share of the UK secondary aggregate market, | M68: 0.51428571 | N68: V1.0 | T68: Aggregates and sand, from secondary resources, bulk, loose
F69: Aggregates and sand, mixture of recycled and secondary resources, bulk, loose | G69: 0.014181254 | H69: Data on recycled and (particularly) secondary aggregates would benefit from improvement. Limited data on the embodied carbon of secondary aggregates was available. There was also limited data on the consumption mixture of recycled and secondary aggregates in the UK. The mixture was modelled with 33% secondary and 67% recycled aggregates. [Estimated from Ref: Aggregates, cement and ready-mix concrete market investigation, Working paper on market definition for aggregates, cement and RMX. ND67. Available from: https://assets.publishing.service.gov.uk/media/5329dfb440f0b60a730002cf/market_definition_housestyled.pdf] | M69: 0.59042185 | N69: V1.0 | T69: Aggregates and sand, mixture of recycled and secondary resources, bulk, loose
F467: <<< End of Main Embodied Carbon Data >>>
F470: Wider Lifecycle Notes (Modules B, C and D)
F471: The ICE Database is a cradle to gate data resource (module A1 to A3). Modules B (in-use), C (end of life) and D (benefits to future lifecycles) are beyond the scope of the ICE Database. However, some important information is provided here. It is also worth checking the links to the Environmental Product Declarations (EPDs) further below. Many EPDs have data for wider lifecycles.
F472: Considerations specific to this material:
F473: No comments on wider life cycle impacts.
F477: Considerations for all materials:
F478: The ICE database contains data on the cradle to gate, Modules A1-3, embodied carbon. It is important to consider the amount of construction waste in a building project. The material wasted has an embodied carbon impact which should not be neglected. In many cases this can be a significant contribution to embodied carbon of a construction building. Users will need to consider if a material or product has a notable in-use or end of life impact, based upon their application. Durability and lifetime should also be considered as a part of a fair and comparative assessment. Finally, end of life relies on assumptions for the disposal route, such as landfill, reuse or recycling. The end of life phase should consider that it cannot be guaranteed what will happen at the end of the lifetime. Reviews of potential scenarios with sensitivity analysis should be undertaken where possible. Finally, users are directed to the references section, which contains links to EPDs. Many of the EPDs state impacts of installation, in-use and end of life.
F484: ICE Database Embodied Carbon (EC) Statistics - kg CO2e/kg
F485: This is not the main embodied carbon data. See the section 'Selected embodied carbon coefficients' for the main data.
F486: The below statistics have come from the data collected for the ICE version stated at the top of this material profile. These statistics are taken from all of the data collected in the backend ICE database, which is not publicly available. The categories of sub-material types are sometimes merged in the final version of the publicly available ICE database, e.g. if sample size is deemed individually too low across similar categories. The below statistics may therefore show different data for similar sounding material sub-categories, in some instances. These statistics are provided for transparency and general information purposes. It is recommended to use the main embodied carbon data shown above, rather than the statistical averages presented here. For example, for some materials the average embodied carbon of all data collected is a poor indicator of the average embodied carbon of that material. This may arise due to sub-material types that have an unusually high or low impact. Those sub-material types may have a low market share. In such cases, they could influence the statistical average unfairly. For this reason, some of the material and sub-material categories in the main ICE Database considers the consumption mixture of various sub-material types.
B488: SELECT SUB-MATERIAL - REST AUTO GENERATED | F488: Main Material | G488: Sample Size | H488: Average Embodied Carbon (kg CO2e/kg) | I488: Min Embodied Carbon (kg CO2e/kg) | J488: Max Embodied Carbon (kg CO2e/kg) | K488: Standard Deviation Embodied Carbon (kg CO2e/kg) | L488: Variance Based on a Sample (Excel Var Function) Embodied Carbon (kg CO2e/kg) | M488: Comments
E489: 1 | F489: AggregateSand - All Data Collected | G489: 162 | H489: 0.01597112 | I489: 0.00025 | J489: 0.338274 | K489: 0.051527822 | L489: 0.0026551164 | M489: This data doesn’t include any modelled datapoints, e.g. datapoints that have modelled a consumption mixture of sub-material types. It is all data collected from the literature. All sub-categories may not be shown.
E490: 2 | F490: AggregateSand, Land won gravel and sand | G490: 134 | H490: 0.0043575012 | I490: 0.00025 | J490: 0.0342735 | K490: 0.0050160908 | L490: 2.5161167e-05
E491: 3 | F491: AggregateSand, Recycled aggregate, no heat treat | G491: 14 | H491: 0.0060529786 | I491: 0.00157 | J491: 0.01548 | K491: 0.004612556 | L491: 2.1275673e-05
E492: 4 | F492: AggregateSand, Recycled aggregate, heat treat | G492: 6 | H492: 0.11877167 | I492: 0.00222 | J492: 0.2608 | K492: 0.10279094 | L492: 0.010565977
E493: 5 | F493: AggregateSand, Secondary manufactured | G493: 4 | H493: 0.063323 | I493: 0.039973 | J493: 0.085424 | K493: 0.016991736 | L493: 0.0002887191
E494: 6 | F494: AggregateSand, Expanded clay agg and sand | G494: 2 | H494: 0.3350915 | I494: 0.331909 | J494: 0.338274 | K494: 0.0031825 | L494: 1.0128306e-05
E495: 7 | F495: AggregateSand, Marine sand and aggregate | G495: 1 | H495: 0.0090375 | I495: 0.0090375 | J495: 0.0090375 | K495: 0 | L495: 0
E496: 8 | F496: AggregateSand, Expanded foamed glass | G496: 1 | H496: 0.273532 | I496: 0.273532 | J496: 0.273532 | K496: 0 | L496: 0
E497: 9 | F497: AggregateSand, General aggregate
E498: 10
E499: 11
E500: 12
E501: 13
E502: 14
E503: 15
E504: 16
F505: For some of the sub-categories, mainly with larger sample sizes, the percentiles are shown below
B508: AUTO GENERATED | F508: Main Material | G508: Percentiles - Where Available - kgCO2e per kg | N508: Comments
G509: 10 | H509: 20 | I509: 25 | J509: 50 | K509: 75 | L509: 80 | M509: 90
E510: 1 | F510: AggregateSand - All Data Collected | G510: 0.001825 | H510: 0.00215 | I510: 0.00227 | J510: 0.0035 | K510: 0.00547 | L510: 0.00609 | M510: 0.01562255 | N510: For small sample sizes data for a particular percentile may not be available.
E511: 2 | F511: AggregateSand, Land won gravel and sand | G511: 0.00172 | H511: 0.00214 | I511: 0.00223 | J511: 0.00309 | K511: 0.0048375 | L511: 0.00516 | M511: 0.00615
E512: 3 | F512: AggregateSand, Recycled aggregate, no heat treat | G512: 0.001708 | H512: 0.002196 | I512: 0.00242 | J512: 0.00386 | K512: 0.01103 | L512: 0.01203 | M512: 0.013631805
E513: 4 | F513: AggregateSand, Recycled aggregate, heat treat | H513: 0.003072 | I513: 0.0038175 | J513: 0.101185 | K513: 0.2473675 | L513: 0.253636
E514: 5 | F514: AggregateSand, Secondary manufactured | H514: 0.039973 | I514: 0.04402675 | J514: 0.0639475 | K514: 0.08199475 | L514: 0.085424
E515: 6 | F515: AggregateSand, Expanded clay agg and sand | J515: 0.393208
E516: 7 | F516: AggregateSand, Marine sand and aggregate | J516: 0.0090375
E517: 8 | F517: AggregateSand, Expanded foamed glass | J517: 0.27763
E518: 9 | F518: AggregateSand, General aggregate
E519: 10
E520: 11
E521: 12
E522: 13
E523: 14
E524: 15
E525: 16
F526: For some of the sub-categories there are histograms and distribution charts provided below. The individual datapoints may be found further below.
B530: AUTO GENERATED | F530: 1 - Profile of data for: | H530: AggregateSand - All Data Collected
B532: Edit range on source data
B535: AUTO GENERATED | F535: 2 - Profile of data for: | H535: AggregateSand, Land won gravel and sand
B538: Edit range on source data
B541: AUTO GENERATED | F541: 3 - Profile of data for: | H541: AggregateSand, Recycled aggregate, no heat treat
B543: Edit range on source data
B546: AUTO GENERATED | F546: 4 - Profile of data for: | H546: AggregateSand, Recycled aggregate, heat treat
B548: Edit range on source data
B551: AUTO GENERATED | F551: 5 - Profile of data for: | H551: AggregateSand, Secondary manufactured
B553: Edit range on source data
B556: AUTO GENERATED | F556: 6 - Profile of data for: | H556: AggregateSand, Expanded clay agg and sand
B558: Edit range on source data
B561: AUTO GENERATED | F561: 7 - Profile of data for: | H561: AggregateSand, Marine sand and aggregate
...

Sheet Aluminium
A1: THESE ROWS AND COLUMNS WILL BE HIDDEN - They contain update notes and information for lookup calculations
F2: SELECT Material | G2: Aluminium | I2: Hide these rows, used for lookup formulas
F3: Sheet name | G3: =MID(CELL("filename",A1),FIND("]",CELL("filename",A1))+1,255) -> Aluminium
F4: Workbook name | G4: =MID(CELL("filename",A1),FIND("[",CELL("filename",A1))+1,FIND("]", CELL("filename",A1))-FIND("[",CELL("filename",A1))-1) -> ICE DB Educational V4.1 - Oct 2025.xlsx | L4: Worksheet ref | M4: =CONCATENATE("[",G4,"]",G3,"!") -> [ICE DB Educational V4.1 - Oct 2025.xlsx]Aluminium!
B6: Edit Title Manually | F6: Material Profile: Aluminium
F7: ICE DB Version: | G7: =Miscellaneous!$E$3 -> V4.1 - Oct 2025 | J7: Check this link to see when the material profile was last updated
F8: To access this material profile, please register and download the Advanced version for free, with the link below:
F9: http://www.circularecology.com/embodied-energy-and-carbon-footprint-database.html
B10: Update URL Manually | F10: For further information on this material, please visit this page: | H10: INSERT LINK TO WEBPAGE…

Sheet Asphalt
A1: THESE ROWS AND COLUMNS WILL BE HIDDEN - They contain update notes and information for lookup calculations
F2: SELECT Material | G2: Asphalt | I2: Hide these rows, used for lookup formulas
F3: Sheet name | G3: =MID(CELL("filename",A1),FIND("]",CELL("filename",A1))+1,255) -> Asphalt
F4: Workbook name | G4: =MID(CELL("filename",A1),FIND("[",CELL("filename",A1))+1,FIND("]", CELL("filename",A1))-FIND("[",CELL("filename",A1))-1) -> ICE DB Educational V4.1 - Oct 2025.xlsx
B6: Edit Title Manually | F6: Material Profile: Asphalt
F7: ICE DB Version: | G7: =Miscellaneous!$E$3 -> V4.1 - Oct 2025 | J7: Check this link to see when the material profile was last updated
F8: To access this material profile, please register and download the Advanced version for free, with the link below:
F9: http://www.circularecology.com/embodied-energy-and-carbon-footprint-database.html
B10: Update URL Manually | F10: For further information on this material, please visit this page: | H10: INSERT LINK TO WEBPAGE…
F118: The below will be deleted before sending externally
F120: NOTES: Check the slicers are on the correct materials | I120: All Data Points Pivot Tables | L120: All Data Points Pivot Tables | R120: All Data Points Pivot Tables | Y120: All Data Points Pivot Tables | AG120: Reference Lookup Pivot Table
F122: Number 1 | G122: =#REF! -> #REF! | I122: Number 2 | J122: =#REF! -> #REF! | L122: Number 3 | M122: =#REF! -> #REF! | O122: Number 4 | P122: =#REF! -> #REF! | R122: Number 5 | S122: =#REF! -> #REF! | U122: Number 6 | V122: =#REF! -> #REF! | X122: Number 7 | Y122: =#REF! -> #REF! | AA122: Number 8 | AB122: =#REF! -> #REF!
F134: Paste below per kg Embodied Carbon | I134: Paste below per kg Embodied Carbon | L134: Paste below per kg Embodied Carbon | O134: Paste below per kg Embodied Carbon | R134: Paste below per kg Embodied Carbon | U134: Paste below per kg Embodied Carbon | X134: Paste below per kg Embodied Carbon | AA134: Paste below per kg Embodied Carbon | AF134: Paste below reference numbers, filtered by this material
B135: Headers in this row | F135: Per kg. Embodied Carbon (kg CO2/kg) | G135: Data Point Number | I135: Per kg. Embodied Carbon (kg CO2/kg) | J135: Data Point Number | L135: Per kg. Embodied Carbon (kg CO2/kg) | M135: Data Point Number | O135: Per kg. Embodied Carbon (kg CO2/kg) | P135: Data Point Number | AF135: Row Labels
B136: Start data from this row | F136: 0.0980285 | G136: 30721 | I136: 0.0797795 | J136: 30724 | L136: 0.07 | M136: 30744 | O136: 0.0980285 | P136: 30721 | AF136: 364
F137: 0.0797795 | G137: 30724 | I137: 0.0773739 | J137: 30722 | L137: 0.0644 | M137: 30747 | AF137: 367
F138: 0.0773739 | G138: 30722 | I138: 0.07126 | J138: 30723 | AF138: 457
F139: 0.07126 | G139: 30723 | I139: 0.049 | J139: 31366 | AF139: 929
F140: 0.07 | G140: 30744 | I140: 0.0366 | J140: 31367 | AF140: 987
F141: 0.0644 | G141: 30747 | I141: 0.0314 | J141: 30844
F142: 0.049 | G142: 31366 | I142: 0.0314 | J142: 31365
F143: 0.0366 | G143: 31367 | I143: 0.031 | J143: 31368
F144: 0.0314 | G144: 30844 | I144: 0.0297 | J144: 31369
F145: 0.0314 | G145: 31365 | I145: 0.0287 | J145: 30841
F146: 0.031 | G146: 31368 | I146: 0.0276 | J146: 30842
F147: 0.0297 | G147: 31369 | I147: 0.0274 | J147: 31370
F148: 0.0287 | G148: 30841 | I148: 0.0265 | J148: 30843
F149: 0.0276 | G149: 30842 | I149: 0.0249 | J149: 30839
F150: 0.0274 | G150: 31370 | I150: 0.0238 | J150: 30840
F151: 0.0265 | G151: 30843 | I151: 0.0236 | J151: 30836
F152: 0.0249 | G152: 30839 | I152: 0.0225 | J152: 30837
F153: 0.0238 | G153: 30840 | I153: 0.0214 | J153: 30838
F154: 0.0236 | G154: 30836
F155: 0.0225 | G155: 30837
F156: 0.0214 | G156: 30838

Sheet Bitumen
A1: THESE ROWS AND COLUMNS WILL BE HIDDEN - They contain update notes and information for lookup calculations
F2: SELECT Material | G2: Bitumen | I2: Hide these rows, used for lookup formulas
F3: Sheet name | G3: =MID(CELL("filename",A1),FIND("]",CELL("filename",A1))+1,255) -> Bitumen
F4: Workbook name | G4: =MID(CELL("filename",A1),FIND("[",CELL("filename",A1))+1,FIND("]", CELL("filename",A1))-FIND("[",CELL("filename",A1))-1) -> ICE DB Educational V4.1 - Oct 2025.xlsx
B6: Edit Title Manually | F6: Material Profile: Bitumen
F7: ICE DB Version: | G7: =Miscellaneous!$E$3 -> V4.1 - Oct 2025 | J7: Check this link to see when the material profile was last updated
F8: To access this material profile, please register and download the Advanced version for free, with the link below:
F9: http://www.circularecology.com/embodied-energy-and-carbon-footprint-database.html
B10: Update URL Manually | F10: For further information on this material, please visit this page: | H10: INSERT LINK TO WEBPAGE…
F118: The below will be deleted before sending externally
F120: NOTES: Check the slicers are on the correct materials | I120: All Data Points Pivot Tables | L120: All Data Points Pivot Tables | R120: All Data Points Pivot Tables | Y120: All Data Points Pivot Tables | AG120: Reference Lookup Pivot Table
F122: Number 1 | G122: =#REF! -> #REF! | I122: Number 2 | J122: =#REF! -> #REF! | L122: Number 3 | M122: =#REF! -> #REF! | O122: Number 4 | P122: =#REF! -> #REF! | R122: Number 5 | S122: =#REF! -> #REF! | U122: Number 6 | V122: =#REF! -> #REF! | X122: Number 7 | Y122: =#REF! -> #REF! | AA122: Number 8 | AB122: =#REF! -> #REF!
F134: Paste below per kg Embodied Carbon | I134: Paste below per kg Embodied Carbon | L134: Paste below per kg Embodied Carbon | O134: Paste below per kg Embodied Carbon | R134: Paste below per kg Embodied Carbon | U134: Paste below per kg Embodied Carbon | X134: Paste below per kg Embodied Carbon | AA134: Paste below per kg Embodied Carbon | AF134: Paste below reference numbers, filtered by this material
E135: Header | F135: Per kg. Embodied Carbon (kg CO2/kg) | G135: Data Point Number | H135: Header | I135: Per kg. Embodied Carbon (kg CO2/kg) | J135: Data Point Number | K135: Header | L135: Per kg. Embodied Carbon (kg CO2/kg) | M135: Data Point Number | O135: Per kg. Embodied Carbon (kg CO2/kg) | P135: Data Point Number | R135: Per kg. Embodied Carbon (kg CO2/kg) | S135: Data Point Number | T135: Header | W135: Header | Z135: Header | AE135: Header | AF135: Row Labels
F136: 1.531352 | G136: 30758 | I136: 1.531352 | J136: 30758 | L136: 0.38879 | M136: 30386 | O136: 0.246299 | P136: 31803 | R136: 0.379756 | S136: 31804 | AF136: 345
F137: 1.0848925 | G137: 30382 | I137: 1.0848925 | J137: 30382 | L137: 0.277061 | M137: 31805 | O137: 0.19086 | P137: 31800 | R137: 0.32629 | S137: 31801 | AF137: 378
F138: 1.05 | G138: 31234 | I138: 0.91235161 | J138: 30381 | L138: 0.221666 | M138: 31802 | AF138: 856
F139: 0.91235161 | G139: 30381 | I139: 0.5244 | J139: 30383 | AF139: 929
F140: 0.660961 | G140: 30385 | I140: 0.435282 | J140: 30384 | AF140: 1258
F141: 0.5244 | G141: 30383
F142: 0.435282 | G142: 30384
F143: 0.38879 | G143: 30386
F144: 0.379756 | G144: 31804
F145: 0.32629 | G145: 31801
F146: 0.277061 | G146: 31805
F147: 0.246299 | G147: 31803
F148: 0.221666 | G148: 31802
F149: 0.19086 | G149: 31800
F150: 0.0785222 | G150: 30725

Sheet Cement_and_Mortar
A1: THESE ROWS AND COLUMNS WILL BE HIDDEN - They contain update notes and information for lookup calculations
F2: SELECT Material | G2: Cement | I2: Hide these rows, used for lookup formulas
F3: Sheet name | G3: =MID(CELL("filename",A1),FIND("]",CELL("filename",A1))+1,255) -> Cement_and_Mortar
F4: Workbook name | G4: =MID(CELL("filename",A1),FIND("[",CELL("filename",A1))+1,FIND("]", CELL("filename",A1))-FIND("[",CELL("filename",A1))-1) -> ICE DB Educational V4.1 - Oct 2025.xlsx
B6: Edit Title Manually | F6: Material Profile: Cement & Mortar
F7: ICE DB Version: | G7: =Miscellaneous!$E$3 -> V4.1 - Oct 2025 | J7: Check this link to see when the material profile was last updated
F8: To access this material profile, please register and download the Advanced version for free, with the link below:
F9: http://www.circularecology.com/embodied-energy-and-carbon-footprint-database.html
B10: Update URL Manually | F10: For further information on this material, please visit this page: | H10: INSERT LINK TO WEBPAGE…
F117: The below will be deleted before sending externally
F119: NOTES: Check the slicers are on the correct materials | I119: All Data Points Pivot Tables | L119: All Data Points Pivot Tables | R119: All Data Points Pivot Tables | Y119: All Data Points Pivot Tables | AG119: Reference Lookup Pivot Table
F121: Number 1 | G121: =#REF! -> #REF! | I121: Number 2 | J121: =#REF! -> #REF! | L121: Number 3 | M121: =#REF! -> #REF! | O121: Number 4 | P121: =#REF! -> #REF! | R121: Number 5 | S121: =#REF! -> #REF! | U121: Number 6 | V121: =#REF! -> #REF! | X121: Number 7 | Y121: =#REF! -> #REF! | AA121: Number 8 | AB121: =#REF! -> #REF!
F133: Paste below per kg Embodied Carbon | I133: Paste below per kg Embodied Carbon | L133: Paste below per kg Embodied Carbon | O133: Paste below per kg Embodied Carbon | R133: Paste below per kg Embodied Carbon | U133: Paste below per kg Embodied Carbon | X133: Paste below per kg Embodied Carbon | AA133: Paste below per kg Embodied Carbon | AF133: Paste below reference numbers, filtered by this material
B134: Headers in this row | F134: Per kg. Embodied Carbon (kg CO2/kg) | G134: Data Point Number | I134: Per kg. Embodied Carbon (kg CO2/kg) | J134: Data Point Number | L134: Per kg. Embodied Carbon (kg CO2/kg) | M134: Data Point Number | O134: Per kg. Embodied Carbon (kg CO2/kg) | P134: Data Point Number | R134: Per kg. Embodied Carbon (kg CO2/kg) | S134: Data Point Number | U134: Per kg. Embodied Carbon (kg CO2/kg) | V134: Data Point Number | X134: Per kg. Embodied Carbon (kg CO2/kg) | Y134: Data Point Number | AA134: Per kg. Embodied Carbon (kg CO2/kg) | AB134: Data Point Number | AF134: Row Labels
B135: Start data from this row | F135: 2.67 | G135: 31557 | I135: 1.11 | J135: 30147 | L135: 1.812 | M135: 30882 | O135: 2.67 | P135: 31557 | R135: 0.156 | S135: 30191 | U135: 0.93 | V135: 30726 | X135: 0.55378692 | Y135: 30387 | AA135: 0.156 | AB135: 30191 | AF135: 346
F136: 2.28 | G136: 31553 | I136: 1.11 | J136: 30148 | L136: 1.5782 | M136: 30880 | O136: 2.28 | P136: 31553 | R136: 0.14056399 | S136: 31545 | U136: 0.465 | V136: 30727 | AA136: 0.14056399 | AB136: 31545 | AF136: 347
F137: 1.88 | G137: 31554 | I137: 1.11 | J137: 30149 | L137: 1.1735 | M137: 30881 | O137: 1.88 | P137: 31554 | R137: 0.123 | S137: 30192 | U137: 0.465 | V137: 30729 | AA137: 0.123 | AB137: 30192 | AF137: 348
F138: 1.812 | G138: 30882 | I138: 1.11 | J138: 30150 | L138: 0.86827 | M138: 30166 | O138: 1.33 | P138: 31556 | R138: 0.111 | S138: 30193 | AA138: 0.111 | AB138: 30193 | AF138: 349
F139: 1.5782 | G139: 30880 | I139: 1.11 | J139: 30151 | L139: 0.83 | M139: 31551 | O139: 1.31 | P139: 31555 | AF139: 350
F140: 1.33 | G140: 31556 | I140: 1.11 | J140: 30152 | L140: 0.808791 | M140: 30167 | O140: 0.527 | P140: 31552 | AF140: 352
F141: 1.31 | G141: 31555 | I141: 1.11 | J141: 30153 | L141: 0.791428 | M141: 30168 | AF141: 353
F142: 1.1735 | G142: 30881 | I142: 1.11 | J142: 30732 | L142: 0.777884 | M142: 30169 | AF142: 354
F143: 1.11 | G143: 30147 | I143: 1.11 | J143: 30733 | L143: 0.734711 | M143: 30170 | AF143: 355
F144: 1.11 | G144: 30148 | I144: 1.11 | J144: 30734 | L144: 0.721237 | M144: 30171 | AF144: 502
F145: 1.11 | G145: 30149 | I145: 0.93 | J145: 30154 | L145: 0.71973 | M145: 30172 | AF145: 929
F146: 1.11 | G146: 30150 | I146: 0.93 | J146: 30155 | L146: 0.587 | M146: 30730 | AF146: 1167
F147: 1.11 | G147: 30151 | I147: 0.93 | J147: 30156 | L147: 0.390808 | M147: 30188 | AF147: 1173
F148: 1.11 | G148: 30152 | I148: 0.93 | J148: 30157 | L148: 0.373444 | M148: 30189 | AF148: 1174
F149: 1.11 | G149: 30153 | I149: 0.93 | J149: 30158 | AF149: 1175
F150: 1.11 | G150: 30732 | I150: 0.93 | J150: 30159 | AF150: 1176
F151: 1.11 | G151: 30733 | I151: 0.93 | J151: 30160 | AF151: 1177
F152: 1.11 | G152: 30734 | I152: 0.93 | J152: 30161 | AF152: 1178
F153: 0.93 | G153: 30154 | I153: 0.93 | J153: 30162 | AF153: 1179
F154: 0.93 | G154: 30155 | I154: 0.93 | J154: 30163 | AF154: 29386
F155: 0.93 | G155: 30156 | I155: 0.93 | J155: 30164 | AF155: 29387
F156: 0.93 | G156: 30157 | I156: 0.93 | J156: 30165
F157: 0.93 | G157: 30158 | I157: 0.578 | J157: 30173
F158: 0.93 | G158: 30159 | I158: 0.506 | J158: 30174
F159: 0.93 | G159: 30160 | I159: 0.502586 | J159: 30175
F160: 0.93 | G160: 30161 | I160: 0.465 | J160: 30176
F161: 0.93 | G161: 30162 | I161: 0.465 | J161: 30177
F162: 0.93 | G162: 30163 | I162: 0.465 | J162: 30178
F163: 0.93 | G163: 30164 | I163: 0.465 | J163: 30179
F164: 0.93 | G164: 30165 | I164: 0.465 | J164: 30180
F165: 0.93 | G165: 30726 | I165: 0.465 | J165: 30181
F166: 0.86827 | G166: 30166 | I166: 0.465 | J166: 30182
F167: 0.83 | G167: 31551 | I167: 0.465 | J167: 30183
... F176: 0.55378692 | G176: 30387 | I176: 0.0877 | J176: 30194
F177: 0.527 | G177: 31552
F178: 0.506 | G178: 30174
F179: 0.502586 | G179: 30175
F180: 0.465 | G180: 30176
F181: 0.465 | G181: 30177
F182: 0.465 | G182: 30178
F183: 0.465 | G183: 30179
F184: 0.465 | G184: 30180
F185: 0.465 | G185: 30181
F186: 0.465 | G186: 30182
F187: 0.465 | G187: 30183
F188: 0.465 | G188: 30184
... F204: 0.0877 | G204: 30194

Sheet Ceramic
A1: THESE ROWS AND COLUMNS WILL BE HIDDEN - They contain update notes and information for lookup calculations
F2: SELECT Material | G2: Ceramic | I2: Hide these rows, used for lookup formulas
F3: Sheet name | G3: =MID(CELL("filename",A1),FIND("]",CELL("filename",A1))+1,255) -> Ceramic
F4: Workbook name | G4: =MID(CELL("filename",A1),FIND("[",CELL("filename",A1))+1,FIND("]", CELL("filename",A1))-FIND("[",CELL("filename",A1))-1) -> ICE DB Educational V4.1 - Oct 2025.xlsx
B6: Edit Title Manually | F6: Material Profile: Ceramic
F7: ICE DB Version: | G7: =Miscellaneous!$E$3 -> V4.1 - Oct 2025 | J7: Check this link to see when the material profile was last updated
F8: To access this material profile, please register and download the Advanced version for free, with the link below:
F9: http://www.circularecology.com/embodied-energy-and-carbon-footprint-database.html
B10: Update URL Manually | F10: For further information on this material, please visit this page: | H10: INSERT LINK TO WEBPAGE…
F119: The below will be deleted before sending externally
F121: NOTES: Check the slicers are on the correct materials | I121: All Data Points Pivot Tables | L121: All Data Points Pivot Tables | R121: All Data Points Pivot Tables | Y121: All Data Points Pivot Tables | AG121: Reference Lookup Pivot Table
F123: Number 1 | G123: =#REF! -> #REF! | I123: Number 2 | J123: =#REF! -> #REF! | L123: Number 3 | M123: =#REF! -> #REF! | O123: Number 4 | P123: =#REF! -> #REF! | R123: Number 5 | S123: =#REF! -> #REF! | U123: Number 6 | V123: =#REF! -> #REF! | X123: Number 7 | Y123: =#REF! -> #REF! | AA123: Number 8 | AB123: =#REF! -> #REF!
F135: Paste below per kg Embodied Carbon | I135: Paste below per kg Embodied Carbon | L135: Paste below per kg Embodied Carbon | O135: Paste below per kg Embodied Carbon | R135: Paste below per kg Embodied Carbon | U135: Paste below per kg Embodied Carbon | X135: Paste below per kg Embodied Carbon | AA135: Paste below per kg Embodied Carbon | AF135: Paste below reference numbers, filtered by this material
B136: Headers in this row | F136: Per kg. Embodied Carbon (kg CO2/kg) | G136: Data Point Number | I136: Per kg. Embodied Carbon (kg CO2/kg) | J136: Data Point Number | L136: Per kg. Embodied Carbon (kg CO2/kg) | M136: Data Point Number | O136: Per kg. Embodied Carbon (kg CO2/kg) | P136: Data Point Number | R136: Per kg. Embodied Carbon (kg CO2/kg) | S136: Data Point Number | AF136: Row Labels
B137: Start data from this row | F137: 3.272 | G137: 57422 | I137: 1.8780488 | J137: 44330 | L137: 2.8112245 | M137: 32500 | O137: 3.272 | P137: 57422 | R137: 0.255 | S137: 30390 | AF137: 929
F138: 2.8112245 | G138: 32500 | I138: 1.3076923 | J138: 56228 | L138: 2.80282 | M138: 30388 | O138: 2.6124075 | P138: 47542 | AF138: 2101
F139: 2.80282 | G139: 30388 | I139: 1.2326148 | J139: 41150 | L139: 2.7715076 | M139: 32907 | O139: 1.4555256 | P139: 54820 | AF139: 2314
F140: 2.7715076 | G140: 32907 | I140: 1.2290546 | J140: 54079 | L140: 2.653 | M140: 76347 | O140: 1.4552772 | P140: 53523 | AF140: 2315
F141: 2.653 | G141: 76347 | I141: 1.2235294 | J141: 43383 | L141: 2.3889061 | M141: 56609 | O141: 1.3924078 | P141: 54821 | AF141: 2316
F142: 2.6124075 | G142: 47542 | I142: 1.1489362 | J142: 31830 | L142: 2.2184087 | M142: 32498 | O142: 1.3787234 | P142: 53524 | AF142: 2317
F143: 2.3889061 | G143: 56609 | I143: 1.1489362 | J143: 56563 | L143: 2.21 | M143: 75223 | O143: 1.3571429 | P143: 44311 | AF143: 2318
F144: 2.2184087 | G144: 32498 | I144: 1.0092395 | J144: 45924 | L144: 2.0180995 | M144: 32505 | O144: 1.3494856 | P144: 47552 | AF144: 2319
F145: 2.21 | G145: 75223 | I145: 0.99649123 | J145: 31834 | L145: 1.9949622 | M145: 32499 | O145: 1.0804054 | P145: 51745 | AF145: 2553
F146: 2.0180995 | G146: 32505 | I146: 0.9795082 | J146: 44958 | L146: 1.9808307 | M146: 32528 | O146: 1.0804054 | P146: 51750 | AF146: 2556
F147: 1.9949622 | G147: 32499 | I147: 0.93205128 | J147: 44963 | L147: 1.9005 | M147: 71507 | O147: 1.0728916 | P147: 54822 | AF147: 2557
F148: 1.9808307 | G148: 32528 | I148: 0.91456311 | J148: 31837 | L148: 1.74 | M148: 55441 | O148: 1.0728916 | P148: 57110 | AF148: 2620
F149: 1.9005 | G149: 71507 | I149: 0.88658537 | J149: 41146 | L149: 1.7223 | M149: 71304 | O149: 1.0714286 | P149: 53522 | AF149: 2621
... F155: 1.5058 | G155: 75398 | I155: 0.79650811 | J155: 45479 | L155: 0.5126 | M155: 56693 | O155: 0.88507265 | P155: 54819 | AF155: 2943
F156: 1.5 | G156: 55440 | I156: 0.7877551 | J156: 48073 | O156: 0.8560477 | P156: 45480 | AF156: 2944
F157: 1.4555256 | G157: 54820 | I157: 0.71428571 | J157: 41148 | O157: 0.85590189 | P157: 42849 | AF157: 2945
F158: 1.4552772 | G158: 53523 | I158: 0.69189189 | J158: 31831 | O158: 0.84579439 | P158: 32654 | AF158: 2946
F159: 1.3924078 | G159: 54821 | I159: 0.68965517 | J159: 41149 | O159: 0.81120732 | P159: 42844 | AF159: 2947
F160: 1.3787234 | G160: 53524 | I160: 0.68444444 | J160: 32384 | O160: 0.80388476 | P160: 32655 | AF160: 2949
F161: 1.3571429 | G161: 44311 | I161: 0.68444444 | J161: 42532 | O161: 0.80388476 | P161: 32660 | AF161: 3222
F162: 1.3494856 | G162: 47552 | I162: 0.67804878 | J162: 31832 | O162: 0.80216059 | P162: 32656 | AF162: 3223
F163: 1.3076923 | G163: 56228 | I163: 0.64417178 | J163: 43380 | O163: 0.80037634 | P163: 32514 | AF163: 3896
F164: 1.2326148 | G164: 41150 | I164: 0.64193548 | J164: 31835 | O164: 0.79970083 | P164: 54078 | AF164: 3897
F165: 1.2290546 | G165: 54079 | I165: 0.63636364 | J165: 32389 | O165: 0.79970083 | P165: 42833 | AF165: 3904
F166: 1.2235294 | G166: 43383 | I166: 0.63636364 | J166: 42720 | O166: 0.79970083 | P166: 45474 | AF166: 3916
F167: 1.1489362 | G167: 31830 | I167: 0.62242651 | J167: 42840 | O167: 0.76344086 | P167: 42835 | AF167: 3922
... F187: 0.85590189 | G187: 42849 | I187: 0.45022624 | J187: 55790 | O187: 0.61349693 | P187: 69352 | AF187: 11026
F188: 0.84736741 | G188: 42851 | O188: 0.61349693 | P188: 69354 | AF188: 11027
F189: 0.84680851 | G189: 42841 | O189: 0.61349693 | P189: 69360 | AF189: 11028
F190: 0.84579439 | G190: 32654 | O190: 0.61349693 | P190: 69363 | AF190: 11090
F191: 0.81120732 | G191: 42844 | O191: 0.61226994 | P191: 55817 | AF191: 11099
F192: 0.80388476 | G192: 32655 | O192: 0.61226994 | P192: 55826 | AF192: 11100
F193: 0.80388476 | G193: 32660 | O193: 0.61226994 | P193: 55861 | AF193: 11101
F194: 0.80216059 | G194: 32656 | O194: 0.58901099 | P194: 54081 | AF194: 11102
F195: 0.80037634 | G195: 32514 | O195: 0.58831263 | P195: 66297 | AF195: 11337
F196: 0.79970083 | G196: 54078 | O196: 0.58733625 | P196: 54084 | AF196: 11353
F197: 0.79970083 | G197: 42833 | O197: 0.58367204 | P197: 42839 | AF197: 11619
F198: 0.79970083 | G198: 45474 | O198: 0.58223684 | P198: 55833 | AF198: 11620
F199: 0.79654074 | G199: 42842 | O199: 0.57 | P199: 70267 | AF199: 11621
... F217: 0.72857143 | G217: 42536 | O217: 0.26872247 | P217: 32517 | AF217: 13046
F218: 0.7281768 | G218: 33004 | AF218: 13067
F219: 0.727 | G219: 71479 | AF219: 13114
F220: 0.71428571 | G220: 41148 | AF220: 13115
F221: 0.69403049 | G221: 32658 | AF221: 13149
F222: 0.69378016 | G222: 30197 | AF222: 13150
F223: 0.69189189 | G223: 31831 | AF223: 13151
F224: 0.68965517 | G224: 41149 | AF224: 13152
F225: 0.68444444 | G225: 32384 | AF225: 13153
F226: 0.68444444 | G226: 42532 | AF226: 13155
F227: 0.67804878 | G227: 31832 | AF227: 13156
F228: 0.64417178 | G228: 43380 | AF228: 13165
F229: 0.64193548 | G229: 31835 | AF229: 13213
... F266: 0.5126 | G266: 56693 | AF266: 29188
F267: 0.51236749 | G267: 32641
F268: 0.50595238 | G268: 48102
F269: 0.48823949 | G269: 32953
F270: 0.48369565 | G270: 69651
F271: 0.47808765 | G271: 32912
F272: 0.47808765 | G272: 43381
F273: 0.47420635 | G273: 54089
F274: 0.45909091 | G274: 32385
F275: 0.45248869 | G275: 69351
F276: 0.45248869 | G276: 69356
F277: 0.45022624 | G277: 55785
F278: 0.45022624 | G278: 55787
... F287: 0.26872247 | G287: 32517

Sheet Clay_Bricks
A1: THESE ROWS AND COLUMNS WILL BE HIDDEN - They contain update notes and information for lookup calculations
F2: SELECT Material | G2: Clay | I2: Hide these rows, used for lookup formulas
F3: Sheet name | G3: =MID(CELL("filename",A1),FIND("]",CELL("filename",A1))+1,255) -> Clay_Bricks
F4: Workbook name | G4: =MID(CELL("filename",A1),FIND("[",CELL("filename",A1))+1,FIND("]", CELL("filename",A1))-FIND("[",CELL("filename",A1))-1) -> ICE DB Educational V4.1 - Oct 2025.xlsx
B6: Edit Title Manually | F6: Material Profile: Clay Bricks
F7: ICE DB Version: | G7: =Miscellaneous!$E$3 -> V4.1 - Oct 2025 | J7: Check this link to see when the material profile was last updated
F8: To access this material profile, please register and download the Advanced version for free, with the link below:
F9: http://www.circularecology.com/embodied-energy-and-carbon-footprint-database.html
B10: Update URL Manually | F10: For further information on this material, please visit this page: | H10: INSERT LINK TO WEBPAGE…
F118: The below will be deleted before sending externally
F120: NOTES: Check the slicers are on the correct materials | I120: All Data Points Pivot Tables | L120: All Data Points Pivot Tables | R120: All Data Points Pivot Tables | Y120: All Data Points Pivot Tables | AG120: Reference Lookup Pivot Table
F122: Number 1 | G122: =#REF! -> #REF! | I122: Number 2 | J122: =#REF! -> #REF! | L122: Number 3 | M122: =#REF! -> #REF! | O122: Number 4 | P122: =#REF! -> #REF! | R122: Number 5 | S122: =#REF! -> #REF! | U122: Number 6 | V122: =#REF! -> #REF! | X122: Number 7 | Y122: =#REF! -> #REF! | AA122: Number 8 | AB122: =#REF! -> #REF!
F134: Paste below per kg Embodied Carbon | I134: Paste below per kg Embodied Carbon | L134: Paste below per kg Embodied Carbon | O134: Paste below per kg Embodied Carbon | R134: Paste below per kg Embodied Carbon | U134: Paste below per kg Embodied Carbon | X134: Paste below per kg Embodied Carbon | AA134: Paste below per kg Embodied Carbon | AF134: Paste below reference numbers, filtered by this material
B135: Headers in this row | F135: Per kg. Embodied Carbon (kg CO2/kg) | G135: Data Point Number | I135: Per kg. Embodied Carbon (kg CO2/kg) | J135: Data Point Number | L135: Per kg. Embodied Carbon (kg CO2/kg) | M135: Data Point Number | O135: Per kg. Embodied Carbon (kg CO2/kg) | P135: Data Point Number | R135: Per kg. Embodied Carbon (kg CO2/kg) | S135: Data Point Number | AF135: Row Labels
B136: Start data from this row | F136: 0.354 | G136: 31527 | I136: 0.354 | J136: 31527 | L136: 0.29988111 | M136: 30198 | O136: 0.30782609 | P136: 30200 | R136: 0.255 | S136: 30390 | AF136: 390
F137: 0.313 | G137: 31525 | I137: 0.313 | J137: 31525 | L137: 0.255549 | M137: 30199 | AF137: 396
F138: 0.30782609 | G138: 30200 | I138: 0.283 | J138: 31529 | L138: 0.23858998 | M138: 30391 | AF138: 929
F139: 0.29988111 | G139: 30198 | I139: 0.246 | J139: 31524 | L139: 0.23826755 | M139: 30392 | AF139: 930
F140: 0.283 | G140: 31529 | I140: 0.2405113 | J140: 30201 | L140: 0.213 | M140: 31782 | AF140: 1146
F141: 0.255549 | G141: 30199 | I141: 0.24033979 | J141: 30389 | L141: 0.195 | M141: 31622 | AF141: 444
F142: 0.255 | G142: 30390 | I142: 0.226 | J142: 31528 | AF142: 1256
F143: 0.246 | G143: 31524 | I143: 0.179 | J143: 31526
F144: 0.2405113 | G144: 30201
F145: 0.24033979 | G145: 30389
F146: 0.23858998 | G146: 30391
F147: 0.23826755 | G147: 30392
F148: 0.226 | G148: 31528
F149: 0.213 | G149: 31782
F150: 0.195 | G150: 31622
F151: 0.179 | G151: 31526

Sheet Concrete
A1: THESE ROWS AND COLUMNS WILL BE HIDDEN - They contain update notes and information for lookup calculations
F2: SELECT Material | G2: Concrete | I2: Hide these rows, used for lookup formulas
F3: Sheet name | G3: =MID(CELL("filename",A1),FIND("]",CELL("filename",A1))+1,255) -> Concrete
F4: Workbook name | G4: =MID(CELL("filename",A1),FIND("[",CELL("filename",A1))+1,FIND("]", CELL("filename",A1))-FIND("[",CELL("filename",A1))-1) -> ICE DB Educational V4.1 - Oct 2025.xlsx
B6: Edit Title Manually | F6: Material Profile: Concrete
F7: ICE DB Version: | G7: =Miscellaneous!$E$3 -> V4.1 - Oct 2025 | J7: Check this link to see when the material profile was last updated
F8: To access this material profile, please register and download the Advanced version for free, with the link below:
F9: http://www.circularecology.com/embodied-energy-and-carbon-footprint-database.html
B10: Update URL Manually | F10: For further information on this material, please visit this page: | H10: INSERT LINK TO WEBPAGE…
F118: The below will be deleted before sending externally
F120: NOTES: Check the slicers are on the correct materials | I120: All Data Points Pivot Tables | L120: All Data Points Pivot Tables | R120: All Data Points Pivot Tables | Y120: All Data Points Pivot Tables | AG120: Reference Lookup Pivot Table
F122: Number 1 | G122: =#REF! -> #REF! | I122: Number 2 | J122: =#REF! -> #REF! | L122: Number 3 | M122: =#REF! -> #REF! | O122: Number 4 | P122: =#REF! -> #REF! | R122: Number 5 | S122: =#REF! -> #REF! | U122: Number 6 | V122: =#REF! -> #REF! | X122: Number 7 | Y122: =#REF! -> #REF! | AA122: Number 8 | AB122: =#REF! -> #REF!
F134: Paste below per kg Embodied Carbon | I134: Paste below per kg Embodied Carbon | L134: Paste below per kg Embodied Carbon | O134: Paste below per kg Embodied Carbon | R134: Paste below per kg Embodied Carbon | U134: Paste below per kg Embodied Carbon | X134: Paste below per kg Embodied Carbon | AA134: Paste below per kg Embodied Carbon | AF134: Paste below reference numbers, filtered by this material
B135: Headers in this row | F135: Per kg. Embodied Carbon (kg CO2/kg) | G135: Data Point Number | I135: Per kg. Embodied Carbon (kg CO2/kg) | J135: Data Point Number | L135: Per kg. Embodied Carbon (kg CO2/kg) | M135: Data Point Number | O135: Per kg. Embodied Carbon (kg CO2/kg) | P135: Data Point Number | R135: Per kg. Embodied Carbon (kg CO2/kg) | S135: Data Point Number | AF135: Row Labels
B136: Start data from this row | F136: 0.55823455 | G136: 30224 | I136: 0.16518047 | J136: 30146 | L136: 0.36630339 | M136: 30402 | O136: 0.55823455 | P136: 30224 | R136: 0.11728395 | S136: 30746 | AF136: 330
F137: 0.531242 | G137: 30223 | I137: 0.16130435 | J137: 31538 | L137: 0.3238388 | M137: 30393 | O137: 0.531242 | P137: 30223 | AF137: 331
F138: 0.50587013 | G138: 30834 | I138: 0.15521739 | J138: 31539 | L138: 0.29018182 | M138: 31390 | O138: 0.50587013 | P138: 30834 | AF138: 365
F139: 0.48158158 | G139: 30222 | I139: 0.13945833 | J139: 30218 | L139: 0.28 | M139: 31565 | O139: 0.48158158 | P139: 30222 | AF139: 366
F140: 0.47343432 | G140: 30221 | I140: 0.13249476 | J140: 30145 | L140: 0.27774173 | M140: 31564 | O140: 0.47343432 | P140: 30221 | AF140: 381
F141: 0.36630339 | G141: 30402 | I141: 0.13249476 | J141: 30745 | L141: 0.21374545 | M141: 31384 | O141: 0.33879792 | P141: 30220 | AF141: 382
F142: 0.33879792 | G142: 30220 | I142: 0.13133047 | J142: 31546 | L142: 0.20641667 | M142: 31385 | AF142: 383
F143: 0.3238388 | G143: 30393 | I143: 0.13054167 | J143: 30217 | L143: 0.2055375 | M143: 31382 | AF143: 384
F144: 0.29018182 | G144: 31390 | I144: 0.12123475 | J144: 30216 | L144: 0.19735333 | M144: 31386 | AF144: 456
F145: 0.28 | G145: 31565 | I145: 0.11045833 | J145: 30215 | L145: 0.19418182 | M145: 31383 | AF145: 496
F146: 0.27774173 | G146: 31564 | I146: 0.10652174 | J146: 31537 | L146: 0.18625 | M146: 31570 | AF146: 497
F147: 0.21374545 | G147: 31384 | I147: 0.10434783 | J147: 31536 | L147: 0.18426 | M147: 30764 | AF147: 498
F148: 0.20641667 | G148: 31385 | I148: 0.10347826 | J148: 30875 | L148: 0.1831 | M148: 30219 | AF148: 499
F149: 0.2055375 | G149: 31382 | I149: 0.10336134 | J149: 31572 | L149: 0.1770428 | M149: 30893 | AF149: 500
F150: 0.19735333 | G150: 31386 | I150: 0.097817797 | J150: 30214 | L150: 0.17679474 | M150: 31388 | AF150: 514
F151: 0.19418182 | G151: 31383 | I151: 0.096625 | J151: 30212 | L151: 0.17622568 | M151: 30894 | AF151: 929
F152: 0.18625 | G152: 31570 | I152: 0.092608696 | J152: 30874 | L152: 0.17187202 | M152: 30400 | AF152: 1003
F153: 0.18426 | G153: 30764 | I153: 0.087958333 | J153: 30211 | L153: 0.17187202 | M153: 30401 | AF153: 1004
... F157: 0.17622568 | G157: 30894 | I157: 0.064782609 | J157: 30876 | L157: 0.15064 | M157: 31389 | AF157: 1160
F158: 0.17187202 | G158: 30400 | L158: 0.14892086 | M158: 30892 | AF158: 1161
F159: 0.17187202 | G159: 30401 | L159: 0.14512 | M159: 30398 | AF159: 1168
F160: 0.16733333 | G160: 31569 | L160: 0.13648919 | M160: 30397 | AF160: 1184
F161: 0.16518047 | G161: 30146 | L161: 0.13648095 | M161: 30396 | AF161: 1185
F162: 0.16364737 | G162: 31387 | L162: 0.13493 | M162: 30395 | AF162: 1186
F163: 0.1628855 | G163: 30399 | L163: 0.13394 | M163: 30763 | AF163: 1187
F164: 0.16130435 | G164: 31538 | L164: 0.131 | M164: 31567 | AF164: 1188
F165: 0.15521739 | G165: 31539 | L165: 0.1236855 | M165: 30394 | AF165: 1189
F166: 0.15064 | G166: 31389 | L166: 0.11781377 | M166: 30762 | AF166: 1190
F167: 0.14892086 | G167: 30892 | L167: 0.11044 | M167: 30761 | AF167: 1191
F168: 0.14512 | G168: 30398 | L168: 0.10965517 | M168: 31530
F169: 0.13945833 | G169: 30218 | L169: 0.097142857 | M169: 30213
F170: 0.13648919 | G170: 30397 | L170: 0.09122807 | M170: 31566
F171: 0.13648095 | G171: 30396 | L171: 0.086857143 | M171: 30210
F172: 0.13493 | G172: 30395 | L172: 0.080125 | M172: 30204
F173: 0.13394 | G173: 30763 | L173: 0.070571429 | M173: 30208
F174: 0.13249476 | G174: 30145 | L174: 0.061061224 | M174: 30207
F175: 0.13249476 | G175: 30745 | L175: 0.059183673 | M175: 30206
F176: 0.13133047 | G176: 31546 | L176: 0.05847619 | M176: 30205
F177: 0.131 | G177: 31567 | L177: 0.044891443 | M177: 31568
F178: 0.13054167 | G178: 30217 | L178: 0.04277551 | M178: 30203
F179: 0.1236855 | G179: 30394 | L179: 0.038583333 | M179: 31381
F180: 0.12123475 | G180: 30216 | L180: 0.033877551 | M180: 30202
F181: 0.11781377 | G181: 30762
F182: 0.11728395 | G182: 30746
F183: 0.11045833 | G183: 30215
F184: 0.11044 | G184: 30761
F185: 0.10965517 | G185: 31530
F186: 0.10652174 | G186: 31537
F187: 0.10434783 | G187: 31536
F188: 0.10347826 | G188: 30875
F189: 0.10336134 | G189: 31572
F190: 0.097817797 | G190: 30214
F191: 0.097142857 | G191: 30213
F192: 0.096625 | G192: 30212
... F209: 0.033877551 | G209: 30202

Sheet Glass
A1: THESE ROWS AND COLUMNS WILL BE HIDDEN - They contain update notes and information for lookup calculations
F2: SELECT Material | G2: Glass | I2: Hide these rows, used for lookup formulas
F3: Sheet name | G3: =MID(CELL("filename",A1),FIND("]",CELL("filename",A1))+1,255) -> Glass
F4: Workbook name | G4: =MID(CELL("filename",A1),FIND("[",CELL("filename",A1))+1,FIND("]", CELL("filename",A1))-FIND("[",CELL("filename",A1))-1) -> ICE DB Educational V4.1 - Oct 2025.xlsx
B6: Edit Title Manually | F6: Material Profile: Glass
F7: ICE DB Version: | G7: =Miscellaneous!$E$3 -> V4.1 - Oct 2025 | J7: Check this link to see when the material profile was last updated
F8: To access this material profile, please register and download the Advanced version for free, with the link below:
F9: http://www.circularecology.com/embodied-energy-and-carbon-footprint-database.html
B10: Update URL Manually | F10: For further information on this material, please visit this page: | H10: INSERT LINK TO WEBPAGE…
F118: The below will be deleted before sending externally
I120: All Data Points Pivot Tables | L120: All Data Points Pivot Tables | R120: All Data Points Pivot Tables | Y120: All Data Points Pivot Tables | AG120: Reference Lookup Pivot Table
F122: Number 1 | G122: =#REF! -> #REF! | I122: Number 2 | J122: =#REF! -> #REF! | L122: Number 3 | M122: =#REF! -> #REF! | O122: Number 4 | P122: =#REF! -> #REF! | R122: Number 5 | S122: =#REF! -> #REF! | U122: Number 6 | V122: =#REF! -> #REF! | X122: Number 7 | Y122: =#REF! -> #REF! | AA122: Number 8 | AB122: =#REF! -> #REF!
F134: Paste below per kg Embodied Carbon | I134: Paste below per kg Embodied Carbon | L134: Paste below per kg Embodied Carbon | O134: Paste below per kg Embodied Carbon | R134: Paste below per kg Embodied Carbon | U134: Paste below per kg Embodied Carbon | X134: Paste below per kg Embodied Carbon | AA134: Paste below per kg Embodied Carbon | AF134: Paste below reference numbers, filtered by this material
B135: Headers in this row | F135: Per kg. Embodied Carbon (kg CO2/kg) | G135: Data Point Number | I135: Per kg. Embodied Carbon (kg CO2/kg) | J135: Data Point Number | L135: Per kg. Embodied Carbon (kg CO2/kg) | M135: Data Point Number | O135: Per kg. Embodied Carbon (kg CO2/kg) | P135: Data Point Number | R135: Per kg. Embodied Carbon (kg CO2/kg) | S135: Data Point Number | U135: Per kg. Embodied Carbon (kg CO2/kg) | V135: Data Point Number | X135: Per kg. Embodied Carbon (kg CO2/kg) | Y135: Data Point Number | AA135: Per kg. Embodied Carbon (kg CO2/kg) | AB135: Data Point Number | AF135: Row Labels
B136: Start data from this row | F136: 5.0617063 | G136: 30769 | I136: 2.0266667 | J136: 31328 | L136: 2.44 | M136: 31479 | O136: 1.94 | P136: 31436 | R136: 1.738646 | S136: 31044 | U136: 2.2029412 | V136: 31322 | X136: 1.8701022 | Y136: 30409 | AF136: 389
F137: 4.1929739 | G137: 30770 | I137: 2 | J137: 31329 | L137: 2.2133333 | M137: 31480 | O137: 1.8187524 | P137: 30410 | R137: 1.6518987 | S137: 31467 | U137: 2.1340909 | V137: 31323 | X137: 1.8466667 | Y137: 31434 | AF137: 391
F138: 3.025512 | G138: 30771 | I138: 1.9542857 | J138: 31330 | L138: 2.08 | M138: 31481 | O138: 1.7 | P138: 31437 | R138: 1.5813953 | S138: 31468 | U138: 2.1 | V138: 31324 | X138: 1.7318436 | Y138: 31431 | AF138: 393
F139: 2.8853602 | G139: 30772 | I139: 1.91 | J139: 31331 | L139: 2.03 | M139: 31482 | O139: 1.6692913 | P139: 31438 | R139: 1.5573898 | S139: 31045 | U139: 2.0948718 | V139: 31325 | X139: 1.7033333 | Y139: 31435 | AF139: 394
F140: 2.5959917 | G140: 30407 | I140: 1.84 | J140: 31332 | L140: 1.928 | M140: 31483 | O140: 1.6623377 | P140: 31439 | R140: 1.5384615 | S140: 31469 | U140: 2.0119048 | V140: 31326 | X140: 1.6766667 | Y140: 31432 | AF140: 395
F141: 2.44 | G141: 31479 | I141: 1.7933333 | J141: 31333 | L141: 1.9 | M141: 31484 | O141: 1.6181102 | P141: 31362 | R141: 1.5064935 | S141: 31470 | U141: 1.9469388 | V141: 31327 | X141: 1.6533333 | Y141: 31433 | AF141: 397
F142: 2.3748534 | G142: 30408 | I142: 1.76 | J142: 31334 | L142: 1.89 | M142: 31413 | O142: 1.555 | P142: 31440 | R142: 1.4477612 | S142: 31471 | AF142: 509
F143: 2.2133333 | G143: 31480 | I143: 1.76 | J143: 31442 | L143: 1.8533333 | M143: 31485 | O143: 1.49 | P143: 31363 | R143: 1.4220779 | S143: 31472 | AF143: 666
F144: 2.2029412 | G144: 31322 | I144: 1.73 | J144: 31335 | L144: 1.808 | M144: 31414 | O144: 1.472 | P144: 31441 | AF144: 668
F145: 2.1340909 | G145: 31323 | I145: 1.7028571 | J145: 31336 | L145: 1.792 | M145: 31486 | O145: 1.3305085 | P145: 31166 | AF145: 677
F146: 2.1 | G146: 31324 | I146: 1.65 | J146: 31337 | L146: 1.765 | M146: 31487 | AF146: 788
F147: 2.0948718 | G147: 31325 | I147: 1.65 | J147: 31443 | L147: 1.76 | M147: 31415 | AF147: 929
F148: 2.08 | G148: 31481 | I148: 1.64 | J148: 31444 | L148: 1.76 | M148: 31416 | AF148: 944
F149: 2.03 | G149: 31482 | I149: 1.60358 | J149: 30411 | L149: 1.72 | M149: 31488 | AF149: 950
F150: 2.0266667 | G150: 31328 | I150: 1.5866667 | J150: 31473 | L150: 1.712 | M150: 31489 | AF150: 968
F151: 2.0119048 | G151: 31326 | I151: 1.576 | J151: 31338 | L151: 1.71 | M151: 31490 | AF151: 1035
F152: 2 | G152: 31329 | I152: 1.576 | J152: 31445 | L152: 1.695 | M152: 31417 | AF152: 1053
F153: 1.9542857 | G153: 31330 | I153: 1.56 | J153: 31346 | L153: 1.68 | M153: 31418 | AF153: 1058
F154: 1.9469388 | G154: 31327 | I154: 1.56 | J154: 31055 | L154: 1.6733333 | M154: 31491 | AF154: 1064
F155: 1.94 | G155: 31436 | I155: 1.56 | J155: 31347 | L155: 1.656 | M155: 31419 | AF155: 1089
F156: 1.928 | G156: 31483 | I156: 1.556 | J156: 31056 | L156: 1.64 | M156: 31492 | AF156: 1095
F157: 1.91 | G157: 31331 | I157: 1.555 | J157: 31057 | L157: 1.63 | M157: 31493 | AF157: 1101
F158: 1.9 | G158: 31484 | I158: 1.555 | J158: 31348 | L158: 1.6266667 | M158: 31420 | AF158: 1126
F159: 1.89 | G159: 31413 | I159: 1.5542857 | J159: 31058 | L159: 1.6266667 | M159: 31421
F160: 1.8701022 | G160: 30409 | I160: 1.5542857 | J160: 31349 | L160: 1.6084211 | M160: 31494
F161: 1.8533333 | G161: 31485 | I161: 1.5533333 | J161: 31059 | L161: 1.6 | M161: 31495
F162: 1.8466667 | G162: 31434 | I162: 1.5533333 | J162: 31060 | L162: 1.576 | M162: 31496
F163: 1.84 | G163: 31332 | I163: 1.5533333 | J163: 31350 | L163: 1.57 | M163: 31422
F164: 1.8187524 | G164: 30410 | I164: 1.552 | J164: 31351 | L164: 1.56 | M164: 31423
F165: 1.808 | G165: 31414 | I165: 1.552 | J165: 31360 | L165: 1.54 | M165: 31497
F166: 1.7933333 | G166: 31333 | I166: 1.55 | J166: 31361 | L166: 1.5333333 | M166: 31498
F167: 1.792 | G167: 31486 | I167: 1.5333333 | J167: 31339 | L167: 1.52 | M167: 31424
F168: 1.765 | G168: 31487 | I168: 1.5333333 | J168: 31446 | L168: 1.5066667 | M168: 31499
F169: 1.76 | G169: 31415 | I169: 1.53 | J169: 31447 | L169: 1.4933333 | M169: 31425
F170: 1.76 | G170: 31334 | I170: 1.52 | J170: 30887 | L170: 1.488 | M170: 31426
... F178: 1.71 | G178: 31490 | I178: 1.48 | J178: 31504 | L178: 1.3066667 | M178: 31430
F179: 1.7033333 | G179: 31435 | I179: 1.475 | J179: 31449
F180: 1.7028571 | G180: 31336 | I180: 1.47 | J180: 31340
F181: 1.7 | G181: 31437 | I181: 1.4666667 | J181: 31475
F182: 1.695 | G182: 31417 | I182: 1.464 | J182: 31450
F183: 1.68 | G183: 31418 | I183: 1.444 | J183: 31505
F184: 1.6766667 | G184: 31432 | I184: 1.44 | J184: 31476
F185: 1.6733333 | G185: 31491 | I185: 1.44 | J185: 31451
F186: 1.6692913 | G186: 31438 | I186: 1.436 | J186: 31341
F187: 1.6623377 | G187: 31439 | I187: 1.4305694 | J187: 30774
F188: 1.656 | G188: 31419 | I188: 1.43 | J188: 31506
F189: 1.6533333 | G189: 31433 | I189: 1.4178218 | J189: 30775
F190: 1.6518987 | G190: 31467 | I190: 1.4166667 | J190: 31452
... F244: 1.48 | G244: 31448 | I244: 0.92 | J244: 31006
F245: 1.48 | G245: 31504
F246: 1.4757895 | G246: 31500
F247: 1.475 | G247: 31449
F248: 1.472 | G248: 31441
F249: 1.47 | G249: 31340
F250: 1.4666667 | G250: 31475
F251: 1.464 | G251: 31450
F252: 1.4477612 | G252: 31471
F253: 1.444 | G253: 31505
F254: 1.44 | G254: 31427
F255: 1.44 | G255: 31476
F256: 1.44 | G256: 31451
... F324: 0.92 | G324: 31006

Sheet Insulation
A1: THESE ROWS AND COLUMNS WILL BE HIDDEN - They contain update notes and information for lookup calculations
F2: SELECT Material | G2: Insulation | I2: Hide these rows, used for lookup formulas
F3: Sheet name | G3: =MID(CELL("filename",A1),FIND("]",CELL("filename",A1))+1,255) -> Insulation
F4: Workbook name | G4: =MID(CELL("filename",A1),FIND("[",CELL("filename",A1))+1,FIND("]", CELL("filename",A1))-FIND("[",CELL("filename",A1))-1) -> ICE DB Educational V4.1 - Oct 2025.xlsx
B6: Edit Title Manually | F6: Material Profile: Insulation
F7: ICE DB Version: | G7: =Miscellaneous!$E$3 -> V4.1 - Oct 2025 | J7: Check this link to see when the material profile was last updated
F8: To access this material profile, please register and download the Advanced version for free, with the link below:
F9: http://www.circularecology.com/embodied-energy-and-carbon-footprint-database.html
B10: Update URL Manually | F10: For further information on this material, please visit this page: | H10: INSERT LINK TO WEBPAGE…
F119: The below will be deleted before sending externally
F121: NOTES: Check the slicers are on the correct materials | I121: All Data Points Pivot Tables | L121: All Data Points Pivot Tables | R121: All Data Points Pivot Tables | Y121: All Data Points Pivot Tables | AG121: Reference Lookup Pivot Table
F123: Number 1 | G123: =#REF! -> #REF! | I123: Number 2 | J123: =#REF! -> #REF! | L123: Number 3 | M123: =#REF! -> #REF! | O123: Number 4 | P123: =#REF! -> #REF! | R123: Number 5 | S123: =#REF! -> #REF! | U123: Number 6 | V123: =#REF! -> #REF! | X123: Number 7 | Y123: =#REF! -> #REF! | AA123: Number 8 | AB123: =#REF! -> #REF!
F135: Paste below per kg Embodied Carbon | I135: Paste below per kg Embodied Carbon | L135: Paste below per kg Embodied Carbon | O135: Paste below per kg Embodied Carbon | R135: Paste below per kg Embodied Carbon | U135: Paste below per kg Embodied Carbon | X135: Paste below per kg Embodied Carbon | AA135: Paste below per kg Embodied Carbon | AF135: Paste below reference numbers, filtered by this material
B136: Headers in this row | F136: Per kg. Embodied Carbon (kg CO2/kg) | G136: Data Point Number | I136: Per kg. Embodied Carbon (kg CO2/kg) | J136: Data Point Number | L136: Per kg. Embodied Carbon (kg CO2/kg) | M136: Data Point Number | O136: Per kg. Embodied Carbon (kg CO2/kg) | P136: Data Point Number | R136: Per kg. Embodied Carbon (kg CO2/kg) | S136: Data Point Number | U136: Per kg. Embodied Carbon (kg CO2/kg) | V136: Data Point Number | AF136: Row Labels
B137: Start data from this row | F137: 6.2724375 | G137: 30416 | I137: 3.8241758 | J137: 44485 | L137: 3.8040541 | M137: 44130 | O137: 3.9855072 | P137: 54935 | R137: 4.893617 | S137: 40818 | U137: 6.2724375 | V137: 30416 | AF137: 400
F138: 5.05 | G138: 53463 | I138: 3.8241758 | J138: 44489 | L138: 3.6545455 | M138: 42576 | O138: 3.9565217 | P138: 54934 | R138: 4.893617 | S138: 47956 | U138: 5.05 | V138: 53463 | AF138: 401
F139: 4.893617 | G139: 40818 | I139: 3.6388889 | J139: 45072 | L139: 3.6283784 | M139: 42436 | O139: 3.648855 | P139: 71867 | R139: 4.7177419 | S139: 55449 | U139: 4.6125 | V139: 56194 | AF139: 402
F140: 4.893617 | G140: 47956 | I140: 3.4 | J140: 42548 | L140: 3.6111111 | M140: 42578 | O140: 3.3617021 | P140: 51068 | R140: 4.5232558 | S140: 40427 | U140: 4.375 | V140: 56195 | AF140: 403
F141: 4.7177419 | G141: 55449 | I141: 3.3333333 | J141: 40570 | L141: 3.5944444 | M141: 42483 | O141: 3.3333333 | P141: 40934 | R141: 4.5232558 | S141: 32138 | U141: 4.2916667 | V141: 56196 | AF141: 404
F142: 4.6125 | G142: 56194 | I142: 3.255814 | J142: 45787 | L142: 3.5695652 | M142: 42581 | O142: 3.3333333 | P142: 41014 | R142: 4.5044248 | S142: 32139 | U142: 4.2335766 | V142: 57671 | AF142: 405
F143: 4.5232558 | G143: 40427 | I143: 3.1746032 | J143: 45770 | L143: 3.4630872 | M143: 44054 | O143: 3.3333333 | P143: 41015 | R143: 4.4354839 | S143: 48696 | U143: 4.198895 | V143: 57658 | AF143: 415
F144: 4.5232558 | G144: 32138 | I144: 3.0470348 | J144: 51464 | L144: 3.1690531 | M144: 72403 | O144: 3.3333333 | P144: 41017 | R144: 4.423284 | S144: 65794 | U144: 4.1598361 | V144: 57660 | AF144: 416
F145: 4.5044248 | G145: 32139 | I145: 3 | J145: 45973 | L145: 3.1557377 | M145: 73530 | O145: 3.3333333 | P145: 43541 | R145: 4.3618421 | S145: 53336 | U145: 4.1527446 | V145: 57659 | AF145: 417
F146: 4.4354839 | G146: 48696 | I146: 2.9760766 | J146: 48706 | L146: 3.1475599 | M146: 32212 | O146: 3.3333333 | P146: 43542 | R146: 4.3618421 | S146: 49299 | U146: 3.9716312 | V146: 57657 | AF146: 418
F147: 4.423284 | G147: 65794 | I147: 2.9760766 | J147: 49487 | L147: 3.137037 | M147: 48064 | O147: 3.3333333 | P147: 43991 | R147: 4.3618421 | S147: 32552 | AF147: 419
F148: 4.375 | G148: 56195 | I148: 2.9623968 | J148: 44050 | L148: 2.9829545 | M148: 44064 | O148: 3.3333333 | P148: 43992 | R148: 4.3618421 | S148: 32553 | AF148: 420
F149: 4.3618421 | G149: 53336 | I149: 2.9577922 | J149: 46170 | L149: 2.9829545 | M149: 44065 | O149: 3.3333333 | P149: 43993 | R149: 4.3333333 | S149: 40812 | AF149: 423
F150: 4.3618421 | G150: 49299 | I150: 2.9012534 | J150: 44049 | L150: 2.8571429 | M150: 44058 | O150: 3.3333333 | P150: 40945 | R150: 4.3333333 | S150: 40815 | AF150: 425
F151: 4.3618421 | G151: 32552 | I151: 2.785081 | J151: 43579 | L151: 2.8535032 | M151: 44056 | O151: 3.3333333 | P151: 41012 | R151: 4.3247423 | S151: 55087 | AF151: 435
F152: 4.3618421 | G152: 32553 | I152: 2.785081 | J152: 44125 | L152: 2.8535032 | M152: 44062 | O152: 3.3333333 | P152: 43994 | R152: 4.2888889 | S152: 47951 | AF152: 436
F153: 4.3333333 | G153: 40812 | I153: 2.7125 | J153: 44264 | L153: 2.8392857 | M153: 44063 | O153: 3.3333333 | P153: 43999 | R153: 4.2660099 | S153: 49301 | AF153: 437
F154: 4.3333333 | G154: 40815 | I154: 2.7083333 | J154: 45950 | L154: 2.8392857 | M154: 44066 | O154: 3.1423179 | P154: 72859 | R154: 4.2660099 | S154: 49300 | AF154: 438
F155: 4.3247423 | G155: 55087 | I155: 2.7020785 | J155: 42057 | L155: 2.75 | M155: 54865 | O155: 3.1268437 | P155: 41965 | R155: 4.2660099 | S155: 32554 | AF155: 929
F156: 4.2916667 | G156: 56196 | I156: 2.6062323 | J156: 49705 | L156: 2.7356557 | M156: 30783 | O156: 3.1130435 | P156: 53321 | R156: 4.2660099 | S156: 32555 | AF156: 2097
F157: 4.2888889 | G157: 47951 | I157: 2.5761124 | J157: 46209 | L157: 2.7180966 | M157: 30780 | O157: 3.0725462 | P157: 41964 | R157: 4.2540984 | S157: 49302 | AF157: 2103
F158: 4.2660099 | G158: 49301 | I158: 2.565 | J158: 68219 | L158: 2.7180966 | M158: 30781 | O158: 3.003663 | P158: 43387 | R158: 4.2540984 | S158: 32556 | AF158: 2161
... F173: 4.1527446 | G173: 57659 | I173: 2.2473868 | J173: 41010 | L173: 2.0947368 | M173: 49346 | O173: 2.927 | P173: 39356 | R173: 4.0232558 | S173: 43621 | AF173: 2347
F174: 4.1111111 | G174: 48112 | I174: 2.2414634 | J174: 41461 | L174: 1.9294118 | M174: 45438 | R174: 4.0232558 | S174: 43620 | AF174: 2348
F175: 4.0935449 | G175: 57087 | I175: 2.2269759 | J175: 46083 | L175: 1.9294118 | M175: 32176 | R175: 4.0023301 | S175: 71460 | AF175: 2349
F176: 4.0673491 | G176: 57083 | I176: 2.1825397 | J176: 45769 | L176: 1.8920863 | M176: 54963 | R176: 4 | S176: 32605 | AF176: 2350
F177: 4.0465116 | G177: 44741 | I177: 2.1793023 | J177: 33552 | L177: 1.8920863 | M177: 54964 | R177: 4 | S177: 32607 | AF177: 2351
F178: 4.0384615 | G178: 32610 | I178: 2.1665116 | J178: 51013 | L178: 1.8920863 | M178: 54966 | R178: 4 | S178: 32615 | AF178: 2352
F179: 4.0384615 | G179: 32613 | I179: 2.1645022 | J179: 45729 | L179: 1.8859223 | M179: 54978 | R179: 4 | S179: 32617 | AF179: 2353
F180: 4.0232558 | G180: 41082 | I180: 2.1501976 | J180: 42056 | L180: 1.8567961 | M180: 54984 | R180: 4 | S180: 56050 | AF180: 2354
F181: 4.0232558 | G181: 41875 | I181: 2.1501976 | J181: 49486 | L181: 1.8099548 | M181: 32647 | R181: 3.9953811 | S181: 40703 | AF181: 2357
F182: 4.0232558 | G182: 43621 | I182: 2.1428571 | J182: 40937 | L182: 1.780303 | M182: 49358 | R182: 3.9953811 | S182: 44005 | AF182: 2358
F183: 4.0232558 | G183: 43620 | I183: 2.1428571 | J183: 41011 | L183: 1.725 | M183: 45441 | R183: 3.9953811 | S183: 44006 | AF183: 2359
F184: 4.0023301 | G184: 71460 | I184: 2.1346544 | J184: 46084 | L184: 1.725 | M184: 32177 | R184: 3.9953811 | S184: 44007 | AF184: 2360
F185: 4 | G185: 32605 | I185: 2.12 | J185: 70211 | L185: 1.7066667 | M185: 32787 | R185: 3.97808 | S185: 47557 | AF185: 2361
... F230: 3.3867735 | G230: 41088 | I230: 1.6962025 | J230: 55736 | L230: 1.4413519 | M230: 44274 | R230: 1.1439329 | S230: 71845 | AF230: 3095
F231: 3.3617021 | G231: 51068 | I231: 1.6874327 | J231: 48213 | L231: 1.4388889 | M231: 56700 | AF231: 3098
F232: 3.3333333 | G232: 40570 | I232: 1.6796875 | J232: 42617 | L232: 1.4358974 | M232: 56705 | AF232: 3099
F233: 3.3333333 | G233: 40934 | I233: 1.6786571 | J233: 46216 | L233: 1.434555 | M233: 54807 | AF233: 3100
F234: 3.3333333 | G234: 41014 | I234: 1.6779661 | J234: 45977 | L234: 1.43 | M234: 71179 | AF234: 3101
F235: 3.3333333 | G235: 41015 | I235: 1.6752137 | J235: 32218 | L235: 1.4267016 | M235: 54983 | AF235: 3102
F236: 3.3333333 | G236: 41017 | I236: 1.6666667 | J236: 42413 | L236: 1.4212963 | M236: 40513 | AF236: 3104
F237: 3.3333333 | G237: 43541 | I237: 1.656051 | J237: 55699 | L237: 1.4172662 | M237: 54962 | AF237: 3105
F238: 3.3333333 | G238: 43542 | I238: 1.6448598 | J238: 39937 | L238: 1.4172662 | M238: 54965 | AF238: 3106
F239: 3.3333333 | G239: 43991 | I239: 1.6444444 | J239: 42467 | L239: 1.4136808 | M239: 40596 | AF239: 3107
F240: 3.3333333 | G240: 43992 | I240: 1.6375199 | J240: 55747 | L240: 1.3857143 | M240: 44299 | AF240: 3108
F241: 3.3333333 | G241: 43993 | I241: 1.626898 | J241: 55748 | L241: 1.3851852 | M241: 32197 | AF241: 3109
F242: 3.3333333 | G242: 40945 | I242: 1.626898 | J242: 55737 | L242: 1.3794872 | M242: 39233 | AF242: 3110
... F498: 1.4861461 | G498: 55721 | I498: 0.73214286 | J498: 45442 | L498: 0.88513513 | M498: 44824 | AF498: 19624
F499: 1.4845938 | G499: 55716 | L499: 0.8828125 | M499: 32829 | AF499: 19626
F500: 1.4814815 | G500: 46108 | L500: 0.87987988 | M500: 54990 | AF500: 19631
F501: 1.4814815 | G501: 55719 | L501: 0.87946429 | M501: 44328 | AF501: 19638
F502: 1.4751773 | G502: 45912 | L502: 0.87914894 | M502: 30794 | AF502: 19641
F503: 1.4698795 | G503: 55731 | L503: 0.87878788 | M503: 44386 | AF503: 19646
F504: 1.4690909 | G504: 56571 | L504: 0.87878788 | M504: 44390 | AF504: 19647
F505: 1.4657534 | G505: 55750 | L505: 0.87878788 | M505: 44529 | AF505: 19653
F506: 1.462963 | G506: 40657 | L506: 0.87878788 | M506: 44536 | AF506: 19660
F507: 1.4585635 | G507: 44297 | L507: 0.87878788 | M507: 44739 | AF507: 19726
F508: 1.4571429 | G508: 56702 | L508: 0.87878788 | M508: 44389 | AF508: 19818
F509: 1.4539683 | G509: 40683 | L509: 0.87855297 | M509: 32968 | AF509: 19872
F510: 1.4508929 | G510: 55753 | L510: 0.87687323 | M510: 32974 | AF510: 19884
... F598: 1.3333333 | G598: 40555 | L598: 0.71515151 | M598: 44196 | AF598: 28779
F599: 1.3333333 | G599: 40559 | AF599: 28831
F600: 1.3333333 | G600: 33514 | AF600: 28832
F601: 1.3333333 | G601: 33516 | AF601: 28833
F602: 1.3333333 | G602: 33527 | AF602: 28834
F603: 1.3333333 | G603: 55762 | AF603: 28835
F604: 1.3315217 | G604: 55767 | AF604: 28836
F605: 1.3303769 | G605: 55770 | AF605: 28837
F606: 1.3219697 | G606: 45993 | AF606: 28838
F607: 1.3179572 | G607: 40560 | AF607: 28840
F608: 1.3179572 | G608: 33513 | AF608: 28841
F609: 1.3157895 | G609: 32757 | AF609: 28842
F610: 1.3153153 | G610: 40549 | AF610: 28843
... F660: 1.2801932 | G660: 55687 | AF660: 29348
F661: 1.28 | G661: 55683
F662: 1.278826 | G662: 55680
F663: 1.277533 | G663: 55694
F664: 1.2773723 | G664: 55691
F665: 1.2745098 | G665: 55688
F666: 1.2736842 | G666: 55622
F667: 1.27 | G667: 32186
F668: 1.27 | G668: 40231
F669: 1.2692308 | G669: 32173
F670: 1.2692308 | G670: 45436
F671: 1.2666667 | G671: 42462
...

Sheet Paint
A1: THESE ROWS AND COLUMNS WILL BE HIDDEN - They contain update notes and information for lookup calculations
F2: SELECT Material | G2: Paint | I2: Hide these rows, used for lookup formulas
F3: Sheet name | G3: =MID(CELL("filename",A1),FIND("]",CELL("filename",A1))+1,255) -> Paint
F4: Workbook name | G4: =MID(CELL("filename",A1),FIND("[",CELL("filename",A1))+1,FIND("]", CELL("filename",A1))-FIND("[",CELL("filename",A1))-1) -> ICE DB Educational V4.1 - Oct 2025.xlsx
B6: Edit Title Manually | F6: Material Profile: Paint
F7: ICE DB Version: | G7: =Miscellaneous!$E$3 -> V4.1 - Oct 2025 | J7: Check this link to see when the material profile was last updated
F8: To access this material profile, please register and download the Advanced version for free, with the link below:
F9: http://www.circularecology.com/embodied-energy-and-carbon-footprint-database.html
B10: Update URL Manually | F10: For further information on this material, please visit this page: | H10: INSERT LINK TO WEBPAGE…
F119: The below will be deleted before sending externally
F121: NOTES: Check the slicers are on the correct materials | I121: All Data Points Pivot Tables | L121: All Data Points Pivot Tables | R121: All Data Points Pivot Tables | Y121: All Data Points Pivot Tables | AG121: Reference Lookup Pivot Table
F123: Number 1 | G123: =#REF! -> #REF! | I123: Number 2 | J123: =#REF! -> #REF! | L123: Number 3 | M123: =#REF! -> #REF! | O123: Number 4 | P123: =#REF! -> #REF! | R123: Number 5 | S123: =#REF! -> #REF! | U123: Number 6 | V123: =#REF! -> #REF! | X123: Number 7 | Y123: =#REF! -> #REF! | AA123: Number 8 | AB123: =#REF! -> #REF!
F135: Paste below per kg Embodied Carbon | I135: Paste below per kg Embodied Carbon | L135: Paste below per kg Embodied Carbon | O135: Paste below per kg Embodied Carbon | R135: Paste below per kg Embodied Carbon | U135: Paste below per kg Embodied Carbon | X135: Paste below per kg Embodied Carbon | AA135: Paste below per kg Embodied Carbon | AF135: Paste below reference numbers, filtered by this material
B136: Headers in this row | F136: Per kg. Embodied Carbon (kg CO2/kg) | G136: Data Point Number | I136: Per kg. Embodied Carbon (kg CO2/kg) | J136: Data Point Number | L136: Per kg. Embodied Carbon (kg CO2/kg) | M136: Data Point Number | O136: Per kg. Embodied Carbon (kg CO2/kg) | P136: Data Point Number | R136: Per kg. Embodied Carbon (kg CO2/kg) | S136: Data Point Number | AF136: Row Labels
B137: Start data from this row | F137: 4.7619048 | G137: 43733 | I137: 4.7619048 | J137: 43733 | AF137: 2128
F138: 4.7466443 | G138: 52876 | I138: 4.7466443 | J138: 52876 | AF138: 2129
F139: 4.6166667 | G139: 54230 | I139: 4.6166667 | J139: 54230 | AF139: 2166
F140: 4.4837359 | G140: 54215 | I140: 4.4837359 | J140: 54215 | AF140: 2281
F141: 4.473111 | G141: 54218 | I141: 4.473111 | J141: 54218 | AF141: 2282
F142: 4.3972522 | G142: 39855 | I142: 4.3972522 | J142: 39855 | AF142: 2293
F143: 4.3703119 | G143: 52866 | I143: 4.3703119 | J143: 52866 | AF143: 2304
F144: 4.3703119 | G144: 52871 | I144: 4.3703119 | J144: 52871 | AF144: 2321
F145: 4.3480769 | G145: 53007 | I145: 4.3480769 | J145: 53007 | AF145: 2329
F146: 4.3435115 | G146: 44229 | I146: 4.3435115 | J146: 44229 | AF146: 2383
F147: 4.3309524 | G147: 53019 | I147: 4.3309524 | J147: 53019 | AF147: 2624
F148: 4.3208333 | G148: 53004 | I148: 4.3208333 | J148: 53004 | AF148: 4646
F149: 4.3137365 | G149: 54220 | I149: 4.3137365 | J149: 54220 | AF149: 4647
... F388: 2.2297393 | G388: 45917 | I388: 2.2297393 | J388: 45917 | AF388: 29028
F389: 2.229375 | G389: 52908 | I389: 2.229375 | J389: 52908
F390: 2.2285714 | G390: 53031 | I390: 2.2285714 | J390: 53031
F391: 2.2183099 | G391: 53053 | I391: 2.2183099 | J391: 53053
F392: 2.2170286 | G392: 53757 | I392: 2.2170286 | J392: 53757
F393: 2.2129412 | G393: 52736 | I393: 2.2129412 | J393: 52736
F394: 2.2112154 | G394: 55157 | I394: 2.2112154 | J394: 55157
F395: 2.2112154 | G395: 53746 | I395: 2.2112154 | J395: 53746
F396: 2.2101449 | G396: 41930 | I396: 2.2101449 | J396: 41930
F397: 2.2097656 | G397: 39419 | I397: 2.2097656 | J397: 39419
F398: 2.2096842 | G398: 52912 | I398: 2.2096842 | J398: 52912
F399: 2.2089306 | G399: 54227 | I399: 2.2089306 | J399: 54227
F400: 2.2071277 | G400: 48005 | I400: 2.2071277 | J400: 48005
... F720: 0.44 | G720: 48296 | I720: 0.44 | J720: 48296

Sheet Plaster
A1: THESE ROWS AND COLUMNS WILL BE HIDDEN - They contain update notes and information for lookup calculations
F2: SELECT Material | G2: Plaster | I2: Hide these rows, used for lookup formulas
F3: Sheet name | G3: =MID(CELL("filename",A1),FIND("]",CELL("filename",A1))+1,255) -> Plaster
F4: Workbook name | G4: =MID(CELL("filename",A1),FIND("[",CELL("filename",A1))+1,FIND("]", CELL("filename",A1))-FIND("[",CELL("filename",A1))-1) -> ICE DB Educational V4.1 - Oct 2025.xlsx
B6: Edit Title Manually | F6: Material Profile: Plaster
F7: ICE DB Version: | G7: =Miscellaneous!$E$3 -> V4.1 - Oct 2025 | J7: Check this link to see when the material profile was last updated
F8: To access this material profile, please register and download the Advanced version for free, with the link below:
F9: http://www.circularecology.com/embodied-energy-and-carbon-footprint-database.html
B10: Update URL Manually | F10: For further information on this material, please visit this page: | H10: INSERT LINK TO WEBPAGE…
F119: The below will be deleted before sending externally
F121: NOTES: Check the slicers are on the correct materials | I121: All Data Points Pivot Tables | L121: All Data Points Pivot Tables | R121: All Data Points Pivot Tables | Y121: All Data Points Pivot Tables | AG121: Reference Lookup Pivot Table
F123: Number 1 | G123: =#REF! -> #REF! | I123: Number 2 | J123: =#REF! -> #REF! | L123: Number 3 | M123: =#REF! -> #REF! | O123: Number 4 | P123: =#REF! -> #REF! | R123: Number 5 | S123: =#REF! -> #REF! | U123: Number 6 | V123: =#REF! -> #REF! | X123: Number 7 | Y123: =#REF! -> #REF! | AA123: Number 8 | AB123: =#REF! -> #REF!
F135: Paste below per kg Embodied Carbon | I135: Paste below per kg Embodied Carbon | L135: Paste below per kg Embodied Carbon | O135: Paste below per kg Embodied Carbon | R135: Paste below per kg Embodied Carbon | U135: Paste below per kg Embodied Carbon | X135: Paste below per kg Embodied Carbon | AA135: Paste below per kg Embodied Carbon | AF135: Paste below reference numbers, filtered by this material
B136: Headers in this row | F136: Per kg. Embodied Carbon (kg CO2/kg) | G136: Data Point Number | I136: Per kg. Embodied Carbon (kg CO2/kg) | J136: Data Point Number | L136: Per kg. Embodied Carbon (kg CO2/kg) | M136: Data Point Number | O136: Per kg. Embodied Carbon (kg CO2/kg) | P136: Data Point Number | R136: Per kg. Embodied Carbon (kg CO2/kg) | S136: Data Point Number | AF136: Row Labels
B137: Start data from this row | F137: 0.51866377 | G137: 56107 | I137: 0.51866377 | J137: 56107 | L137: 0.44 | M137: 76578 | O137: 0.44946215 | P137: 42237 | AF137: 568
F138: 0.51831189 | G138: 56111 | I138: 0.51831189 | J138: 56111 | L138: 0.425 | M138: 76579 | O138: 0.44261379 | P138: 42748 | AF138: 569
F139: 0.47995781 | G139: 41258 | I139: 0.47995781 | J139: 41258 | L139: 0.4 | M139: 76580 | O139: 0.434 | P139: 52426 | AF139: 572
F140: 0.46383881 | G140: 53293 | I140: 0.46383881 | J140: 53293 | L140: 0.38095238 | M140: 76581 | O140: 0.43378995 | P140: 42460 | AF140: 573
F141: 0.46326531 | G141: 41257 | I141: 0.46326531 | J141: 41257 | L141: 0.37 | M141: 76582 | O141: 0.421875 | P141: 52422 | AF141: 575
F142: 0.46065574 | G142: 46060 | I142: 0.46065574 | J142: 46060 | L142: 0.33333333 | M142: 76584 | O142: 0.40996785 | P142: 56137 | AF142: 929
F143: 0.45071429 | G143: 46188 | I143: 0.45071429 | J143: 46188 | L143: 0.32967033 | M143: 76585 | O143: 0.39659091 | P143: 52432 | AF143: 1262
F144: 0.44946215 | G144: 42237 | I144: 0.44067797 | J144: 42380 | L144: 0.3 | M144: 76586 | O144: 0.39444444 | P144: 56133 | AF144: 2197
F145: 0.44261379 | G145: 42748 | I145: 0.43714286 | J145: 41250 | L145: 0.29787234 | M145: 76587 | O145: 0.39426878 | P145: 56134 | AF145: 2397
F146: 0.44067797 | G146: 42380 | I146: 0.43243243 | J146: 41255 | L146: 0.29 | M146: 76588 | O146: 0.38811812 | P146: 40604 | AF146: 2486
F147: 0.44 | G147: 76578 | I147: 0.42966102 | J147: 41246 | L147: 0.28 | M147: 76589 | O147: 0.38714286 | P147: 56193 | AF147: 2488
F148: 0.43714286 | G148: 41250 | I148: 0.42832703 | J148: 52654 | L148: 0.27 | M148: 76590 | O148: 0.384 | P148: 45946 | AF148: 2489
F149: 0.434 | G149: 52426 | I149: 0.4220339 | J149: 45534 | L149: 0.27 | M149: 76591 | O149: 0.383682 | P149: 53383 | AF149: 2490
... F221: 0.32956522 | G221: 53238 | I221: 0.16935484 | J221: 46109 | L221: 0.091 | M221: 76650 | O221: 0.29394938 | P221: 56091 | AF221: 6482
F222: 0.32835821 | G222: 42415 | L222: 0.09 | M222: 55611 | O222: 0.29394813 | P222: 56088 | AF222: 6483
F223: 0.32743363 | G223: 56130 | L223: 0.09 | M223: 76651 | O223: 0.29282933 | P223: 48266 | AF223: 6484
F224: 0.32618683 | G224: 70750 | L224: 0.0896 | M224: 76652 | O224: 0.2912679 | P224: 53367 | AF224: 6485
F225: 0.3248303 | G225: 53376 | L225: 0.0896 | M225: 76653 | O225: 0.29089003 | P225: 40602 | AF225: 6486
F226: 0.3229309 | G226: 53380 | L226: 0.0873 | M226: 76654 | O226: 0.29069767 | P226: 46022 | AF226: 6487
F227: 0.32292788 | G227: 32445 | L227: 0.0873 | M227: 76655 | O227: 0.29037892 | P227: 51003 | AF227: 6489
F228: 0.32267685 | G228: 53370 | L228: 0.087 | M228: 49947 | O228: 0.29027555 | P228: 53369 | AF228: 6490
F229: 0.32242632 | G229: 48268 | L229: 0.087 | M229: 76656 | O229: 0.28926896 | P229: 56060 | AF229: 6491
F230: 0.32215074 | G230: 48265 | L230: 0.086 | M230: 49955 | O230: 0.28926896 | P230: 56070 | AF230: 6492
F231: 0.3221369 | G231: 49224 | L231: 0.081 | M231: 49956 | O231: 0.28660117 | P231: 53365 | AF231: 6493
F232: 0.32126697 | G232: 45499 | L232: 0.0787 | M232: 76657 | O232: 0.28627451 | P232: 41239 | AF232: 6494
F233: 0.32 | G233: 49935 | L233: 0.0785 | M233: 76658 | O233: 0.28543584 | P233: 40601 | AF233: 6495
... F243: 0.31198003 | G243: 32390 | L243: 0.053 | M243: 76665 | O243: 0.28125 | P243: 32638 | AF243: 6505
F244: 0.31170471 | G244: 56096 | O244: 0.27924528 | P244: 41242 | AF244: 6506
F245: 0.31161563 | G245: 56094 | O245: 0.27910448 | P245: 42512 | AF245: 6507
F246: 0.31117825 | G246: 41251 | O246: 0.27910448 | P246: 56125 | AF246: 6508
F247: 0.31006976 | G247: 50999 | O247: 0.27778268 | P247: 53384 | AF247: 6509
F248: 0.30964952 | G248: 53345 | O248: 0.27777778 | P248: 66298 | AF248: 6510
F249: 0.30875358 | G249: 48274 | O249: 0.2764977 | P249: 56064 | AF249: 6511
F250: 0.30847458 | G250: 41249 | O250: 0.27632577 | P250: 56059 | AF250: 6512
F251: 0.308 | G251: 30948 | O251: 0.27632577 | P251: 56067 | AF251: 6513
F252: 0.30769231 | G252: 45497 | O252: 0.27511416 | P252: 56126 | AF252: 6514
F253: 0.30693069 | G253: 40600 | O253: 0.275 | P253: 56131 | AF253: 6515
F254: 0.30615033 | G254: 48800 | O254: 0.27402597 | P254: 41403 | AF254: 6516
F255: 0.30610687 | G255: 41240 | O255: 0.27367056 | P255: 54623 | AF255: 6517
... F512: 0.18699911 | G512: 32581 | O512: 0.11 | P512: 62563 | AF512: 28987
F513: 0.18681319 | G513: 45703 | AF513: 29040
F514: 0.18681319 | G514: 46107 | AF514: 29049
F515: 0.18627451 | G515: 45103 | AF515: 29076
F516: 0.18551724 | G516: 76609 | AF516: 29185
F517: 0.1852459 | G517: 42768 | AF517: 29248
F518: 0.18518519 | G518: 45135 | AF518: 29251
F519: 0.18518519 | G519: 45647 | AF519: 29254
F520: 0.18518519 | G520: 46117
F521: 0.18467221 | G521: 42166
F522: 0.18235294 | G522: 76610
F523: 0.18222222 | G523: 32810
F524: 0.18166667 | G524: 42795
F525: 0.18141593 | G525: 42164
F526: 0.18139535 | G526: 42816
F527: 0.18124583 | G527: 56093
F528: 0.18085714 | G528: 76611
F529: 0.18055556 | G529: 44564
F530: 0.18 | G530: 76612
F531: 0.18 | G531: 76613
... F704: 0.053 | G704: 76665

Sheet Rubber
A1: THESE ROWS AND COLUMNS WILL BE HIDDEN - They contain update notes and information for lookup calculations
F2: SELECT Material | G2: Rubber | I2: Hide these rows, used for lookup formulas
F3: Sheet name | G3: =MID(CELL("filename",A1),FIND("]",CELL("filename",A1))+1,255) -> Rubber
F4: Workbook name | G4: =MID(CELL("filename",A1),FIND("[",CELL("filename",A1))+1,FIND("]", CELL("filename",A1))-FIND("[",CELL("filename",A1))-1) -> ICE DB Educational V4.1 - Oct 2025.xlsx
B6: Edit Title Manually | F6: Material Profile: Rubber
F7: ICE DB Version: | G7: =Miscellaneous!$E$3 -> V4.1 - Oct 2025 | J7: Check this link to see when the material profile was last updated
F8: To access this material profile, please register and download the Advanced version for free, with the link below:
F9: http://www.circularecology.com/embodied-energy-and-carbon-footprint-database.html
B10: Update URL Manually | F10: For further information on this material, please visit this page: | H10: INSERT LINK TO WEBPAGE…
F119: The below will be deleted before sending externally
F121: NOTES: Check the slicers are on the correct materials | I121: All Data Points Pivot Tables | L121: All Data Points Pivot Tables | R121: All Data Points Pivot Tables | Y121: All Data Points Pivot Tables | AG121: Reference Lookup Pivot Table
F123: Number 1 | G123: =#REF! -> #REF! | I123: Number 2 | J123: =#REF! -> #REF! | L123: Number 3 | M123: =#REF! -> #REF! | O123: Number 4 | P123: =#REF! -> #REF! | R123: Number 5 | S123: =#REF! -> #REF! | U123: Number 6 | V123: =#REF! -> #REF! | X123: Number 7 | Y123: =#REF! -> #REF! | AA123: Number 8 | AB123: =#REF! -> #REF!
F135: Paste below per kg Embodied Carbon | I135: Paste below per kg Embodied Carbon | L135: Paste below per kg Embodied Carbon | O135: Paste below per kg Embodied Carbon | R135: Paste below per kg Embodied Carbon | U135: Paste below per kg Embodied Carbon | X135: Paste below per kg Embodied Carbon | AA135: Paste below per kg Embodied Carbon | AF135: Paste below reference numbers, filtered by this material
B136: Headers in this row | F136: Per kg. Embodied Carbon (kg CO2/kg) | G136: Data Point Number | I136: Per kg. Embodied Carbon (kg CO2/kg) | J136: Data Point Number | L136: Per kg. Embodied Carbon (kg CO2/kg) | M136: Data Point Number | O136: Per kg. Embodied Carbon (kg CO2/kg) | P136: Data Point Number | R136: Per kg. Embodied Carbon (kg CO2/kg) | S136: Data Point Number | AF136: Row Labels
B137: Start data from this row | F137: 6.35686 | G137: 30608 | I137: 6.35686 | J137: 30608 | AF137: 596
F138: 5.1407129 | G138: 44401 | I138: 5.1407129 | J138: 44401 | AF138: 597
F139: 4.7538462 | G139: 32688 | I139: 4.7538462 | J139: 32688 | AF139: 598
F140: 4.29977 | G140: 30575 | I140: 4.29977 | J140: 30575 | AF140: 599
F141: 4.20151 | G141: 30609 | I141: 4.20151 | J141: 30609 | AF141: 600
F142: 4.16778 | G142: 30577 | I142: 4.16778 | J142: 30577 | AF142: 632
F143: 4.10241 | G143: 30572 | I143: 4.10241 | J143: 30572 | AF143: 929
F144: 4 | G144: 30974 | I144: 4 | J144: 30974 | AF144: 2651
F145: 3.99847 | G145: 30581 | I145: 3.99847 | J145: 30581 | AF145: 2652
F146: 3.97332 | G146: 30975 | I146: 3.97332 | J146: 30975 | AF146: 2653
F147: 3.94471 | G147: 30976 | I147: 3.94471 | J147: 30976 | AF147: 2654
F148: 3.905 | G148: 30977 | I148: 3.905 | J148: 30977 | AF148: 2998
F149: 3.905 | G149: 30978 | I149: 3.905 | J149: 30978 | AF149: 2999
... F170: 2.152512 | G170: 31010 | I170: 2.152512 | J170: 31010 | AF170: 28566
F171: 2.1505376 | G171: 32914 | I171: 2.1505376 | J171: 32914
F172: 2.146283 | G172: 32918 | I172: 2.146283 | J172: 32918
F173: 1.8523622 | G173: 32708 | I173: 1.8523622 | J173: 32708
F174: 1.7655131 | G174: 32711 | I174: 1.7655131 | J174: 32711
F175: 1.6982935 | G175: 32934 | I175: 1.6982935 | J175: 32934
F176: 1.6924829 | G176: 42899 | I176: 1.6924829 | J176: 42899
F177: 1.6571429 | G177: 32716 | I177: 1.6571429 | J177: 32716
F178: 1.604328 | G178: 32923 | I178: 1.604328 | J178: 32923
F179: 1.5607143 | G179: 32929 | I179: 1.5607143 | J179: 32929
F180: 1.5595238 | G180: 42863 | I180: 1.5595238 | J180: 42863
F181: 1.554083 | G181: 32927 | I181: 1.554083 | J181: 32927
F182: 1.4953964 | G182: 32933 | I182: 1.4953964 | J182: 32933
... F197: 0.77509931 | G197: 32932 | I197: 0.77509931 | J197: 32932

Sheet Steel
A1: THESE ROWS AND COLUMNS WILL BE HIDDEN - They contain update notes and information for lookup calculations
F2: SELECT Material | G2: Steel | I2: Hide these rows, used for lookup formulas
F3: Sheet name | G3: =MID(CELL("filename",A1),FIND("]",CELL("filename",A1))+1,255) -> Steel
F4: Workbook name | G4: =MID(CELL("filename",A1),FIND("[",CELL("filename",A1))+1,FIND("]", CELL("filename",A1))-FIND("[",CELL("filename",A1))-1) -> ICE DB Educational V4.1 - Oct 2025.xlsx
B6: Edit Title Manually | F6: Material Profile: Steel
F7: ICE DB Version: | G7: =Miscellaneous!$E$3 -> V4.1 - Oct 2025 | J7: Check this link to see when the material profile was last updated
F8: To access this material profile, please register and download the Advanced version for free, with the link below:
F9: http://www.circularecology.com/embodied-energy-and-carbon-footprint-database.html
B10: Update URL Manually | F10: For further information on this material, please visit this page: | H10: INSERT LINK TO WEBPAGE…
F117: The below will be deleted before sending externally
F119: NOTES: Check the slicers are on the correct materials | I119: All Data Points Pivot Tables | L119: All Data Points Pivot Tables | R119: All Data Points Pivot Tables | Y119: All Data Points Pivot Tables | AG119: Reference Lookup Pivot Table
F121: Number 1 | G121: =#REF! -> #REF! | I121: Number 2 | J121: =#REF! -> #REF! | L121: Number 3 | M121: =#REF! -> #REF! | O121: Number 4 | P121: =#REF! -> #REF! | R121: Number 5 | S121: =#REF! -> #REF! | U121: Number 6 | V121: =#REF! -> #REF! | X121: Number 7 | Y121: =#REF! -> #REF! | AA121: Number 8 | AB121: =#REF! -> #REF!
F133: Paste below per kg Embodied Carbon | I133: Paste below per kg Embodied Carbon | L133: Paste below per kg Embodied Carbon | O133: Paste below per kg Embodied Carbon | R133: Paste below per kg Embodied Carbon | U133: Paste below per kg Embodied Carbon | X133: Paste below per kg Embodied Carbon | AA133: Paste below per kg Embodied Carbon | AF133: Paste below reference numbers, filtered by this material
B134: Headers in this row | F134: Per kg. Embodied Carbon (kg CO2/kg) | G134: Data Point Number | I134: Per kg. Embodied Carbon (kg CO2/kg) | J134: Data Point Number | L134: Per kg. Embodied Carbon (kg CO2/kg) | M134: Data Point Number | O134: Per kg. Embodied Carbon (kg CO2/kg) | P134: Data Point Number | R134: Per kg. Embodied Carbon (kg CO2/kg) | S134: Data Point Number | U134: Per kg. Embodied Carbon (kg CO2/kg) | V134: Data Point Number | AF134: Row Labels
B135: Start data from this row | F135: 16.154522 | G135: 30908 | I135: 3.2 | J135: 31170 | L135: 2.88 | M135: 30698 | O135: 3.59237 | P135: 30648 | R135: 3.6 | S135: 31173 | U135: 6.29 | V135: 30312 | AF135: 29359
F136: 10.542456 | G136: 31259 | I136: 2.58 | J136: 31535 | L136: 2.81 | M136: 30699 | O136: 3.1548125 | P136: 31375 | R136: 3.2 | S136: 31168 | U136: 4.51417 | V136: 30644 | AF136: 334
F137: 10.317869 | G137: 31260 | I137: 2.56 | J137: 30793 | L137: 2.73 | M137: 30701 | O137: 3.0266292 | P137: 31376 | R137: 3.2 | S137: 31364 | U137: 4.42546 | V137: 30645 | AF137: 360
F138: 8 | G138: 31261 | I138: 2.4 | J138: 31171 | L138: 2.72095 | M138: 30321 | O138: 2.9 | P138: 31374 | R138: 2.85 | S138: 31391 | U138: 4.41886 | V138: 30646 | AF138: 361
F139: 6.29 | G139: 30312 | I139: 2.36 | J139: 30792 | L139: 2.71 | M139: 30703 | O139: 2.88906 | P139: 30653 | R139: 1.735 | S139: 30342 | U139: 3.91099 | V139: 30314 | AF139: 362
F140: 5.3269006 | G140: 31262 | I140: 2.35 | J140: 30902 | L140: 2.5627876 | M140: 30323 | O140: 2.4583333 | P140: 30333 | R140: 1.5 | S140: 31174 | U140: 3.68 | V140: 30901 | AF140: 368
F141: 5.3 | G141: 30313 | I141: 1.99 | J141: 31796 | L141: 2.46 | M141: 30706 | O141: 2.442623 | P141: 30334 | R141: 1.4044289 | S141: 30826 | U141: 3.60644 | V141: 30315 | AF141: 369
F142: 4.51417 | G142: 30644 | I142: 1.91 | J142: 30710 | L142: 2.45861 | M142: 30332 | O142: 2.4237288 | P142: 30335 | R142: 1.3537653 | S142: 30827 | AF142: 407
F143: 4.42546 | G143: 30645 | I143: 1.8 | J143: 31176 | L143: 2.37 | M143: 30707 | O143: 2.3854167 | P143: 30338 | R143: 1.2 | S143: 31169 | AF143: 408
F144: 4.41886 | G144: 30646 | I144: 1.5 | J144: 31172 | L144: 2.22 | M144: 30709 | O144: 2.3833333 | P144: 30339 | R144: 0.975 | S144: 31540 | AF144: 409
F145: 4.0636594 | G145: 31263 | I145: 1.22 | J145: 30898 | L145: 1.1 | M145: 30741 | AF145: 410
F146: 3.9503059 | G146: 30647 | I146: 1.09 | J146: 30899 | L146: 1.04 | M146: 30740 | AF146: 411
F147: 3.91099 | G147: 30314 | I147: 1.089 | J147: 31377 | L147: 0.643 | M147: 31345 | AF147: 412
F148: 3.68 | G148: 30901 | I148: 1.03 | J148: 31533 | AF148: 413
F149: 3.60644 | G149: 30315 | I149: 1.016 | J149: 30884 | AF149: 447
F150: 3.6 | G150: 31173 | I150: 1.01 | J150: 30790 | AF150: 448
F151: 3.59237 | G151: 30648 | I151: 0.981 | J151: 31541 | AF151: 449
F152: 3.4456 | G152: 31264 | I152: 0.96 | J152: 31542 | AF152: 457
F153: 3.4385965 | G153: 31265 | I153: 0.959 | J153: 30791 | AF153: 493
F154: 3.3413992 | G154: 30649 | I154: 0.9 | J154: 30789 | AF154: 501
F155: 3.2400339 | G155: 31544 | I155: 0.899 | J155: 30742 | AF155: 505
F156: 3.2 | G156: 31168 | I156: 0.898 | J156: 31549 | AF156: 506
F157: 3.2 | G157: 31170 | I157: 0.891 | J157: 30879 | AF157: 517
F158: 3.2 | G158: 31364 | I158: 0.839 | J158: 30787 | AF158: 519
F159: 3.1548125 | G159: 31375 | I159: 0.799 | J159: 31547 | AF159: 520
... F178: 2.73 | G178: 30701 | I178: 0.282 | J178: 30788 | AF178: 967
F179: 2.73 | G179: 30702 | AF179: 996
F180: 2.72095 | G180: 30320 | AF180: 997
F181: 2.72095 | G181: 30321 | AF181: 999
F182: 2.71 | G182: 30703 | AF182: 1000
F183: 2.7 | G183: 30704 | AF183: 1001
F184: 2.6600985 | G184: 31266 | AF184: 1002
F185: 2.6051 | G185: 30322 | AF185: 1013
F186: 2.6 | G186: 31175 | AF186: 1014
F187: 2.58 | G187: 31535 | AF187: 1025
F188: 2.5627876 | G188: 30323 | AF188: 1026
F189: 2.56 | G189: 30705 | AF189: 1027
F190: 2.56 | G190: 30793 | AF190: 1028
... F234: 1.5 | G234: 31172 | AF234: 29385
F235: 1.5 | G235: 31174
F236: 1.438 | G236: 30883
F237: 1.4044289 | G237: 30826
F238: 1.3537653 | G238: 30827
F239: 1.28 | G239: 30712
F240: 1.2769134 | G240: 30825
F241: 1.2368421 | G241: 31273
F242: 1.22 | G242: 30898
F243: 1.2 | G243: 31169
F244: 1.1 | G244: 30741
F245: 1.09 | G245: 30899
F246: 1.089 | G246: 31377
... F284: 0.282 | G284: 30788

Sheet Timber
A1: THESE ROWS AND COLUMNS WILL BE HIDDEN - They contain update notes and information for lookup calculations
F2: SELECT Material | G2: Timber | I2: Hide these rows, used for lookup formulas
F3: Sheet name | G3: =MID(CELL("filename",A1),FIND("]",CELL("filename",A1))+1,255) -> Timber
F4: Workbook name | G4: =MID(CELL("filename",A1),FIND("[",CELL("filename",A1))+1,FIND("]", CELL("filename",A1))-FIND("[",CELL("filename",A1))-1) -> ICE DB Educational V4.1 - Oct 2025.xlsx
B6: Edit Title Manually | F6: Material Profile: Timber
F7: ICE DB Version: | G7: =Miscellaneous!$E$3 -> V4.1 - Oct 2025 | J7: Check this link to see when the material profile was last updated
F8: To access this material profile, please register and download the Advanced version for free, with the link below:
F9: http://www.circularecology.com/embodied-energy-and-carbon-footprint-database.html
B10: Update URL Manually | F10: For further information on this material, please visit this page: | H10: INSERT LINK TO WEBPAGE…
F120: The below will be deleted before sending externally
F122: NOTES: Check the slicers are on the correct materials | I122: All Data Points Pivot Tables | L122: All Data Points Pivot Tables | R122: All Data Points Pivot Tables | Y122: All Data Points Pivot Tables | AG122: Reference Lookup Pivot Table
F124: Number 1 | G124: =#REF! -> #REF! | I124: Number 2 | J124: =#REF! -> #REF! | L124: Number 3 | M124: =#REF! -> #REF! | O124: Number 4 | P124: =#REF! -> #REF! | R124: Number 5 | S124: =#REF! -> #REF! | U124: Number 6 | V124: =#REF! -> #REF! | X124: Number 7 | Y124: =#REF! -> #REF! | AA124: Number 8 | AB124: =#REF! -> #REF!
F136: Paste below per kg Embodied Carbon | I136: Paste below per kg Embodied Carbon | L136: Paste below per kg Embodied Carbon | O136: Paste below per kg Embodied Carbon | R136: Paste below per kg Embodied Carbon | U136: Paste below per kg Embodied Carbon | X136: Paste below per kg Embodied Carbon | AA136: Paste below per kg Embodied Carbon | AF136: Paste below reference numbers, filtered by this material
B137: Headers in this row | F137: Per kg. Embodied Carbon (kg CO2/kg) | G137: Data Point Number | I137: Per kg. Embodied Carbon (kg CO2/kg) | J137: Data Point Number | L137: Per kg. Embodied Carbon (kg CO2/kg) | M137: Data Point Number | O137: Per kg. Embodied Carbon (kg CO2/kg) | P137: Data Point Number | R137: Per kg. Embodied Carbon (kg CO2/kg) | S137: Data Point Number | U137: Per kg. Embodied Carbon (kg CO2/kg) | V137: Data Point Number | X137: Per kg. Embodied Carbon (kg CO2/kg) | Y137: Data Point Number | AA137: Per kg. Embodied Carbon (kg CO2/kg) | AB137: Data Point Number | AF137: Row Labels
B138: Start data from this row | F138: 0.58 | G138: 31708 | I138: -0.406 | J138: 31627 | L138: -1.0055809 | M138: 31737 | O138: -1.1763265 | P138: 31663 | R138: -0.71838 | S138: 31781 | U138: -0.55147059 | V138: 31678 | X138: -0.077333333 | Y138: 31712 | AA138: -0.57714286 | AB138: 31702 | AF138: 29360
F139: 0.174 | G139: 31629 | I139: -0.73 | J139: 31625 | L139: -1.0128605 | M139: 31747 | O139: -1.1809524 | P139: 31672 | R139: -0.81738 | S139: 31780 | U139: -0.59016393 | V139: 31680 | X139: -0.46481481 | Y139: 31713 | AA139: -0.65840517 | AB139: 31703 | AF139: 363
F140: -0.077333333 | G140: 31712 | I140: -0.886 | J140: 31626 | L140: -1.02 | M140: 31768 | O140: -1.1843537 | P140: 31666 | R140: -0.95438 | S140: 31777 | U140: -0.59119497 | V140: 31679 | X140: -0.52 | Y140: 31714 | AA140: -0.73333333 | AB140: 31700 | AF140: 370
F141: -0.24 | G141: 31709 | I141: -1.0524284 | J141: 31293 | L141: -1.0260127 | M141: 31743 | O141: -1.1940136 | P141: 31669 | R141: -0.96338 | S141: 31778 | U141: -0.68804375 | V141: 31631 | X141: -0.7337931 | Y141: 31716 | AA141: -0.74796748 | AB141: 31705 | AF141: 570
F142: -0.27840909 | G142: 31699 | I142: -1.0610119 | J142: 31682 | L142: -1.0274518 | M142: 31752 | O142: -1.1989116 | P142: 31660 | R142: -0.96790167 | S142: 30665 | U142: -0.70665393 | V142: 31718 | X142: -0.84067797 | Y142: 31717 | AA142: -0.77477477 | AB142: 31701 | AF142: 901
F143: -0.28461538 | G143: 31698 | I143: -1.122 | J143: 31624 | L143: -1.0286097 | M143: 31733 | O143: -1.2130208 | P143: 31664 | R143: -1 | S143: 31773 | U143: -0.75423729 | V143: 31677 | X143: -0.8768546 | Y143: 31707 | AA143: -0.78918919 | AB143: 31704 | AF143: 903
F144: -0.406 | G144: 31627 | I144: -1.1320316 | J144: 30680 | L144: -1.0301205 | M144: 31770 | O144: -1.2136054 | P144: 31657 | R144: -1.00338 | S144: 31779 | U144: -0.81320755 | V144: 31676 | X144: -0.93230769 | Y144: 31715 | AA144: -1.0157125 | AB144: 30685 | AF144: 904
F145: -0.41666667 | G145: 31710 | I145: -1.174 | J145: 31628 | L145: -1.0309854 | M145: 31738 | O145: -1.2174479 | P145: 31673 | R145: -1.0076923 | S145: 31772 | U145: -0.9125 | V145: 31688 | X145: -0.99591837 | Y145: 31684 | AA145: -1.2484083 | AB145: 30667 | AF145: 905
F146: -0.4495036 | G146: 31281 | I146: -1.1943739 | J146: 31645 | L146: -1.0341532 | M146: 31729 | O146: -1.2207031 | P146: 31667 | R146: -1.0153846 | S146: 31771 | U146: -0.94056604 | V146: 31674 | X146: -1.0257649 | Y146: 31706 | AA146: -1.3866259 | AB146: 31691 | AF146: 906
F147: -0.46153846 | G147: 31697 | I147: -1.2431942 | J147: 31653 | L147: -1.038378 | M147: 31748 | O147: -1.2299479 | P147: 31670 | R147: -1.02438 | S147: 31776 | U147: -0.9440678 | V147: 31675 | X147: -1.2650925 | Y147: 30668 | AA147: -1.3991245 | AB147: 31765 | AF147: 907
F148: -0.46285714 | G148: 31696 | I148: -1.2564428 | J148: 31655 | L148: -1.0402606 | M148: 31719 | O148: -1.2346354 | P148: 31661 | R148: -1.074769 | S148: 31775 | U148: -0.9625 | V148: 31689 | X148: -1.2834181 | Y148: 31755 | AA148: -1.4765858 | AB148: 30678 | AF148: 908
F149: -0.46481481 | G149: 31713 | I149: -1.2664247 | J149: 31651 | L149: -1.0415609 | M149: 31741 | O149: -1.2486979 | P149: 31658 | R149: -1.2325073 | S149: 31292 | U149: -1.0685714 | V149: 31630 | X149: -1.2869397 | Y149: 30669 | AF149: 909
F150: -0.51196199 | G150: 31754 | I150: -1.2689655 | J150: 31647 | L150: -1.0415609 | M150: 31750 | O150: -1.2578797 | P150: 31683 | R150: -1.2405272 | S150: 31766 | U150: -1.0718054 | V150: 31623 | X150: -1.3417499 | Y150: 30671 | AF150: 910
F151: -0.51428571 | G151: 31711 | I151: -1.2736842 | J151: 31649 | L151: -1.0415609 | M151: 31751 | O151: -1.3382313 | P151: 31662 | R151: -1.2477149 | S151: 31761 | AF151: 911
F152: -0.52 | G152: 31714 | I152: -1.2793103 | J152: 31641 | L152: -1.0415609 | M152: 31720 | O152: -1.3428571 | P152: 31671 | R152: -1.2956667 | S152: 31767 | AF152: 913
F153: -0.55147059 | G153: 31678 | I153: -1.2805808 | J153: 31643 | L153: -1.0415609 | M153: 31722 | O153: -1.3462585 | P153: 31665 | R153: -1.3782667 | S153: 31774 | AF153: 914
F154: -0.57714286 | G154: 31702 | I154: -1.2809437 | J154: 31637 | L154: -1.0415609 | M154: 31724 | O154: -1.3559184 | P154: 31668 | AF154: 915
F155: -0.57961937 | G155: 30660 | I155: -1.2814882 | J155: 31639 | L155: -1.0415609 | M155: 31742 | O155: -1.3608163 | P155: 31659 | AF155: 916
F156: -0.59016393 | G156: 31680 | I156: -1.2941924 | J156: 31644 | L156: -1.0415609 | M156: 31745 | O156: -1.3755102 | P156: 31656 | AF156: 929
F157: -0.59119497 | G157: 31679 | I157: -1.3012704 | J157: 31635 | L157: -1.0415609 | M157: 31746 | O157: -1.4648298 | P157: 30688 | AF157: 942
F158: -0.59351988 | G158: 31279 | I158: -1.340249 | J158: 31690 | L158: -1.0415609 | M158: 31749 | O158: -1.4665043 | P158: 30689 | AF158: 943
F159: -0.6363824 | G159: 31760 | I159: -1.3430127 | J159: 31652 | L159: -1.0422718 | M159: 31725 | O159: -1.4700105 | P159: 30690 | AF159: 1202
F160: -0.63659358 | G160: 31286 | I160: -1.3556477 | J160: 30686 | L160: -1.0434759 | M160: 31739 | AF160: 1203
F161: -0.63749046 | G161: 31287 | I161: -1.3562613 | J161: 31654 | L161: -1.0504585 | M161: 31744 | AF161: 1204
F162: -0.65513771 | G162: 31633 | I162: -1.3662432 | J162: 31650 | L162: -1.0520601 | M162: 31734 | AF162: 1205
F163: -0.65840517 | G163: 31703 | I163: -1.368784 | J163: 31646 | L163: -1.0534101 | M163: 31721 | AF163: 1206
F164: -0.67021846 | G164: 30659 | I164: -1.3735027 | J164: 31648 | L164: -1.0569652 | M164: 31730 | AF164: 1207
F165: -0.67413793 | G165: 31694 | I165: -1.3791289 | J165: 31640 | L165: -1.0626989 | M165: 31735 | AF165: 1208
F166: -0.6831 | G166: 31285 | I166: -1.3803993 | J166: 31642 | L166: -1.0638865 | M166: 31740 | AF166: 1209
F167: -0.68804375 | G167: 31631 | I167: -1.3807623 | J167: 31636 | L167: -1.0641214 | M167: 31726 | AF167: 1210
F168: -0.70665393 | G168: 31718 | I168: -1.3813067 | J168: 31638 | L168: -1.0673074 | M168: 31731 | AF168: 1211
F169: -0.71071429 | G169: 31632 | I169: -1.4010889 | J169: 31634 | L169: -1.0711328 | M169: 31727 | AF169: 1212
F170: -0.7137032 | G170: 31282 | I170: -1.4355157 | J170: 30682 | L170: -1.0833791 | M170: 31736 | AF170: 1213
F171: -0.71838 | G171: 31781 | I171: -1.436873 | J171: 30687 | L171: -1.0842487 | M171: 31723 | AF171: 1214
... F174: -0.73333333 | G174: 31700 | I174: -1.481894 | J174: 30677 | L174: -1.1666327 | M174: 31757 | AF174: 1217
F175: -0.7337931 | G175: 31716 | I175: -1.4864301 | J175: 30750 | AF175: 1218
F176: -0.74796748 | G176: 31705 | I176: -1.4873196 | J176: 31764 | AF176: 1219
F177: -0.7512848 | G177: 31283 | I177: -1.5163567 | J177: 30679 | AF177: 1220
F178: -0.75423729 | G178: 31677 | I178: -1.5236992 | J178: 31763 | AF178: 1221
F179: -0.77477477 | G179: 31701 | I179: -1.5438814 | J179: 31321 | AF179: 1222
F180: -0.78918919 | G180: 31704 | I180: -1.546432 | J180: 31320 | AF180: 1223
F181: -0.79036635 | G181: 31687 | AF181: 1224
F182: -0.79289367 | G182: 31284 | AF182: 1225
F183: -0.81320755 | G183: 31676 | AF183: 1226
F184: -0.81535649 | G184: 31280 | AF184: 1227
F185: -0.81738 | G185: 31780 | AF185: 1228
F186: -0.81778572 | G186: 31288 | AF186: 1229
F187: -0.82396358 | G187: 31756 | AF187: 1230
F188: -0.84067797 | G188: 31717 | AF188: 1231
F189: -0.85196078 | G189: 31685 | AF189: 1232
F190: -0.8768546 | G190: 31707 | AF190: 1233
F191: -0.886 | G191: 31626 | AF191: 1234
F192: -0.9125 | G192: 31688 | AF192: 1235
... F212: -1.0157125 | G212: 30685 | AF212: 1255
F213: -1.02 | G213: 31768
F214: -1.02438 | G214: 31776
F215: -1.0257649 | G215: 31706
F216: -1.0260127 | G216: 31743
F217: -1.0274518 | G217: 31752
F218: -1.0286097 | G218: 31733
F219: -1.0301205 | G219: 31770
F220: -1.0309854 | G220: 31738
F221: -1.033228 | G221: 30661
F222: -1.0341532 | G222: 31729
F223: -1.038378 | G223: 31748
F224: -1.0402606 | G224: 31719
... F348: -1.546432 | G348: 31320

Sheet Vinyl
A1: THESE ROWS AND COLUMNS WILL BE HIDDEN - They contain update notes and information for lookup calculations
F2: SELECT Material | G2: Vinyl | I2: Hide these rows, used for lookup formulas
F3: Sheet name | G3: =MID(CELL("filename",A1),FIND("]",CELL("filename",A1))+1,255) -> Vinyl
F4: Workbook name | G4: =MID(CELL("filename",A1),FIND("[",CELL("filename",A1))+1,FIND("]", CELL("filename",A1))-FIND("[",CELL("filename",A1))-1) -> ICE DB Educational V4.1 - Oct 2025.xlsx
B6: Edit Title Manually | F6: Material Profile: Vinyl
F7: ICE DB Version: | G7: =Miscellaneous!$E$3 -> V4.1 - Oct 2025 | J7: Check this link to see when the material profile was last updated
F8: To access this material profile, please register and download the Advanced version for free, with the link below:
F9: http://www.circularecology.com/embodied-energy-and-carbon-footprint-database.html
B10: Update URL Manually | F10: For further information on this material, please visit this page: | H10: INSERT LINK TO WEBPAGE…
F119: The below will be deleted before sending externally
F121: NOTES: Check the slicers are on the correct materials | I121: All Data Points Pivot Tables | L121: All Data Points Pivot Tables | R121: All Data Points Pivot Tables | Y121: All Data Points Pivot Tables | AG121: Reference Lookup Pivot Table
F123: Number 1 | G123: =#REF! -> #REF! | I123: Number 2 | J123: =#REF! -> #REF! | L123: Number 3 | M123: =#REF! -> #REF! | O123: Number 4 | P123: =#REF! -> #REF! | R123: Number 5 | S123: =#REF! -> #REF! | U123: Number 6 | V123: =#REF! -> #REF! | X123: Number 7 | Y123: =#REF! -> #REF! | AA123: Number 8 | AB123: =#REF! -> #REF!
F135: Paste below per kg Embodied Carbon | I135: Paste below per kg Embodied Carbon | L135: Paste below per kg Embodied Carbon | O135: Paste below per kg Embodied Carbon | R135: Paste below per kg Embodied Carbon | U135: Paste below per kg Embodied Carbon | X135: Paste below per kg Embodied Carbon | AA135: Paste below per kg Embodied Carbon | AF135: Paste below reference numbers, filtered by this material
B136: Headers in this row | F136: Per kg. Embodied Carbon (kg CO2/kg) | G136: Data Point Number | I136: Per kg. Embodied Carbon (kg CO2/kg) | J136: Data Point Number | L136: Per kg. Embodied Carbon (kg CO2/kg) | M136: Data Point Number | O136: Per kg. Embodied Carbon (kg CO2/kg) | P136: Data Point Number | R136: Per kg. Embodied Carbon (kg CO2/kg) | S136: Data Point Number | AF136: Row Labels
B137: Start data from this row | F137: 3.6507937 | G137: 41134 | I137: 3.6507937 | J137: 41134 | L137: 3.3758 | M137: 49800 | AF137: 2124
F138: 3.626875 | G138: 32767 | I138: 3.626875 | J138: 32767 | L138: 3.3412888 | M138: 41612 | AF138: 2188
F139: 3.5324232 | G139: 55072 | I139: 3.5324232 | J139: 55072 | L139: 3.2166667 | M139: 42410 | AF139: 2189
F140: 3.5324232 | G140: 32441 | I140: 3.5324232 | J140: 32441 | L140: 2.9812834 | M140: 42794 | AF140: 2190
F141: 3.5324232 | G141: 32442 | I141: 3.5324232 | J141: 32442 | L141: 2.8270782 | M141: 44350 | AF141: 2191
F142: 3.5294118 | G142: 41021 | I142: 3.5294118 | J142: 41021 | L142: 2.8270782 | M142: 39141 | AF142: 2218
F143: 3.3758 | G143: 49800 | I143: 3.3545455 | J143: 40617 | L143: 2.7338061 | M143: 48142 | AF143: 2224
F144: 3.3545455 | G144: 40617 | I144: 3.2977099 | J144: 32880 | L144: 2.7211268 | M144: 66723 | AF144: 2226
F145: 3.3412888 | G145: 41612 | I145: 3.236246 | J145: 41618 | L145: 2.6595745 | M145: 41883 | AF145: 2227
F146: 3.2977099 | G146: 32880 | I146: 3.1746032 | J146: 41022 | L146: 2.5641026 | M146: 43643 | AF146: 2465
F147: 3.236246 | G147: 41618 | I147: 3.1651515 | J147: 32764 | L147: 2.5177305 | M147: 52705 | AF147: 2507
F148: 3.2166667 | G148: 42410 | I148: 3.1363636 | J148: 55972 | L148: 2.4787363 | M148: 43713 | AF148: 2508
F149: 3.1746032 | G149: 41022 | I149: 3.1010874 | J149: 32873 | L149: 2.4787363 | M149: 43710 | AF149: 2509
... F242: 2.1778584 | G242: 45327 | I242: 0.63094034 | J242: 43544 | L242: 1.5984148 | M242: 50392 | AF242: 13142
F243: 2.163662 | G243: 43550 | L243: 1.5953608 | M243: 49974 | AF243: 13143
F244: 2.1633803 | G244: 54863 | L244: 1.5768966 | M244: 48739 | AF244: 13145
F245: 2.1553645 | G245: 44331 | L245: 1.5625 | M245: 41902 | AF245: 13618
F246: 2.1540911 | G246: 31938 | L246: 1.5612245 | M246: 43740 | AF246: 13622
F247: 2.145 | G247: 45469 | L247: 1.555938 | M247: 32484 | AF247: 13626
F248: 2.1117166 | G248: 51059 | L248: 1.5309842 | M248: 43714 | AF248: 13639
F249: 2.1117166 | G249: 56214 | L249: 1.5155131 | M249: 43741 | AF249: 13646
F250: 2.0858896 | G250: 44488 | L250: 1.5094664 | M250: 32483 | AF250: 16492
F251: 2.0749354 | G251: 33399 | L251: 1.5094664 | M251: 45718 | AF251: 16511
F252: 2.0669136 | G252: 45155 | L252: 1.5094664 | M252: 41498 | AF252: 16621
F253: 2.0413793 | G253: 32885 | L253: 1.505618 | M253: 54108 | AF253: 17433
F254: 2.0234292 | G254: 43585 | L254: 1.4955556 | M254: 46240 | AF254: 18091
... F302: 1.71875 | G302: 42391 | L302: 1.1584158 | M302: 41913 | AF302: 28955
F303: 1.7152582 | G303: 62223 | L303: 0.80120482 | M303: 55647
F304: 1.7142857 | G304: 41439 | L304: 0.75473322 | M304: 48236
F305: 1.7142857 | G305: 41910 | L305: 0.70912951 | M305: 55646
F306: 1.7111111 | G306: 42896 | L306: 0.50213371 | M306: 48240
F307: 1.7021277 | G307: 57081 | L307: 0.50071124 | M307: 53352
F308: 1.6944444 | G308: 39254
F309: 1.6935484 | G309: 62241
F310: 1.6875 | G310: 43705
F311: 1.6875 | G311: 43742
F312: 1.6875 | G312: 44217
F313: 1.6649306 | G313: 41280
F314: 1.6649306 | G314: 52637
F315: 1.6649306 | G315: 52638
F316: 1.6649306 | G316: 52639
F317: 1.6649306 | G317: 57168
F318: 1.6632653 | G318: 44406
F319: 1.6581892 | G319: 43744
... F413: 0.50071124 | G413: 53352

Sheet >> Misc >>
E6: Miscellanous Information >>>

Sheet References ICE V2
E3: Discuss what is needed here - keep?
E6: References from ICE V2.0
E8: The references from ICE V2.0 are presented below. They may be referred to in this file, for any data that is from ICE V2.0. The references for ICE V3.0 onwards have been moved to the material profiles. This allows users to better understand which references are applicable to each material.
E10: Ref No. | F10: Title | G10: Author | H10: Year | I10: Organisation/Publisher | J10: ISBN
E11: 1 | F11: A comparative Environmental Life Cycle Assessment of Modern Office Buildings | G11: K J Eaton & A Amato | H11: 1998 | I11: The Steel Construction Institute | J11: 1859420583
E12: 2 | F12: A comparative LCA of building insulation products made of stone wool, paper wool and flax | G12: Anders Schmidt, Allan Jensen et al. | H12: 2004 | I12: International Journal of LCA
E13: 3 | F13: A Comparison of the Embodied and operational Environmental impacts of insulation in Office Buildings | G13: Mark Lucuik | H13: 2005 | I13: 10th Canadian Conference on Building Science and Technology, Ottawa, May 2005
E14: 4 | F14: A decision making matrix with life cycle perspective of materials for roofs in Sri Lanka | G14: U G Yasantha Abeysundra, Sandhya Babel, Shabbir Gheewala | H14: 2006 | I14: Materials and Design 2006, article in press, doi:10.1016/j.matdes.2006.09.011
E15: 5 | F15: A life cycle analysis of the environmental impacts of asphalt and concrete roads | G15: Gianni Pontarollo & Tim Smith | H15: 2001 | I15: IRF world road congress 2001
E16: 6 | F16: A life cycle assessment and evaluation of construction and demolition waste | G16: Amelia Craighill & Jane Powell | H16: 1999 | I16: The Centre for Social and Economic Research on the Global Environment (CSERGE)
E17: 7 | F17: A material flow analysis and an ecological footprint of the southeast region, chapter 3 | G17: John Barrett et al | H17: 2002 | I17: Taking stock, Biffaward
E18: 8 | F18: Acrylonitrile-Butadiene-Styrene Copolymer (ABS) LCI Data Summary | G18: I Boustead | H18: 2005 | I18: APME, Association of Plastics Manufacturers in Europe
E19: 9 | F19: Acrylonitrile-Butadiene-Styrene Copolymer (ABS) LCI Data Summary in Excel Format | G19: I Boustead | H19: 2005 | I19: APME, Association of Plastics Manufacturers in Europe
E20: 10 | F20: Aluminium applications and society, paper 1 automotive, expanded summary | G20: International primary aluminium institute | H20: 2000 | I20: International primary aluminium institute
E21: 11 | F21: An ecological assessment of the vernacular architecture and of its embodied energy in Yunnan, China | G21: Wang Renping, Cai Zhenyu | H21: 2006 | I21: Building and environment 41, 2006, pg 687-697
E22: 12 | F22: An energy life cycle assessment model for building design | G22: Jorn Dinesen & Steen Traberg-Borup | H22: 1994 | I22: Danish Building research institute (SBI). Proceedings of the CIB conference on buildings and the environment.
E23: 13 | F23: An environmental comparison of bridge forms | G23: D Collings | H23: 2006 | I23: Bridge Engineering, 159, December 2006, Issue BE4, Pg 163-168
... E33: 23 | F33: Building energy performance: A LCA case study of kenaf-fibres insulation board | G33: Fulvio Ardente, Marco Beccali, Maurizio Cellura, Marina Mistretta | H33: 2008 | I33: Energy and Buildings 40 (2008) 1–10
E34: 24 | F34: Building materials energy and the environment: Towards ecologically sustainable development | G34: Bill Lawson | H34: 1996 | I34: The Royal Australian Institute of Architects | J34: 1863180230
E35: 25 | F35: Building Research Establishment (BRE) environmental profiles - Clay tiles | G35: Building Research Establishment (BRE) | H35: 1996 | I35: Building Research Establishment (BRE)
E36: 26 | F36: Building Research Establishment (BRE) Environmental profiles - Glass wool | G36: Building Research Establishment (BRE) | H36: 1999 | I36: Building Research Establishment (BRE)
E37: 27 | F37: Building Research Establishment (BRE) environmental profiles - UK kiln dried timber (softwood) | G37: Building Research Establishment (BRE) | H37: 1996 | I37: Building Research Establishment (BRE)
E38: 28 | F38: Building the Environmental Performance of UK Forest Products into Construction | G38: J S Mundy and P W Bonfield | H38: 2000 | I38: BRE
E39: 29 | F39: Bulk polymerised PVC LCI Data Summary | G39: I Boustead | H39: 1999 | I39: APME, Association of Plastics Manufacturers in Europe
E40: 30 | F40: Bulk polymerised PVC LCI Data Summary in Excel | G40: I Boustead | H40: 1999 | I40: APME, Association of Plastics Manufacturers in Europe
E41: 31 | F41: Ceramic Floor and Wall Tile: An Ecological Building Material | G41: Giorgio Timellini, Carlo Palmonari & Alberto Fregni | H41: 2005 | I41: Tile Today, Issue 46
E42: 32 | F42: Characterization of automotive paints: an environmental impact analysis | G42: Stella Papasavva, Sheila Kia, Joseph Claya, Raymond Gunther | H42: 2001 | I42: Progress in Organic Coatings 43 (2001) 193–206
E43: 33 | F43: CIBSE Guide A: Environmental Design | G43: Chartered institute of Building Service Engineers (CIBSE) | H43: 2006 | I43: Chartered institute of Building Service Engineers (CIBSE) | J43: 1903287669
E44: 34 | F44: Closing Carbon Cycles, Chapter 4 - Gross energy requirements (GER) and gross CO2 emissions for products of the organic chemical industry | G44: Martin Patel, E Jochem | H44: 1999 | I44: Utrecht university, The Netherlands
E45: 35 | F45: CO2 emissions of the Swedish steel industry | G45: Hans Sandberg, Rune Lagneborg et al | H45: 2001 | I45: Scandinavian Journal of Metallurgy
E46: 36 | F46: Comparative analysis of available life cycle inventories of cement in the EU | G46: Alejandro Josa, Antonio Aguado, Atte Heino, Ewan Byars and Arnaldo Carmin | H46: 2002 | I46: Cement and concrete journal 34 (2004) published by Peragmon, Elsevier
E47: 37 | F47: Comparative Analysis of Embodied Energy Rates for Walling Elements in India | G47: P S Chani, Najamuddin & S K Kaushik | H47: 2003 | I47: Journal of the Institution of Engineers (India)
E48: 38 | F48: Comparative energy evaluation of plastic products and their alternatives for the building and construction and transportation industries | G48: Franklin Associates | H48: 1991 | I48: The Society of the plastics industry
E49: 39 | F49: Comparative environmental life cycle assessment of composite materials | G49: O M De Vegt & W G Haije | H49: 1997 | I49: unknown, reference number ECN-I-97-050
E50: 40 | F50: Comparative Life Cycle Assessment of Flooring Materials: Ceramic versus Marble Tile | G50: Giuseppe M. Nicoletti a, Bruno Notarnicola & Giuseppe Tassielli | H50: 2000 | I50: Journal of Cleaner Production; 10, 2002, pg 283-296
E51: 41 | F51: Comparative Life Cycle Assessment of Three Insulation Materials: Stone Wool, Flax and Paper Wool | G51: Anders Schmidt, Anders Ulf Clausen, Allan Astrup Jensen, and Ole Kamstrup | H51: 2003 | I51: LCA Documents 8, Eco-Informa Press | J51: 3-928379-60-7
E52: 42 | F52: Comparing energy use and environmental emissions of reinforced wood doors and steel doors | G52: Lynn knight, Melissa Huff, Janet I Stockhausen & Robert J Ross | H52: 2005 | I52: Forest Products Journal, June 2005, Vol 55, No 6
E53: 43 | F53: Comparison of environmental impacts of two residential heating systems | G53: Lijun Yang, Radu Zmeureanu & Huges Rivard | H53: 2007 | I53: Article in Press, Building and Environment, doi:10.1016/j.buildenv.2007.02.007
E54: 44 | F54: Concrete building blocks made with recycled demolition aggregate | G54: M N Soutsos, S G Millard, J H Bungey | H54: 2006 | I54: Concrete Plant International, August 2006
E55: 45 | F55: Concrete with Ceramic Waste Aggregate | G55: R M Senthamarai and P Devadas Manoharan | H55: 2005 | I55: Cement & Concrete Composites
E56: 46 | F56: Confederation of paper industries web address: http://www.paper.org.uk/ | G56: Confederation of paper industries | H56: 2005 | I56: Confederation of the paper industries
E57: 47 | F57: Conservation of energy and natural resources by recycling building waste | G57: C Thormark | H57: 2001 | I57: Resources Conservation & Recycling
E58: 48 | F58: Conversion processes for polyolefin's | G58: I Boustead | H58: 2003 | I58: APME, Association of Plastics Manufacturers in Europe
E59: 49 | F59: Copper Environmental Profile | G59: Kennecott Utah Copper Corporation | H59: 2004 | I59: Kennecott Utah Copper Corporation
E60: 50 | F60: Cradle-to-Gate Study of Red Clay for Use in the Ceramic Industry | G60: María-Dolores Bovea, Úrsula Saura, Jose Luis Ferrero and Josep Giner | H60: 2007 | I60: International Journal of LCA 12 (6) 439 – 447. DOI: http://dx.doi.org/10.1065/lca2006.06.252
E61: 51 | F61: Data needed for environmental assessment of building projects | G61: Hanne Krogh and klaus Hansen | H61: 1994 | I61: Danish Building research institute (SBI). Proceedings of the CIB conference on buildings and the environment.
E62: 52 | F62: Defining and Improving Environmental Performance in the Concrete Industry | G62: D Higgins, L Parrott & L Sear | H62: 2000 | I62: DETR & UK Concrete Alliance
E63: 53 | F63: ECFA Environmental Declaration Plasticising Admixtures | G63: ECFA - European Federation of Concrete Admixture Association | H63: 2006 | I63: ECFA - European Federation of Concrete Admixture Association
E64: 54 | F64: Ecohouse 2: A Design Guide | G64: Sue Roaf, Manuel Fuentes & Stephanie Thomas | H64: 2003 | I64: Architectural Press (Elsevier) | J64: 750657340
E65: 55 | F65: Ecology of Building Materials | G65: Bjorn Berge | H65: 2000 | I65: Architectural press | J65: 750633948
E66: 56 | F66: ECO-Profiles of the European Plastics Industry, Methodology | G66: I Boustead | H66: 2003 | I66: APME, Association of Plastics Manufacturers in Europe
E67: 57 | F67: EEE: A prototype tool for the evaluation of embodied energy and greenhouse gas emissions of exterior envelope of Canadian houses | G67: Rym Baouendi, Radu Zmeureanu, Brian Bradley & Avi Friedman | H67: 2002 | I67: Centre for Building Studies, Department of Building, Civil and Environmental Engineering, Concordia University, Montreal, Quebec, Canada
E68: 58 | F68: Embodied CO2 of factory made cements and combinations, fact sheet 18 (P2) | G68: Chris Clear, Denis Higgins and Lindon Sear | H68: 2009 | I68: British Cement Association (BCA)
E69: 59 | F69: Embodied CO2 of UK cement, additions and cementitious material, fact sheet 18 (P1) | G69: Chris Clear, Denis Higgins and Lindon Sear | H69: 2009 | I69: British Cement Association (BCA)
E70: 60 | F70: Embodied energy - detailed methodology | G70: Tim Grant at the Centre for Design at RMIT | H70: 2001 | I70: Centre for Design RMIT University Australia
E71: 61 | F71: Embodied energy analysis of New Zealand building materials | G71: Alcorn and Baird | H71: 1996 | I71: Embodied Energy - The Current State of Play, Deakin University, Nov 1996
E72: 62 | F72: Embodied energy and carbon dioxide emissions for building materials | G72: John West, Carol Atkinson & Nigel Howard | H72: 1994 | I72: Proceedings of the CIB conference on buildings and the environment, BRE
E73: 63 | F73: Embodied Energy and CO2 Coefficients for NZ Building Materials | G73: Andrew Alcorn | H73: 2003 | I73: Centre for Building Performance Research, Victoria University of Wellington
E74: 64 | F74: Embodied Energy and CO2 Emissions of Wood and Concrete Framed Buildings in Sweden | G74: L Gustavsson & R Sathre | H74: 2004 | I74: Ecotechnology, Mid-Sweden university
E75: 65 | F75: Embodied Energy Coefficients of Building Materials | G75: Andrew Alcorn | H75: 1996 | I75: Centre for Building Performance Research, Victoria University of Wellington
E76: 66 | F76: Embodied energy in buildings: Wood versus concrete - reply to Borjesson and Gustavsson | G76: M Lenzen and G Treloar | H76: 2002 | I76: Energy Policy 30, 2002, 249-255
E77: 67 | F77: Embodied energy of common and alternative building materials and technologies | G77: B V Venkaarama Reddy & K S Jagadish | H77: 2001 | I77: Energy and buildings, Elsevier
E78: 68 | F78: Energy Analysis | G78: Edited by John A G Thomas | H78: 1977 | I78: IPC science Press Technology | J78: 902852604
E79: 69 | F79: Energy and environmental impact analysis of double-glazed windows | G79: G Weir and T Muneer | H79: 1996 | I79: Napier university
E80: 70 | F80: Energy consumption and associated greenhouse gas emissions related to maintenance of a residential structure | G80: Paul Winistorfer & Zhangjing Chen | H80: 2004 | I80: CORRIM
E81: 71 | F81: Energy consumption of asphalt and reinforced concrete pavement materials and construction | G81: Pablo Zapata & John Gambatese | H81: 2005 | I81: Journal of infrastructure systems, March 2005
E82: 72 | F82: Energy Performance of buildings | G82: George Baird, Michael R Donn | H82: 1984 | I82: CRC Press Inc. | J82: 849351863
E83: 73 | F83: Energy use during the life cycle of buildings: a method | G83: K Adalberth | H83: 1997 | I83: Building and environment, Vol 32, No. 4, pg 317-320
E84: 74 | F84: Environmental assessment of bio-based polymers and natural fibres | G84: Martin Patel, Catia Bastioli et al | H84: 2003 | I84: Unknown
E85: 75 | F85: Environmental Assessment of Brick Production in Greece | G85: Christopher Koroneos & Aris Dompros | H85: 2006 | I85: Bulding and Environment 42, 2007, Pg 2114-2123
E86: 76 | F86: Environmental Benefits of Recycling - An international Review of Life Cycle Comparisons for Key Materials in the UK Recycling Sector | G86: WRAP - Waste Resources Action Programme | H86: 2006 | I86: WRAP - Waste Resources Action Programme
E87: 77 | F87: Environmental burdens of concrete and concrete products | G87: Sirje Vares & Tarja Häkkinen | H87: 1998 | I87: Technical Research Centre of Finland, VTT Building Technology
E88: 78 | F88: Environmental declaration of the VELFAC 200 window system according to the LCA principle (EDIP method) | G88: Velfac | H88: 2006 | I88: Teknologisk Institut (The Danish Technological Institute)
E89: 79 | F89: Environmental Declaration, Nordic Timber Industry, ND Security Window | G89: Nr 310181/1- Norwegian Institute of Wood Technology | H89: 2001
E90: 80 | F90: Environmental Fact Sheet - Elevator system Schindler 3100/3300/5300 | G90: QP 04017, Schindler | H90: 2005
E91: 81 | F91: Environmental Fact Sheet - Elevator system Schindler 7000 | G91: QP 03060, Schindler | H91: 2003
E92: 82 | F92: Environmental impact of building and construction materials, Volume B: Mineral products | G92: R Clough and R Martyn | H92: 1995 | I92: CIRIA, Construction Industry Research and Information Association | J92: 860178129
E93: 83 | F93: Environmental impact of building and construction materials, Volume C: Metals | G93: N Howard | H93: 1995 | I93: CIRIA, Construction Industry Research and Information Association | J93: 860178137
E94: 84 | F94: Environmental impact of building and construction materials, Volume D: Plastics and elastomers | G94: R Clough and R Martyn | H94: 1995 | I94: CIRIA, Construction Industry Research and Information Association | J94: 860178145
E95: 85 | F95: Environmental impact of building and construction materials, Volume E: Timber and timber products | G95: J Newton and R Venables | H95: 1995 | I95: CIRIA, Construction Industry Research and Information Association | J95: 860178153
E96: 86 | F96: Environmental impact of building and construction materials, Volume F: Paints and coatings, adhesives and sealants | G96: R Bradley, A Griffiths and M Levitt | H96: 1995 | I96: CIRIA, Construction Industry Research and Information Association | J96: 860178161
E97: 87 | F97: Environmental Impact of Coated Exterior Wooden Cladding | G97: Tarja Häkkinen, Pirjo Ahola, Leila Vanhatalo, Arja Merra | H97: 1999 | I97: VTT Building Technology
E98: 88 | F98: Environmental Impact of producing hardwood lumber using life-cycle inventory | G98: Richard D Bergman, Scott A Bowe | H98: 2008 | I98: Wood and Fibre Science, 40(3). Pp 448-458
E99: 89 | F99: Environmental LCI data for Rockwool Rollbatt | G99: Price Waterhouse Coopers, PWC | H99: 2003 | I99: Price Waterhouse Coopers, PWC
E100: 90 | F100: Environmental Performance Evaluation of Thermal Insulation Materials and its Impact on the Building | G100: A M Papadopoulos & E Giama | H100: 2006 | I100: Building and Environment, Article in Press, doi:10.1016/j.buildenv.2006.04.012
E101: 91 | F101: Environmental Product Declaration (ISO DIS 21 930) Glasal | G101: Etex - Glasal | H101: 2007
E102: 92 | F102: Environmental Product Declaration for Steel Roof Cladding using Colorcoat HPS200 | G102: Corus | H102: 2005
E103: 93 | F103: Environmental product declaration of raw and melamine faced wood particleboard | G103: SAIB S.p.A, Italy | H103: 2007
E104: 94 | F104: Environmental Resource guide | G104: Joseph A Demkin | H104: 1997 | I104: AIA, American institute of Architects | J104: 471140430
E105: 95 | F105: Environmental, economic and social analysis of materials for doors and windows in Sri Lanka | G105: U G Yasantha Abeysundra, Sandhya Babel, Shabbir Gheewala & Alice Sharp | H105: 2006 | I105: Building and Environment 42, 2007, Pg 2141-2149
E106: 96 | F106: Environmental, Health, and Safety Guidelines for Cement and Lime Manufacturing | G106: International Finance Corporation, World Bank Group | H106: 2007 | I106: World Bank Group
E107: 97 | F107: Epoxy resin LCI Data Summary | G107: I Boustead | H107: 1999 | I107: APME, Association of Plastics Manufacturers in Europe
E108: 98 | F108: Epoxy resin LCI Data Summary in excel format | G108: I Boustead | H108: 1999 | I108: APME, Association of Plastics Manufacturers in Europe
E109: 99 | F109: Estimate of energy consumption and CO2 emission associated with the production, use and final disposal of sheets made of PVC-P, MDPE and bituminous materials | G109: José María Baldasano Recio, María Gonçalves Ageitos, Pedro Jiménez Guerrero | H109: 2005 | I109: Universitat Politecnica de Catalunya
E110: 100 | F110: Estimating the embodied energy of timber building products | G110: Stephen Pullen | H110: 2000 | I110: Journal of the institute of Wood Science, Vol 15 No.3, 2000
E111: 101 | F111: EU ETS Phase II Benchmarks Supporting Documentation: Ceramics | G111: Enviros Consulting Limited | H111: 2006 | I111: Enviros Consulting Limited
E112: 102 | F112: European Database for Corrugated Board Life Cycle Studies | G112: FEFCO European Federation of Corrugated Board Manufacturers, & GEO & ECO | H112: 2006 | I112: FEFCO European Federation of Corrugated Board Manufacturers, & GEO & ECO
E113: 103 | F113: Eurostrand - Oriented Strand Board (OSB) - Environmental Product Declaration | G113: Institut Bauen und Umwelt -German Institute of Construction and Environment | H113: 2005 | I113: Declaration number: AUB-EHW-10305-E
E114: 104 | F114: Evaluate the whole life environmental impact of glass in a fully glazed commercial building | G114: Mohamed R Kiani, Andrew Miller et al | H114: 2005 | I114: University of Brighton
E115: 105 | F115: Evaluation of building environmental impacts: Two case studies | G115: Stephen Carpenter & John Kokko | H115: 1996 | I115: ASHRAE transactions
...

Sheet >> Hidden >>
E6: Miscellanous Information >>>

Sheet Miscellaneous
D2: Expiry date | E2: 47057 | G2: 43676
D3: ICE DB Version Number | E3: V4.1 - Oct 2025 | G3: 43585
D7: In-SituConcList | E7: EC - kg CO2e per m3 | G7: Full In-SituConcList | H7: EC - kg CO2e per m3 | I7: EC - kg CO2e per kg | J7: Density
D8: Concrete, average UK mix | E8: 246 | G8: Concrete, average UK mix | H8: 246 | I8: 0.10336134 | J8: 2380
D9: Concrete GEN0 with CEM I cement | E9: 154.64828 | G9: Concrete GEN0 with CEM I cement | H9: 154.64828 | I9: 0.065252437 | J9: 2370
D10: Concrete GEN1 with CEM I cement | E10: 212.97226 | G10: Concrete GEN1 with CEM I cement | H10: 212.97226 | I10: 0.089861714 | J10: 2370
D11: Concrete GEN 2 with CEM I cement | E11: 229.91638 | G11: Concrete GEN 2 with CEM I cement | H11: 229.91638 | I11: 0.097011133 | J11: 2370
